Workbook

Sheet Aggregate_Efficiency_BAU
A1: Scenarios - BAU 2025-2050
A2: Year | C2: 2017 | D2: 2018 | E2: 2019 | F2: 2020 | G2: 2021 | H2: 2022 | I2: 2023 | J2: 2024 | K2: 2025 | L2: 2026 | M2: 2027 | N2: 2028 | O2: 2029 | P2: 2030 | Q2: 2031 | R2: 2032 | S2: 2033 | T2: 2034 | U2: 2035 | V2: 2036 | W2: 2037 | X2: 2038 | Y2: 2039 | Z2: 2040 | AA2: 2041 | AB2: 2042 | AC2: 2043 | AD2: 2044 | AE2: 2045 | AF2: 2046 | AG2: 2047 | AH2: 2048 | AI2: 2049 | AJ2: 2050
A3: Total Final exergy [TJ] | C3: 1 | D3: 1 | E3: 1 | F3: 1 | G3: 1 | H3: 1 | I3: 1 | J3: 1 | K3: 1 | L3: 1 | M3: 1 | N3: 1 | O3: 1 | P3: 1 | Q3: 1 | R3: 1 | S3: 1 | T3: 1 | U3: 1 | V3: 1 | W3: 1 | X3: 1 | Y3: 1 | Z3: 1 | AA3: 1 | AB3: 1 | AC3: 1 | AD3: 1 | AE3: 1 | AF3: 1 | AG3: 1 | AH3: 1 | AI3: 1 | AJ3: 1
A5: Share final exergy industry [-] | B5: Input | C5: 0.27142931 | D5: 0.27119604 | E5: 0.2732505 | F5: 0.28555072 | G5: 0.28462773 | H5: 0.27572585 | I5: 0.25944504 | J5: 0.25617084 | K5: 0.25289663 | L5: 0.24962243 | M5: 0.24634823 | N5: 0.24307402 | O5: 0.23979982 | P5: 0.23652561 | Q5: 0.23325141 | R5: 0.2299772 | S5: 0.226703 | T5: 0.2234288 | U5: 0.22015459 | V5: 0.21688039 | W5: 0.21360618 | X5: 0.21033198 | Y5: 0.20705778 | Z5: 0.20378357 | AA5: 0.20050937 | AB5: 0.19723516 | AC5: 0.19396096 | AD5: 0.19068675 | AE5: 0.18741255 | AF5: 0.18413835 | AG5: 0.18086414 | AH5: 0.17758994 | AI5: 0.17431573 | AJ5: 0.17104153
A6: Share final exergy transport [-] | B6: Input | C6: 0.3546432 | D6: 0.35679786 | E6: 0.36315882 | F6: 0.32899597 | G6: 0.34997126 | H6: 0.36009084 | I6: 0.372118 | J6: 0.37430883 | K6: 0.37649966 | L6: 0.37869049 | M6: 0.38088132 | N6: 0.38307215 | O6: 0.38526298 | P6: 0.38745381 | Q6: 0.38964464 | R6: 0.39183547 | S6: 0.3940263 | T6: 0.39621713 | U6: 0.39840796 | V6: 0.40059879 | W6: 0.40278962 | X6: 0.40498045 | Y6: 0.40717127 | Z6: 0.4093621 | AA6: 0.41155293 | AB6: 0.41374376 | AC6: 0.41593459 | AD6: 0.41812542 | AE6: 0.42031625 | AF6: 0.42250708 | AG6: 0.42469791 | AH6: 0.42688874 | AI6: 0.42907957 | AJ6: 0.4312704
A7: Share final exergy services [-] | B7: Input | C7: 0.11098227 | D7: 0.11418082 | E7: 0.11117733 | F7: 0.10630522 | G7: 0.10424487 | H7: 0.10934643 | I7: 0.15300365 | J7: 0.15238571 | K7: 0.15176778 | L7: 0.15114984 | M7: 0.1505319 | N7: 0.14991396 | O7: 0.14929603 | P7: 0.14867809 | Q7: 0.14806015 | R7: 0.14744222 | S7: 0.14682428 | T7: 0.14620634 | U7: 0.1455884 | V7: 0.14497047 | W7: 0.14435253 | X7: 0.14373459 | Y7: 0.14311666 | Z7: 0.14249872 | AA7: 0.14188078 | AB7: 0.14126284 | AC7: 0.14064491 | AD7: 0.14002697 | AE7: 0.13940903 | AF7: 0.1387911 | AG7: 0.13817316 | AH7: 0.13755522 | AI7: 0.13693728 | AJ7: 0.13631935
A8: Share final exergy residencial [-] | B8: Input | C8: 0.15680348 | D8: 0.15992742 | E8: 0.15925696 | F8: 0.17964943 | G8: 0.17499831 | H8: 0.16410964 | I8: 0.12335774 | J8: 0.12518344 | K8: 0.12700913 | L8: 0.12883482 | M8: 0.13066052 | N8: 0.13248621 | O8: 0.1343119 | P8: 0.1361376 | Q8: 0.13796329 | R8: 0.13978899 | S8: 0.14161468 | T8: 0.14344037 | U8: 0.14526607 | V8: 0.14709176 | W8: 0.14891746 | X8: 0.15074315 | Y8: 0.15256884 | Z8: 0.15439454 | AA8: 0.15622023 | AB8: 0.15804592 | AC8: 0.15987162 | AD8: 0.16169731 | AE8: 0.16352301 | AF8: 0.1653487 | AG8: 0.16717439 | AH8: 0.16900009 | AI8: 0.17082578 | AJ8: 0.17265148
A9: Share Final Exergy Agriculture/forestry/Fishing [-] | B9: Input | C9: 0.027798035 | D9: 0.028064646 | E9: 0.028618365 | F9: 0.032768238 | G9: 0.03372055 | H9: 0.029928558 | I9: 0.023282591 | J9: 0.022797523 | K9: 0.022312456 | L9: 0.021827389 | M9: 0.021342321 | N9: 0.020857254 | O9: 0.020372187 | P9: 0.019887119 | Q9: 0.019402052 | R9: 0.018916984 | S9: 0.018431917 | T9: 0.01794685 | U9: 0.017461782 | V9: 0.016976715 | W9: 0.016491648 | X9: 0.01600658 | Y9: 0.015521513 | Z9: 0.015036446 | AA9: 0.014551378 | AB9: 0.014066311 | AC9: 0.013581244 | AD9: 0.013096176 | AE9: 0.012611109 | AF9: 0.012126042 | AG9: 0.011640974 | AH9: 0.011155907 | AI9: 0.01067084 | AJ9: 0.010185772
A10: Share Final Exergy Energy industry own use [-] | B10: Input | C10: 0.078343711 | D10: 0.069833206 | E10: 0.06453802 | F10: 0.066730424 | G10: 0.05243729 | H10: 0.060798684 | I10: 0.068792975 | J10: 0.06915366 | K10: 0.069514345 | L10: 0.06987503 | M10: 0.070235716 | N10: 0.070596401 | O10: 0.070957086 | P10: 0.071317771 | Q10: 0.071678456 | R10: 0.072039141 | S10: 0.072399826 | T10: 0.072760512 | U10: 0.073121197 | V10: 0.073481882 | W10: 0.073842567 | X10: 0.074203252 | Y10: 0.074563937 | Z10: 0.074924622 | AA10: 0.075285308 | AB10: 0.075645993 | AC10: 0.076006678 | AD10: 0.076367363 | AE10: 0.076728048 | AF10: 0.077088733 | AG10: 0.077449418 | AH10: 0.077810104 | AI10: 0.078170789 | AJ10: 0.078531474
A12: Final exergy Industry [TJ] | B12: Computed | C12: =+C5*C$3 -> 0.27142931 | D12: =+D5*D$3 -> 0.27119604 | E12: =+E5*E$3 -> 0.2732505 | F12: =+F5*F$3 -> 0.28555072 | G12: =+G5*G$3 -> 0.28462773 | H12: =+H5*H$3 -> 0.27572585 | I12: =+I5*I$3 -> 0.25944504 | J12: =+J5*J$3 -> 0.25617084 | ... AJ12: =+AJ5*AJ$3 -> 0.17104153
A13: Final exergy Transport [TJ] | B13: Computed | C13: =+C6*C$3 -> 0.3546432 | D13: =+D6*D$3 -> 0.35679786 | E13: =+E6*E$3 -> 0.36315882 | F13: =+F6*F$3 -> 0.32899597 | G13: =+G6*G$3 -> 0.34997126 | H13: =+H6*H$3 -> 0.36009084 | I13: =+I6*I$3 -> 0.372118 | J13: =+J6*J$3 -> 0.37430883 | ... AJ13: =+AJ6*AJ$3 -> 0.4312704
A14: Final exergy Services [TJ] | B14: Computed | C14: =+C7*C$3 -> 0.11098227 | D14: =+D7*D$3 -> 0.11418082 | E14: =+E7*E$3 -> 0.11117733 | F14: =+F7*F$3 -> 0.10630522 | G14: =+G7*G$3 -> 0.10424487 | H14: =+H7*H$3 -> 0.10934643 | I14: =+I7*I$3 -> 0.15300365 | J14: =+J7*J$3 -> 0.15238571 | ... AJ14: =+AJ7*AJ$3 -> 0.13631935
A15: Final exergy Residencial [TJ] | B15: Computed | C15: =+C8*C$3 -> 0.15680348 | D15: =+D8*D$3 -> 0.15992742 | E15: =+E8*E$3 -> 0.15925696 | F15: =+F8*F$3 -> 0.17964943 | G15: =+G8*G$3 -> 0.17499831 | H15: =+H8*H$3 -> 0.16410964 | I15: =+I8*I$3 -> 0.12335774 | J15: =+J8*J$3 -> 0.12518344 | ... AJ15: =+AJ8*AJ$3 -> 0.17265148
A16: Final Exergy Agriculture/Forestry/fishing [TJ] | B16: Computed | C16: =+C9*C$3 -> 0.027798035 | D16: =+D9*D$3 -> 0.028064646 | E16: =+E9*E$3 -> 0.028618365 | F16: =+F9*F$3 -> 0.032768238 | G16: =+G9*G$3 -> 0.03372055 | H16: =+H9*H$3 -> 0.029928558 | I16: =+I9*I$3 -> 0.023282591 | J16: =+J9*J$3 -> 0.022797523 | ... AJ16: =+AJ9*AJ$3 -> 0.010185772
A17: Final Exergy Energy industry own use [TJ] | B17: Computed | C17: =+C10*C$3 -> 0.078343711 | D17: =+D10*D$3 -> 0.069833206 | E17: =+E10*E$3 -> 0.06453802 | F17: =+F10*F$3 -> 0.066730424 | G17: =+G10*G$3 -> 0.05243729 | H17: =+H10*H$3 -> 0.060798684 | I17: =+I10*I$3 -> 0.068792975 | J17: =+J10*J$3 -> 0.06915366 | ... AJ17: =+AJ10*AJ$3 -> 0.078531474
A19: Share final exergy industry electricity | B19: Input | C19: 0.2970747 | D19: 0.30075756 | E19: 0.30235708 | F19: 0.30163627 | G19: 0.30591526 | H19: 0.31318182 | I19: 0.31035417 | J19: 0.31226091 | K19: 0.31416765 | L19: 0.31607439 | M19: 0.31798114 | N19: 0.31988788 | O19: 0.32179462 | P19: 0.32370136 | Q19: 0.32560811 | R19: 0.32751485 | S19: 0.32863758 | T19: 0.32990769 | U19: 0.33117295 | V19: 0.3324334 | W19: 0.33368904 | X19: 0.33493993 | Y19: 0.33618607 | Z19: 0.33742751 | AA19: 0.33866425 | AB19: 0.33989634 | AC19: 0.34031391 | AD19: 0.34062099 | AE19: 0.34092529 | AF19: 0.34122685 | AG19: 0.3415257 | AH19: 0.34182189 | AI19: 0.34211544 | AJ19: 0.3424064
A20: Share final exergy transport electricity | B20: Input | C20: 0.0068374586 | D20: 0.0068392983 | E20: 0.0067376336 | F20: 0.0070045484 | G20: 0.0070586514 | H20: 0.0070199832 | I20: 0.0076482888 | J20: 0.0079060577 | K20: 0.0081638265 | L20: 0.0084215954 | M20: 0.0086793642 | N20: 0.0089371331 | O20: 0.0091949019 | P20: 0.0094526708 | Q20: 0.0097104396 | R20: 0.0099682085 | S20: 0.010225977 | T20: 0.010483746 | U20: 0.010741515 | V20: 0.010999284 | W20: 0.011257053 | X20: 0.011514822 | Y20: 0.01177259 | Z20: 0.012030359 | AA20: 0.012288128 | AB20: 0.012545897 | AC20: 0.012803666 | AD20: 0.013061435 | AE20: 0.013319204 | AF20: 0.013576972 | AG20: 0.013834741 | AH20: 0.01409251 | AI20: 0.014350279 | AJ20: 0.014608048
A21: Share final exergy services electricity | B21: Input | C21: 0.73677033 | D21: 0.72971057 | E21: 0.73192341 | F21: 0.7583611 | G21: 0.73914204 | H21: 0.75301205 | I21: 0.74281677 | J21: 0.7426465 | K21: 0.74247623 | L21: 0.74230596 | M21: 0.74213569 | N21: 0.74196542 | O21: 0.74179514 | P21: 0.74162487 | Q21: 0.7414546 | R21: 0.74128433 | S21: 0.74111406 | T21: 0.74094379 | U21: 0.74077351 | V21: 0.74060324 | W21: 0.73947303 | X21: 0.73855213 | Y21: 0.73763311 | Z21: 0.73671595 | AA21: 0.73580065 | AB21: 0.7348872 | AC21: 0.73397559 | AD21: 0.73306583 | AE21: 0.7321579 | AF21: 0.7312518 | AG21: 0.73034752 | AH21: 0.72944507 | AI21: 0.72854442 | AJ21: 0.72764558
A22: Share final exergy residencial electricity | B22: Input | C22: 0.40105887 | D22: 0.41096146 | E22: 0.41088932 | F22: 0.40750368 | G22: 0.42720606 | H22: 0.43001357 | I22: 0.43031559 | J22: 0.43471854 | K22: 0.43912148 | L22: 0.44352443 | M22: 0.44792737 | N22: 0.45233032 | O22: 0.45673326 | P22: 0.4611362 | Q22: 0.46553915 | R22: 0.46994209 | S22: 0.47434504 | T22: 0.47874798 | U22: 0.48315092 | V22: 0.48755387 | W22: 0.49195681 | X22: 0.49635976 | Y22: 0.5007627 | Z22: 0.50516565 | AA22: 0.50956859 | AB22: 0.51397153 | AC22: 0.51837448 | AD22: 0.52277742 | AE22: 0.52718037 | AF22: 0.53158331 | AG22: 0.53367957 | AH22: 0.53499611 | AI22: 0.53629772 | AJ22: 0.53758466
A23: Share final exergy Agriculture/forestry/Fishing electricity | B23: Input | C23: 0.17678412 | D23: 0.18850159 | E23: 0.16560611 | F23: 0.16584001 | G23: 0.17929811 | H23: 0.16275005 | I23: 0.1699724 | J23: 0.17022649 | K23: 0.17048058 | L23: 0.17073467 | M23: 0.17098875 | N23: 0.17124284 | O23: 0.17149693 | P23: 0.17175101 | Q23: 0.1720051 | R23: 0.17225919 | S23: 0.17251327 | T23: 0.17276736 | U23: 0.17302145 | V23: 0.17327553 | W23: 0.17352962 | X23: 0.17378371 | Y23: 0.1740378 | Z23: 0.17429188 | AA23: 0.17439466 | AB23: 0.17454626 | AC23: 0.17469768 | AD23: 0.17484892 | AE23: 0.17499999 | AF23: 0.17515087 | AG23: 0.17530159 | AH23: 0.17545212 | AI23: 0.17560249 | AJ23: 0.17575267
A24: Share final exergy Energy industry own electricity | B24: Input | C24: 0.20857445 | D24: 0.19412629 | E24: 0.17649312 | F24: 0.17373555 | G24: 0.18464616 | H24: 0.17476388 | I24: 0.17891093 | J24: 0.17800461 | K24: 0.1770983 | L24: 0.17619199 | M24: 0.17528568 | N24: 0.17437936 | O24: 0.17347305 | P24: 0.17256674 | Q24: 0.17166043 | R24: 0.17075411 | S24: 0.1698478 | T24: 0.16894149 | U24: 0.16803518 | V24: 0.16712886 | W24: 0.16622255 | X24: 0.16531624 | Y24: 0.16440993 | Z24: 0.16350361 | AA24: 0.1625973 | AB24: 0.16169099 | AC24: 0.16078468 | AD24: 0.15987836 | AE24: 0.15897205 | AF24: 0.15767591 | AG24: 0.15626303 | AH24: 0.1548593 | AI24: 0.15346461 | AJ24: 0.15207889
A25: Share final exergy industry coal/coke | B25: Input | C25: 0.069253404 | D25: 0.061170092 | E25: 0.059562702 | F25: 0.064743037 | G25: 0.054408395 | H25: 0.06007097 | I25: 0.052651272 | J25: 0.049897148 | K25: 0.047143024 | L25: 0.0443889 | M25: 0.041634776 | N25: 0.038880651 | O25: 0.036126527 | P25: 0.033372403 | Q25: 0.030618279 | R25: 0.027864155 | S25: 0.025050269 | T25: 0.02226005 | U25: 0.019480483 | V25: 0.016711505 | W25: 0.013953057 | X25: 0.011205079 | Y25: 0.0084675118 | Z25: 0.0057402957 | AA25: 0.0030233723 | AB25: 0.00031668355 | AC25: 0 | AD25: 0 | AE25: 0 | AF25: 0 | AG25: 0 | AH25: 0 | AI25: 0 | AJ25: 0
A26: Share final exergy industry oil | B26: Input | C26: 0.078378662 | D26: 0.077637821 | E26: 0.069863979 | F26: 0.070795621 | G26: 0.069265914 | H26: 0.082289434 | I26: 0.070176562 | J26: 0.068490573 | K26: 0.066804585 | L26: 0.065118597 | M26: 0.063432608 | N26: 0.06174662 | O26: 0.060060632 | P26: 0.058374643 | Q26: 0.056688655 | R26: 0.055002667 | S26: 0.053189786 | T26: 0.051409312 | U26: 0.049635634 | V26: 0.047868715 | W26: 0.046108514 | X26: 0.044354994 | Y26: 0.042608118 | Z26: 0.040867846 | AA26: 0.039134143 | AB26: 0.03740697 | AC26: 0.035601566 | AD26: 0.033800828 | AE26: 0.032016382 | AF26: 0.030248008 | AG26: 0.02849549 | AH26: 0.026758615 | AI26: 0.025037175 | AJ26: 0.023330965
A27: Share final exergy industry natural gas | B27: Input | C27: 0.27024948 | D27: 0.2755297 | E27: 0.27458465 | F27: 0.2640436 | G27: 0.29137166 | H27: 0.25694602 | I27: 0.28170259 | J27: 0.28512852 | K27: 0.28855445 | L27: 0.29198037 | M27: 0.2954063 | N27: 0.29883222 | O27: 0.30225815 | P27: 0.30568408 | Q27: 0.30911 | R27: 0.31253593 | S27: 0.31520988 | T27: 0.31801834 | U27: 0.32081607 | V27: 0.32360315 | W27: 0.32637964 | X27: 0.32914558 | Y27: 0.33190104 | Z27: 0.33464609 | AA27: 0.33738077 | AB27: 0.34010516 | AC27: 0.34200538 | AD27: 0.34378158 | AE27: 0.3455417 | AF27: 0.34728598 | AG27: 0.34901461 | AH27: 0.35072781 | AI27: 0.35242579 | AJ27: 0.35410875
A28: Share final exergy industry waste/c. renewables | B28: Input | C28: 0.26201817 | D28: 0.25876213 | E28: 0.26551584 | F28: 0.27237961 | G28: 0.25652296 | H28: 0.27022414 | I28: 0.26829567 | J28: 0.26932365 | K28: 0.27035164 | L28: 0.27137962 | M28: 0.2724076 | N28: 0.27343558 | O28: 0.27446356 | P28: 0.27549155 | Q28: 0.27651953 | R28: 0.27754751 | S28: 0.27791249 | T28: 0.27840461 | U28: 0.27889486 | V28: 0.27938323 | W28: 0.27986975 | X28: 0.28035442 | Y28: 0.28083725 | Z28: 0.28131826 | AA28: 0.28179746 | AB28: 0.28227485 | AC28: 0.28207914 | AD28: 0.28179661 | AE28: 0.28151663 | AF28: 0.28123917 | AG28: 0.2809642 | AH28: 0.28069169 | AI28: 0.28042159 | AJ28: 0.28015389
A29: Share final exergy industry heat | B29: Input | C29: 0.023025582 | D29: 0.026142703 | E29: 0.028115736 | F29: 0.026401859 | G29: 0.022515809 | H29: 0.017287611 | I29: 0.016819733 | J29: 0.014899195 | K29: 0.012978657 | L29: 0.011058119 | M29: 0.0091375808 | N29: 0.0072170427 | O29: 0.0052965046 | P29: 0.0033759665 | Q29: 0.0014554284 | R29: -0.0004651097 | S29: 0 | T29: 0 | U29: 0 | V29: 0 | W29: 0 | X29: 0 | Y29: 0 | Z29: 0 | AA29: 0 | AB29: 0 | AC29: 0 | AD29: 0 | AE29: 0 | AF29: 0 | AG29: 0 | AH29: 0 | AI29: 0 | AJ29: =+AI29*(1-AJ$19)/(1-AI$19) -> 0
A30: Share final exergy transport coal/coke | B30: Input | C30: 0 | D30: 0 | E30: 0 | F30: 0 | G30: 0 | H30: 0 | I30: 0 | J30: 0 | K30: 0 | L30: 0 | M30: 0 | N30: 0 | O30: 0 | P30: 0 | Q30: 0 | R30: 0 | S30: 0 | T30: 0 | U30: 0 | V30: 0 | W30: 0 | X30: 0 | Y30: 0 | Z30: 0 | AA30: 0 | AB30: 0 | AC30: 0 | AD30: 0 | AE30: 0 | AF30: 0 | AG30: 0 | AH30: 0 | AI30: 0 | AJ30: 0
A31: Share final exergy transport oil | B31: Input | C31: 0.94650317 | D31: 0.94323568 | E31: 0.94252362 | F31: 0.93788625 | G31: 0.92726817 | H31: 0.92771702 | I31: 0.93231343 | J31: 0.93126882 | K31: 0.93022422 | L31: 0.92917962 | M31: 0.92813502 | N31: 0.92709042 | O31: 0.92604581 | P31: 0.92500121 | Q31: 0.92395661 | R31: 0.92291201 | S31: 0.92186741 | T31: 0.9208228 | U31: 0.9197782 | V31: 0.9187336 | W31: 0.917689 | X31: 0.9166444 | Y31: 0.91559979 | Z31: 0.91455519 | AA31: 0.91351059 | AB31: 0.91246599 | AC31: 0.91142139 | AD31: 0.91037678 | AE31: 0.90933218 | AF31: 0.90828758 | AG31: 0.90724298 | AH31: 0.90619838 | AI31: 0.90515377 | AJ31: 0.90410917
A32: Share final exergy transport natural gas | B32: Input | C32: 0.0025002831 | D32: 0.0026990588 | E32: 0.0028751385 | F32: 0.0039454464 | G32: 0.0042923769 | H32: 0.0055594064 | I32: 0.0047571423 | J32: 0.0050449742 | K32: 0.0053328061 | L32: 0.0056206379 | M32: 0.0059084698 | N32: 0.0061963017 | O32: 0.0064841335 | P32: 0.0067719654 | Q32: 0.0070597972 | R32: 0.0073476291 | S32: 0.007635461 | T32: 0.0079232928 | U32: 0.0082111247 | V32: 0.0084989566 | W32: 0.0087867884 | X32: 0.0090746203 | Y32: 0.0093624521 | Z32: 0.009650284 | AA32: 0.0099381159 | AB32: 0.010225948 | AC32: 0.01051378 | AD32: 0.010801611 | AE32: 0.011089443 | AF32: 0.011377275 | AG32: 0.011665107 | AH32: 0.011952939 | AI32: 0.012240771 | AJ32: 0.012528603
A33: Share final exergy transport c. renewables/waste | B33: Input | C33: 0.044159087 | D33: 0.047225959 | E33: 0.047863611 | F33: 0.051163753 | G33: 0.061380802 | H33: 0.059703595 | I33: 0.055281142 | J33: 0.055780143 | K33: 0.056279145 | L33: 0.056778146 | M33: 0.057277147 | N33: 0.057776149 | O33: 0.05827515 | P33: 0.058774151 | Q33: 0.059273152 | R33: 0.059772154 | S33: 0.060271155 | T33: 0.060770156 | U33: 0.061269158 | V33: 0.061768159 | W33: 0.06226716 | X33: 0.062766161 | Y33: 0.063265163 | Z33: 0.063764164 | AA33: 0.064263165 | AB33: 0.064762167 | AC33: 0.065261168 | AD33: 0.065760169 | AE33: 0.06625917 | AF33: 0.066758172 | AG33: 0.067257173 | AH33: 0.067756174 | AI33: 0.068255175 | AJ33: 0.068754177
A34: Share final exergy transport heat | B34: Input | C34: 0 | D34: 0 | E34: 0 | F34: 0 | G34: 0 | H34: 0 | I34: 0 | J34: 0 | K34: 0 | L34: 0 | M34: 0 | N34: 0 | O34: 0 | P34: 0 | Q34: 0 | R34: 0 | S34: 0 | T34: 0 | U34: 0 | V34: 0 | W34: 0 | X34: 0 | Y34: 0 | Z34: 0 | AA34: 0 | AB34: 0 | AC34: 0 | AD34: 0 | AE34: 0 | AF34: 0 | AG34: 0 | AH34: 0 | AI34: 0 | AJ34: 0
A35: Share final exergy services coal/coke | B35: Input | C35: 0 | D35: 0 | E35: 0 | F35: 0 | G35: 0 | H35: 0 | I35: 0 | J35: 0 | K35: 0 | L35: 0 | M35: 0 | N35: 0 | O35: 0 | P35: 0 | Q35: 0 | R35: 0 | S35: 0 | T35: 0 | U35: 0 | V35: 0 | W35: 0 | X35: 0 | Y35: 0 | Z35: 0 | AA35: 0 | AB35: 0 | AC35: 0 | AD35: 0 | AE35: 0 | AF35: 0 | AG35: 0 | AH35: 0 | AI35: 0 | AJ35: 0
A36: Share final exergy services oil | B36: Input | C36: 0.077348966 | D36: 0.087056264 | E36: 0.090620219 | F36: 0.073143915 | G36: 0.066652382 | H36: 0.066249945 | I36: 0.071929211 | J36: 0.070741379 | K36: 0.069553547 | L36: 0.068365715 | M36: 0.067177884 | N36: 0.065990052 | O36: 0.06480222 | P36: 0.063614388 | Q36: 0.062426556 | R36: 0.061238724 | S36: 0.060050893 | T36: 0.058863061 | U36: 0.057675229 | V36: 0.056487397 | W36: 0.055227871 | X36: 0.053986694 | Y36: 0.052748036 | Z36: 0.051511889 | AA36: 0.050278244 | AB36: 0.049047096 | AC36: 0.047818436 | AD36: 0.046592256 | AE36: 0.045368549 | AF36: 0.044147308 | AG36: 0.042928525 | AH36: 0.041712192 | AI36: 0.040498303 | AJ36: 0.03928685
A37: Share final exergy services natural gas | B37: Input | C37: 0.13908516 | D37: 0.13780262 | E37: 0.13277494 | F37: 0.1231687 | G37: 0.14388299 | H37: 0.13039761 | I37: 0.13838598 | J37: 0.13973149 | K37: 0.14107701 | L37: 0.14242252 | M37: 0.14376803 | N37: 0.14511355 | O37: 0.14645906 | P37: 0.14780457 | Q37: 0.14915009 | R37: 0.1504956 | S37: 0.15184112 | T37: 0.15318663 | U37: 0.15453214 | V37: 0.15587766 | W37: 0.15701934 | X37: 0.15820227 | Y37: 0.1593828 | Z37: 0.16056095 | AA37: 0.1617367 | AB37: 0.16291008 | AC37: 0.16408108 | AD37: 0.16524973 | AE37: 0.16641601 | AF37: 0.16757994 | AG37: 0.16874154 | AH37: 0.16990079 | AI37: 0.17105772 | AJ37: 0.17221233
A38: Share final exergy services c. renewables/waste | B38: Input | C38: 0.019601913 | D38: 0.018216043 | E38: 0.01642892 | F38: 0.01284449 | G38: 0.016374281 | H38: 0.01770829 | I38: 0.012953268 | J38: 0.01193531 | K38: 0.010917351 | L38: 0.0098993929 | M38: 0.0088814346 | N38: 0.0078634762 | O38: 0.0068455179 | P38: 0.0058275596 | Q38: 0.0048096013 | R38: 0.003791643 | S38: 0.0027736846 | T38: 0.0017557263 | U38: 0.00073776801 | V38: -0.00028019031 | W38: 0 | X38: 0 | Y38: 0 | Z38: 0 | AA38: 0 | AB38: 0 | AC38: 0 | AD38: 0 | AE38: 0 | AF38: 0 | AG38: 0 | AH38: 0 | AI38: 0 | AJ38: 0
A39: Share final exergy services renewables | B39: Input | C39: 0.019231307 | D39: 0.019644153 | E39: 0.020836864 | F39: 0.024392322 | G39: 0.02544208 | H39: 0.025857495 | I39: 0.026444102 | J39: 0.027523279 | K39: 0.028602456 | L39: 0.029681633 | M39: 0.030760809 | N39: 0.031839986 | O39: 0.032919163 | P39: 0.03399834 | Q39: 0.035077516 | R39: 0.036156693 | S39: 0.03723587 | T39: 0.038315047 | U39: 0.039394224 | V39: 0.0404734 | W39: 0.041498706 | X39: 0.042533242 | Y39: 0.04356568 | Z39: 0.044596024 | AA39: 0.045624283 | AB39: 0.04665046 | AC39: 0.047674565 | AD39: 0.048696601 | AE39: 0.049716576 | AF39: 0.050734497 | AG39: 0.051750368 | AH39: 0.052764196 | AI39: 0.053775988 | AJ39: 0.05478575
A40: Share final exergy services heat | B40: Input | C40: 0.0079623246 | D40: 0.0075703452 | E40: 0.0074156469 | F40: 0.008089469 | G40: 0.0085062263 | H40: 0.0067746151 | I40: 0.0074706676 | J40: 0.0074220389 | K40: 0.0073734101 | L40: 0.0073247813 | M40: 0.0072761526 | N40: 0.0072275238 | O40: 0.0071788951 | P40: 0.0071302663 | Q40: 0.0070816375 | R40: 0.0070330088 | S40: 0.00698438 | T40: 0.0069357513 | U40: 0.0068871225 | V40: 0.0068384937 | W40: 0.0067810621 | X40: 0.0067256589 | Y40: 0.006670368 | Z40: 0.0066151892 | AA40: 0.0065601222 | AB40: 0.0065051666 | AC40: 0.006450322 | AD40: 0.0063955881 | AE40: 0.0063409647 | AF40: 0.0062864513 | AG40: 0.0062320476 | AH40: 0.0061777533 | AI40: 0.0061235681 | AJ40: 0.0060694916
A41: Share final exergy residencial coal/coke | B41: Input | C41: 0 | D41: 0 | E41: 0 | F41: 0 | G41: 0 | H41: 0 | I41: 0 | J41: 0 | K41: 0 | L41: 0 | M41: 0 | N41: 0 | O41: 0 | P41: 0 | Q41: 0 | R41: 0 | S41: 0 | T41: 0 | U41: 0 | V41: 0 | W41: 0 | X41: 0 | Y41: 0 | Z41: 0 | AA41: 0 | AB41: 0 | AC41: 0 | AD41: 0 | AE41: 0 | AF41: 0 | AG41: 0 | AH41: 0 | AI41: 0 | AJ41: 0
... A46: Share final exergy residencial heat | B46: Input | C46: 0.00019113704 | D46: 0.00022897677 | E46: 0.000186438 | F46: 0.00017904391 | G46: 0.00017952454 | H46: 0.00012876039 | I46: 0.00015578395 | J46: 0.00014960057 | K46: 0.00014341719 | L46: 0.00013723381 | M46: 0.00013105043 | N46: 0.00012486705 | O46: 0.00011868366 | P46: 0.00011250028 | Q46: 0.0001063169 | R46: 0.00010013352 | S46: 9.3950138e-05 | T46: 8.7766756e-05 | U46: 8.1583375e-05 | V46: 7.5399993e-05 | W46: 6.9216611e-05 | X46: 6.303323e-05 | Y46: 5.6849848e-05 | Z46: 5.0666467e-05 | AA46: 4.4483085e-05 | AB46: 3.8299703e-05 | AC46: 3.2116322e-05 | AD46: 2.593294e-05 | AE46: 1.9749559e-05 | AF46: 1.3566177e-05 | AG46: 7.3510228e-06 | AH46: 1.1874438e-06 | AI46: -4.9062574e-06 | AJ46: -1.0931262e-05
A47: Share final exergy Agriculture/Forestry/Fishing Coal/Coke | B47: Input | C47: 0 | D47: 0 | E47: 0 | F47: 0 | G47: 0 | H47: 0 | I47: =+H47*(1-I$23)/(1-H$23) -> 0 | J47: =+I47*(1-J$23)/(1-I$23) -> 0 | K47: =+J47*(1-K$23)/(1-J$23) -> 0 | L47: =+K47*(1-L$23)/(1-K$23) -> 0 | M47: =+L47*(1-M$23)/(1-L$23) -> 0 | N47: =+M47*(1-N$23)/(1-M$23) -> 0 | O47: =+N47*(1-O$23)/(1-N$23) -> 0 | P47: =+O47*(1-P$23)/(1-O$23) -> 0 | ... AJ47: =+AI47*(1-AJ$23)/(1-AI$23) -> 0
A48: Share final exergy Agriculture/Forstry/Fishing Oil | B48: Input | C48: 0.78928161 | D48: 0.78269748 | E48: 0.79580952 | F48: 0.79856739 | G48: 0.78008789 | H48: 0.80941796 | I48: 0.79982069 | J48: 0.80067586 | K48: 0.80153102 | L48: 0.80238619 | M48: 0.80324135 | N48: 0.80409652 | O48: 0.80495168 | P48: 0.80580685 | Q48: 0.80666201 | R48: 0.80751718 | S48: 0.80837234 | T48: 0.80922751 | U48: 0.81008267 | V48: 0.81093784 | W48: 0.811793 | X48: 0.81264817 | Y48: 0.81350333 | Z48: 0.8143585 | AA48: 0.81450698 | AB48: 0.81488395 | AC48: 0.81526048 | AD48: 0.81563656 | AE48: 0.81601221 | AF48: 0.81638742 | AG48: 0.81676219 | AH48: 0.81713652 | AI48: 0.81751042 | AJ48: 0.81788388
A49: Share final exergy Agriculture/Forstry/Fishing natural gas | B49: Input | C49: 0.012661806 | D49: 0.0082961791 | E49: 0.013484001 | F49: 0.013963079 | G49: 0.015486872 | H49: 0.0087150881 | I49: 0.011268208 | J49: 0.011034256 | K49: 0.010800304 | L49: 0.010566352 | M49: 0.0103324 | N49: 0.010098449 | O49: 0.0098644968 | P49: 0.009630545 | Q49: 0.0093965932 | R49: 0.0091626414 | S49: 0.0089286896 | T49: 0.0086947378 | U49: 0.0084607861 | V49: 0.0082268343 | W49: 0.0079928825 | X49: 0.0077589307 | Y49: 0.0075249789 | Z49: 0.0072910271 | AA49: 0.0070509577 | AB49: 0.0068132168 | AC49: 0.0065757541 | AD49: 0.0063385691 | AE49: 0.0061016615 | AF49: 0.0058650307 | AG49: 0.0056286762 | AH49: 0.0053925975 | AI49: 0.0051567942 | AJ49: 0.0049212657
A50: Share final exergy Agriculture/Forstry/Fishing c. renewables/Waste | B50: Input | C50: 0.0086444217 | D50: 0.012388318 | E50: 0.013887209 | F50: 0.013568177 | G50: 0.014002279 | H50: 0.0080226929 | I50: 0.0096880519 | J50: 0.0091016256 | K50: 0.0085151992 | L50: 0.0079287729 | M50: 0.0073423466 | N50: 0.0067559202 | O50: 0.0061694939 | P50: 0.0055830676 | Q50: 0.0049966412 | R50: 0.0044102149 | S50: 0.0038237886 | T50: 0.0032373622 | U50: 0.0026509359 | V50: 0.0020645095 | W50: 0.0014780832 | X50: 0.00089165687 | Y50: 0.00030523054 | Z50: -0.0002811958 | AA50: 0 | AB50: 0 | AC50: 0 | AD50: 0 | AE50: 0 | AF50: 0 | AG50: 0 | AH50: 0 | AI50: 0 | AJ50: 0
A51: Share final exergy Agriculture/Forstry/Fishing heat | B51: Input | C51: 0.012628043 | D51: 0.008116431 | E51: 0.011213164 | F51: 0.0080613482 | G51: 0.011124853 | H51: 0.011094207 | I51: 0.0092506464 | J51: 0.0089617723 | K51: 0.0086728983 | L51: 0.0083840242 | M51: 0.0080951501 | N51: 0.007806276 | O51: 0.007517402 | P51: 0.0072285279 | Q51: 0.0069396538 | R51: 0.0066507798 | S51: 0.0063619057 | T51: 0.0060730316 | U51: 0.0057841575 | V51: 0.0054952835 | W51: 0.0052064094 | X51: 0.0049175353 | Y51: 0.0046286612 | Z51: 0.0043397872 | AA51: 0.0040474015 | AB51: 0.0037565768 | AC51: 0.0034660925 | AD51: 0.003175948 | AE51: 0.0028861427 | AF51: 0.002596676 | AG51: 0.0023075474 | AH51: 0.0020187561 | AI51: 0.0017303017 | AJ51: 0.0014421836
A52: Share Final Exergy Energy industry own use Coal/Coke | B52: Input | C52: 0 | D52: 0 | E52: 0 | F52: 0 | G52: 0 | H52: 0 | I52: 0 | J52: 0 | K52: 0 | L52: 0 | M52: 0 | N52: 0 | O52: 0 | P52: 0 | Q52: 0 | R52: 0 | S52: 0 | T52: 0 | U52: 0 | V52: 0 | W52: 0 | X52: 0 | Y52: 0 | Z52: 0 | AA52: 0 | AB52: 0 | AC52: 0 | AD52: 0 | AE52: 0 | AF52: 0 | AG52: 0 | AH52: 0 | AI52: 0 | AJ52: 0
A53: Share Final Exergy Energy industry own use Oil | B53: Input | C53: 0.59862008 | D53: 0.59920454 | E53: 0.60084938 | F53: 0.59317469 | G53: 0.568324 | H53: 0.69522179 | I53: 0.62585238 | J53: 0.62879911 | K53: 0.63174583 | L53: 0.63469256 | M53: 0.63763929 | N53: 0.64058602 | O53: 0.64353275 | P53: 0.64647948 | Q53: 0.6494262 | R53: 0.65237293 | S53: 0.65531966 | T53: 0.65826639 | U53: 0.66121312 | V53: 0.66415985 | W53: 0.66710657 | X53: 0.6700533 | Y53: 0.67300003 | Z53: 0.67594676 | AA53: 0.67889349 | AB53: 0.68184021 | AC53: 0.68478694 | AD53: 0.68773367 | AE53: 0.6906804 | AF53: 0.69191649 | AG53: 0.6926008 | AH53: 0.69328069 | AI53: 0.69395619 | AJ53: 0.69462735
A54: Share Final Exergy Energy industry own use Natural Gas | B54: Input | C54: 0.081268147 | D54: 0.081522539 | E54: 0.087493827 | F54: 0.084348043 | G54: 0.10926921 | H54: 0.060417284 | I54: 0.072602115 | J54: 0.069338009 | K54: 0.066073903 | L54: 0.062809797 | M54: 0.059545692 | N54: 0.056281586 | O54: 0.05301748 | P54: 0.049753375 | Q54: 0.046489269 | R54: 0.043225163 | S54: 0.039961057 | T54: 0.036696952 | U54: 0.033432846 | V54: 0.03016874 | W54: 0.026904634 | X54: 0.023640529 | Y54: 0.020376423 | Z54: 0.017112317 | AA54: 0.013848212 | AB54: 0.010584106 | AC54: 0.0073200001 | AD54: 0.0040558944 | AE54: 0.00079178865 | AF54: 0 | AG54: 0 | AH54: 0 | AI54: 0 | AJ54: 0
A55: Share Final Exergy Energy industry own use C. Renewables/Waste | B55: Input | C55: 0 | D55: 0 | E55: 0 | F55: 0 | G55: 0 | H55: 0 | I55: 0 | J55: -1.110223e-15 | K55: -2.220446e-16 | L55: -8.8817842e-16 | M55: -8.8817842e-16 | N55: -2.220446e-16 | O55: -2.220446e-16 | P55: -8.8817842e-16 | Q55: 0 | R55: -2.220446e-16 | S55: -4.4408921e-16 | T55: -8.8817842e-16 | U55: -2.220446e-16 | V55: -2.220446e-16 | W55: -4.4408921e-16 | X55: -8.8817842e-16 | Y55: -1.110223e-15 | Z55: -4.4408921e-16 | AA55: -4.4408921e-16 | AB55: -1.110223e-15 | AC55: -2.220446e-16 | AD55: -4.4408921e-16 | AE55: -4.4408921e-16 | AF55: 0 | AG55: 0 | AH55: 0 | AI55: 0 | AJ55: 0
A56: Share Final Exergy Energy industry own use Heat | B56: Input | C56: 0.11153732 | D56: 0.12514663 | E56: 0.13516367 | F56: 0.14874172 | G56: 0.13776063 | H56: 0.069597049 | I56: 0.12263458 | J56: 0.12385827 | K56: 0.12508196 | L56: 0.12630565 | M56: 0.12752934 | N56: 0.12875303 | O56: 0.12997672 | P56: 0.13120041 | Q56: 0.1324241 | R56: 0.13364779 | S56: 0.13487148 | T56: 0.13609517 | U56: 0.13731886 | V56: 0.13854255 | W56: 0.13976624 | X56: 0.14098993 | Y56: 0.14221362 | Z56: 0.14343731 | AA56: 0.144661 | AB56: 0.14588469 | AC56: 0.14710838 | AD56: 0.14833207 | AE56: 0.14955576 | AF56: 0.1504076 | AG56: 0.15113616 | AH56: 0.15186001 | AI56: 0.15257919 | AJ56: 0.15329375
A58: Final exergy industry electricity [TJ] | B58: Computed | C58: =+C19*C12 -> 0.08063478 | D58: =+D19*D12 -> 0.081564258 | E58: =+E19*E12 -> 0.082619224 | F58: =+F19*F12 -> 0.086132456 | G58: =+G19*G12 -> 0.087071965 | H58: =+H19*H12 -> 0.086352326 | I58: =+I19*I12 -> 0.08051985 | J58: =+J19*J12 -> 0.079992139 | ... AJ58: =+AJ19*AJ12 -> 0.058565715
A59: Final exergy transport electricity [TJ] | B59: Computed | C59: =+C20*C13 -> 0.0024248582 | D59: =+D20*D13 -> 0.002440247 | E59: =+E20*E13 -> 0.0024468311 | F59: =+F20*F13 -> 0.0023044682 | G59: =+G20*G13 -> 0.0024703251 | H59: =+H20*H13 -> 0.0025278316 | I59: =+I20*I13 -> 0.0028460659 | J59: =+J20*J13 -> 0.0029593072 | ... AJ59: =+AJ20*AJ13 -> 0.0063000187
A60: Final exergy services electricity [TJ] | B60: Computed | C60: =+C21*C14 -> 0.081768445 | D60: =+D21*D14 -> 0.083318954 | E60: =+E21*E14 -> 0.081373292 | F60: =+F21*F14 -> 0.080617743 | G60: =+G21*G14 -> 0.077051763 | H60: =+H21*H14 -> 0.082339176 | I60: =+I21*I14 -> 0.11365368 | J60: =+J21*J14 -> 0.11316872 | ... AJ60: =+AJ21*AJ14 -> 0.099192171
A61: Final exergy residencial electricity [TJ] | B61: Computed | C61: =+C22*C15 -> 0.062887425 | D61: =+D22*D15 -> 0.065724008 | E61: =+E22*E15 -> 0.065436985 | F61: =+F22*F15 -> 0.073207804 | G61: =+G22*G15 -> 0.074760337 | H61: =+H22*H15 -> 0.070569373 | I61: =+I22*I15 -> 0.05308276 | J61: =+J22*J15 -> 0.05441956 | ... AJ61: =+AJ22*AJ15 -> 0.092814785
A62: Final Exergy Agriculture/Forestry/fishing electricity [TJ] | B62: Computed | C62: =+C23*C16 -> 0.004914251 | D62: =+D23*D16 -> 0.0052902303 | E62: =+E23*E16 -> 0.0047393761 | F62: =+F23*F16 -> 0.0054342848 | G62: =+G23*G16 -> 0.0060460307 | H62: =+H23*H16 -> 0.0048708743 | I62: =+I23*I16 -> 0.0039573979 | J62: =+J23*J16 -> 0.0038807424 | ... AJ62: =+AJ23*AJ16 -> 0.0017901767
A63: Final Exergy Energy industry own use electricity [TJ] | B63: Computed | C63: =+C24*C17 -> 0.016340496 | D63: =+D24*D17 -> 0.013556461 | E63: =+E24*E17 -> 0.011390517 | F63: =+F24*F17 -> 0.011593447 | G63: =+G24*G17 -> 0.009682344 | H63: =+H24*H17 -> 0.010625414 | I63: =+I24*I17 -> 0.012307815 | J63: =+J24*J17 -> 0.012309671 | ... AJ63: =+AJ24*AJ17 -> 0.01194298
A64: Final exergy industry coal/coke [TJ] | B64: Computed | C64: =+C25*C$12 -> 0.018797403 | D64: =+D25*D$12 -> 0.016589087 | E64: =+E25*E$12 -> 0.016275538 | F64: =+F25*F$12 -> 0.018487421 | G64: =+G25*G$12 -> 0.015486138 | H64: =+H25*H$12 -> 0.01656312 | I64: =+I25*I$12 -> 0.013660112 | J64: =+J25*J$12 -> 0.012782194 | ... AJ64: =+AJ25*AJ$12 -> 0
A65: Final exergy industry oil [TJ] | B65: Computed | C65: =+C26*C$12 -> 0.021274266 | D65: =+D26*D$12 -> 0.02105507 | E65: =+E26*E$12 -> 0.019090367 | F65: =+F26*F$12 -> 0.020215741 | G65: =+G26*G$12 -> 0.019715 | H65: =+H26*H$12 -> 0.022689325 | I65: =+I26*I$12 -> 0.018206961 | J65: =+J26*J$12 -> 0.017545288 | ... AJ65: =+AJ26*AJ$12 -> 0.0039905639
A66: Final exergy industry natural gas [TJ] | B66: Computed | C66: =+C27*C$12 -> 0.073353629 | D66: =+D27*D$12 -> 0.074722565 | E66: =+E27*E$12 -> 0.075030393 | F66: =+F27*F$12 -> 0.07539784 | G66: =+G27*G$12 -> 0.082932455 | H66: =+H27*H$12 -> 0.070846662 | I66: =+I27*I$12 -> 0.073086341 | J66: =+J27*J$12 -> 0.073041611 | ... AJ66: =+AJ27*AJ$12 -> 0.060567302
A67: Final exergy industry c. renewables/waste [TJ] | B67: Computed | C67: =+C28*C$12 -> 0.071119412 | D67: =+D28*D$12 -> 0.070175264 | E67: =+E28*E$12 -> 0.072552336 | F67: =+F28*F$12 -> 0.077778194 | G67: =+G28*G$12 -> 0.073013548 | H67: =+H28*H$12 -> 0.074507782 | I67: =+I28*I$12 -> 0.069607982 | J67: =+J28*J$12 -> 0.068992866 | ... AJ67: =+AJ28*AJ$12 -> 0.04791795
A68: Final exergy industry heat [TJ] | B68: Computed | C68: =+C29*C$12 -> 0.0062498177 | D68: =+D29*D$12 -> 0.0070897976 | E68: =+E29*E$12 -> 0.0076826389 | F68: =+F29*F$12 -> 0.00753907 | G68: =+G29*G$12 -> 0.0064086236 | H68: =+H29*H$12 -> 0.0047666413 | I68: =+I29*I$12 -> 0.0043637964 | J68: =+J29*J$12 -> 0.0038167393 | ... AJ68: =+AJ29*AJ$12 -> 0
A69: Final exergy transport coal/coke [TJ] | B69: Computed | C69: =+C$13*C30 -> 0 | D69: =+D$13*D30 -> 0 | E69: =+E$13*E30 -> 0 | F69: =+F$13*F30 -> 0 | G69: =+G$13*G30 -> 0 | H69: =+H$13*H30 -> 0 | I69: =+I$13*I30 -> 0 | J69: =+J$13*J30 -> 0 | ... AJ69: =+AJ$13*AJ30 -> 0
A70: Final exergy transport oil [TJ] | B70: Computed | C70: =+C$13*C31 -> 0.33567091 | D70: =+D$13*D31 -> 0.33654448 | E70: =+E$13*E31 -> 0.34228577 | F70: =+F$13*F31 -> 0.30856079 | G70: =+G$13*G31 -> 0.32451721 | H70: =+H$13*H31 -> 0.3340624 | I70: =+I$13*I31 -> 0.34693061 | J70: =+J$13*J31 -> 0.34858214 | ... AJ70: =+AJ$13*AJ31 -> 0.38991553
A71: Final exergy transport natural gas [TJ] | B71: Computed | C71: =+C$13*C32 -> 0.00088670839 | D71: =+D$13*D32 -> 0.00096301842 | E71: =+E$13*E32 -> 0.0010441319 | F71: =+F$13*F32 -> 0.001298036 | G71: =+G$13*G32 -> 0.0015022085 | H71: =+H$13*H32 -> 0.0020018913 | I71: =+I$13*I32 -> 0.0017702183 | J71: =+J$13*J32 -> 0.0018883784 | ... AJ71: =+AJ$13*AJ32 -> 0.0054032155
A72: Final exergy transport c. renewables/waste [TJ] | B72: Computed | C72: =+C$13*C33 -> 0.01566072 | D72: =+D$13*D33 -> 0.016850121 | E72: =+E$13*E33 -> 0.017382093 | F72: =+F$13*F33 -> 0.016832668 | G72: =+G$13*G33 -> 0.021481517 | H72: =+H$13*H33 -> 0.021498717 | I72: =+I$13*I33 -> 0.020571108 | J72: =+J$13*J33 -> 0.020879 | ... AJ72: =+AJ$13*AJ33 -> 0.029651641
A73: Final exergy transport heat [TJ] | B73: Computed | C73: =+C$13*C34 -> 0 | D73: =+D$13*D34 -> 0 | E73: =+E$13*E34 -> 0 | F73: =+F$13*F34 -> 0 | G73: =+G$13*G34 -> 0 | H73: =+H$13*H34 -> 0 | I73: =+I$13*I34 -> 0 | J73: =+J$13*J34 -> 0 | ... AJ73: =+AJ$13*AJ34 -> 0
A74: Final exergy services coal/coke [TJ] | B74: Computed | C74: =+C$14*C35 -> 0 | D74: =+D$14*D35 -> 0 | E74: =+E$14*E35 -> 0 | F74: =+F$14*F35 -> 0 | G74: =+G$14*G35 -> 0 | H74: =+H$14*H35 -> 0 | I74: =+I$14*I35 -> 0 | J74: =+J$14*J35 -> 0 | ... AJ74: =+AJ$14*AJ35 -> 0
A75: Final exergy services oil [TJ] | B75: Computed | C75: =+C$14*C36 -> 0.008584364 | D75: =+D$14*D36 -> 0.0099401558 | E75: =+E$14*E36 -> 0.010074914 | F75: =+F$14*F36 -> 0.00777558 | G75: =+G$14*G36 -> 0.0069481686 | H75: =+H$14*H36 -> 0.0072441946 | I75: =+I$14*I36 -> 0.011005432 | J75: =+J$14*J36 -> 0.010779976 | ... AJ75: =+AJ$14*AJ36 -> 0.0053555577
A76: Final exergy services natural gas [TJ] | B76: Computed | C76: =+C$14*C37 -> 0.015435987 | D76: =+D$14*D37 -> 0.015734417 | E76: =+E$14*E37 -> 0.014761564 | F76: =+F$14*F37 -> 0.013093476 | G76: =+G$14*G37 -> 0.014999063 | H76: =+H$14*H37 -> 0.014258512 | I76: =+I$14*I37 -> 0.02117356 | J76: =+J$14*J37 -> 0.021293083 | ... AJ76: =+AJ$14*AJ37 -> 0.023475872
A77: Final exergy services c. renewables/waste [TJ] | B77: Computed | C77: =+C$14*C38 -> 0.0021754649 | D77: =+D$14*D38 -> 0.0020799228 | E77: =+E$14*E38 -> 0.0018265235 | F77: =+F$14*F38 -> 0.0013654364 | G77: =+G$14*G38 -> 0.0017069347 | H77: =+H$14*H38 -> 0.0019363382 | I77: =+I$14*I38 -> 0.0019818973 | J77: =+J$14*J38 -> 0.0018187707 | ... AJ77: =+AJ$14*AJ38 -> 0
A78: Final exergy services renewables [TJ] | B78: Computed | C78: =+C$14*C39 -> 0.0021343342 | D78: =+D$14*D39 -> 0.0022429856 | E78: =+E$14*E39 -> 0.0023165869 | F78: =+F$14*F39 -> 0.0025930311 | G78: =+G$14*G39 -> 0.0026522062 | H78: =+H$14*H39 -> 0.0028274246 | I78: =+I$14*I39 -> 0.0040460442 | J78: =+J$14*J39 -> 0.0041941545 | ... AJ78: =+AJ$14*AJ39 -> 0.0074683577
A79: Final exergy services heat [TJ] | B79: Computed | C79: =+C$14*C40 -> 0.00088367688 | D79: =+D$14*D40 -> 0.00086438824 | E79: =+E$14*E40 -> 0.00082445184 | F79: =+F$14*F40 -> 0.00085995277 | G79: =+G$14*G40 -> 0.00088673042 | H79: =+H$14*H40 -> 0.00074077995 | I79: =+I$14*I40 -> 0.0011430394 | J79: =+J$14*J40 -> 0.0011310127 | ... AJ79: =+AJ$14*AJ40 -> 0.00082738913
A80: Final exergy residencial coal/coke [TJ] | B80: Computed | C80: =+C$15*C41 -> 0 | D80: =+D$15*D41 -> 0 | E80: =+E$15*E41 -> 0 | F80: =+F$15*F41 -> 0 | G80: =+G$15*G41 -> 0 | H80: =+H$15*H41 -> 0 | I80: =+I$15*I41 -> 0 | J80: =+J$15*J41 -> 0 | ... AJ80: =+AJ$15*AJ41 -> 0
A81: Final exergy residencial oil [TJ] | B81: Computed | C81: =+C$15*C42 -> 0.02636687 | D81: =+D$15*D42 -> 0.025782385 | E81: =+E$15*E42 -> 0.024839676 | F81: =+F$15*F42 -> 0.029690611 | G81: =+G$15*G42 -> 0.025381586 | H81: =+H$15*H42 -> 0.022143092 | I81: =+I$15*I42 -> 0.016515024 | J81: =+J$15*J42 -> 0.016038591 | ... AJ81: =+AJ$15*AJ42 -> 0
A82: Final exergy residencial natural gas [TJ] | B82: Computed | C82: =+C$15*C43 -> 0.015148648 | D82: =+D$15*D43 -> 0.016430404 | E82: =+E$15*E43 -> 0.017012544 | F82: =+F$15*F43 -> 0.019104196 | G82: =+G$15*G43 -> 0.018160326 | H82: =+H$15*H43 -> 0.016388172 | I82: =+I$15*I43 -> 0.013047134 | J82: =+J$15*J43 -> 0.013361748 | ... AJ82: =+AJ$15*AJ43 -> 0.022304114
A83: Final exergy residencial c. renewables/waste [TJ] | B83: Computed | C83: =+C$15*C44 -> 0.049304341 | D83: =+D$15*D44 -> 0.048634677 | E83: =+E$15*E44 -> 0.04861165 | F83: =+F$15*F44 -> 0.053847966 | G83: =+G$15*G44 -> 0.052810681 | H83: =+H$15*H44 -> 0.051185398 | I83: =+I$15*I44 -> 0.037730749 | J83: =+J$15*J44 -> 0.038237735 | ... AJ83: =+AJ$15*AJ44 -> 0.049816939
A84: Final exergy residencial renewables [TJ] | B84: Computed | C84: =+C$15*C45 -> 0.0030662227 | D84: =+D$15*D45 -> 0.003319329 | E84: =+E$15*E45 -> 0.0033264157 | F84: =+F$15*F45 -> 0.0037666863 | G84: =+G$15*G45 -> 0.0038539597 | H84: =+H$15*H45 -> 0.0038024764 | I84: =+I$15*I45 -> 0.002962858 | J84: =+J$15*J45 -> 0.003107073 | ... AJ84: =+AJ$15*AJ45 -> 0.0077175252
A85: Final exergy residencial heat [TJ] | B85: Computed | C85: =+C$15*C46 -> 2.9970952e-05 | D85: =+D$15*D46 -> 3.6619665e-05 | E85: =+E$15*E46 -> 2.9691549e-05 | F85: =+F$15*F46 -> 3.2165136e-05 | G85: =+G$15*G46 -> 3.141649e-05 | H85: =+H$15*H46 -> 2.1130822e-05 | I85: =+I$15*I46 -> 1.9217157e-05 | J85: =+J$15*J46 -> 1.8727514e-05 | ... AJ85: =+AJ$15*AJ46 -> -1.8872986e-06
A86: Final exergy Agriculture/forestry/Fishing Coal/Coke [TJ] | B86: Computed | C86: =+C$16*C47 -> 0 | D86: =+D$16*D47 -> 0 | E86: =+E$16*E47 -> 0 | F86: =+F$16*F47 -> 0 | G86: =+G$16*G47 -> 0 | H86: =+H$16*H47 -> 0 | I86: =+I$16*I47 -> 0 | J86: =+J$16*J47 -> 0 | ... AJ86: =+AJ$16*AJ47 -> 0
A87: Final exergy Agriculture/forestry/Fishing oil [TJ] | B87: Computed | C87: =+C$16*C48 -> 0.021940478 | D87: =+D$16*D48 -> 0.021966128 | E87: =+E$16*E48 -> 0.022774767 | F87: =+F$16*F48 -> 0.026167646 | G87: =+G$16*G48 -> 0.026304993 | H87: =+H$16*H48 -> 0.024224712 | I87: =+I$16*I48 -> 0.018621898 | J87: =+J$16*J48 -> 0.018253426 | ... AJ87: =+AJ$16*AJ48 -> 0.0083307789
A88: Final exergy Agriculture/forestry/Fishing natural gas [TJ] | B88: Computed | C88: =+C$16*C49 -> 0.00035197332 | D88: =+D$16*D49 -> 0.00023282933 | E88: =+E$16*E49 -> 0.00038589007 | F88: =+F$16*F49 -> 0.00045754548 | G88: =+G$16*G49 -> 0.00052222584 | H88: =+H$16*H49 -> 0.00026083002 | I88: =+I$16*I49 -> 0.00026235306 | J88: =+J$16*J49 -> 0.0002515537 | ... AJ88: =+AJ$16*AJ49 -> 5.0126892e-05
A89: Final exergy Agriculture/forestry/Fishing c. renewables/waste [TJ] | B89: Computed | C89: =+C$16*C50 -> 0.00024029794 | D89: =+D$16*D50 -> 0.00034767375 | E89: =+E$16*E50 -> 0.00039742922 | F89: =+F$16*F50 -> 0.00044460527 | G89: =+G$16*G50 -> 0.00047216453 | H89: =+H$16*H50 -> 0.00024010763 | I89: =+I$16*I50 -> 0.00022556295 | J89: =+J$16*J50 -> 0.00020749452 | ... AJ89: =+AJ$16*AJ50 -> 0
A90: Final exergy Agriculture/forestry/Fishing heat [TJ] | B90: Computed | C90: =+C$16*C51 -> 0.00035103478 | D90: =+D$16*D51 -> 0.00022778476 | E90: =+E$16*E51 -> 0.00032090241 | F90: =+F$16*F51 -> 0.00026415618 | G90: =+G$16*G51 -> 0.00037513616 | H90: =+H$16*H51 -> 0.00033203361 | I90: =+I$16*I51 -> 0.00021537901 | J90: =+J$16*J51 -> 0.00020430621 | ... AJ90: =+AJ$16*AJ51 -> 1.4689753e-05
A91: Final Exergy Energy industry own use Coal/Coke [TJ] | B91: Computed | C91: =+C$17*C52 -> 0 | D91: =+D$17*D52 -> 0 | E91: =+E$17*E52 -> 0 | F91: =+F$17*F52 -> 0 | G91: =+G$17*G52 -> 0 | H91: =+H$17*H52 -> 0 | I91: =+I$17*I52 -> 0 | J91: =+J$17*J52 -> 0 | ... AJ91: =+AJ$17*AJ52 -> 0
A92: Final Exergy Energy industry own use Oil [TJ] | B92: Computed | C92: =+C$17*C53 -> 0.046898119 | D92: =+D$17*D53 -> 0.041844374 | E92: =+E$17*E53 -> 0.038777629 | F92: =+F$17*F53 -> 0.039582799 | G92: =+G$17*G53 -> 0.02980137 | H92: =+H$17*H53 -> 0.042268569 | I92: =+I$17*I53 -> 0.043054247 | J92: =+J$17*J53 -> 0.04348376 | ... AJ92: =+AJ$17*AJ53 -> 0.05455011
A93: Final Exergy Energy industry own use Natural Gas [TJ] | B93: Computed | C93: =+C$17*C54 -> 0.0063668482 | D93: =+D$17*D54 -> 0.0056929803 | E93: =+E$17*E54 -> 0.0056466783 | F93: =+F$17*F54 -> 0.0056285807 | G93: =+G$17*G54 -> 0.0057297813 | H93: =+H$17*H54 -> 0.0036732913 | I93: =+I$17*I54 -> 0.0049945155 | J93: =+J$17*J54 -> 0.0047949771 | ... AJ93: =+AJ$17*AJ54 -> 0
A94: Final Exergy Energy industry own use C. Renewables/Waste [TJ] | B94: Computed | C94: =+C$17*C55 -> 0 | D94: =+D$17*D55 -> 0 | E94: =+E$17*E55 -> 0 | F94: =+F$17*F55 -> 0 | G94: =+G$17*G55 -> 0 | H94: =+H$17*H55 -> 0 | I94: =+I$17*I55 -> 0 | J94: =+J$17*J55 -> -7.6775986e-17 | ... AJ94: =+AJ$17*AJ55 -> 0
A95: Final Exergy Energy industry own use Heat [TJ] | B95: Computed | C95: =+C$17*C56 -> 0.0087382476 | D95: =+D$17*D56 -> 0.0087393904 | E95: =+E$17*E56 -> 0.0087231957 | F95: =+F$17*F56 -> 0.009925598 | G95: =+G$17*G56 -> 0.0072237942 | H95: =+H$17*H56 -> 0.0042314089 | I95: =+I$17*I56 -> 0.0084363976 | J95: =+J$17*J56 -> 0.0085652527 | ... AJ95: =+AJ$17*AJ56 -> 0.012038384
A97: Share final exergy industry coal HTH | B97: Input | C97: 0.034874132 | D97: 0.036372867 | E97: 0.039214851 | F97: 0.033094645 | G97: 0.040076007 | H97: 0.024729956 | I97: 0.038592005 | J97: 0.039491667 | K97: 0.040390489 | L97: 0.041288472 | M97: 0.042185617 | N97: 0.043081927 | O97: 0.043977401 | P97: 0.044872041 | Q97: 0.045765848 | R97: 0.046658823 | S97: 0.047550968 | T97: 0.048442284 | U97: 0.049332771 | V97: 0.050222431 | W97: 0.051111265 | X97: 0.051999275 | Y97: 0.05288646 | Z97: 0.053772824 | AA97: 0.054658366 | AB97: 0.055543087 | AC97: 0.05642699 | AD97: 0.057310075 | AE97: 0.058192343 | AF97: 0.059073795 | AG97: 0.059954433 | AH97: 0.060834257 | AI97: 0.061713269 | AJ97: 0.06259147
A98: Share final exergy industry coal HTH/MTH | B98: Input | C98: 0.96512594 | D98: 0.963629 | E98: 0.96078618 | F98: 0.96690554 | G98: 0.95992322 | H98: 0.97526941 | I98: 0.96140799 | J98: 0.96050833 | K98: 0.95960951 | L98: 0.95871153 | M98: 0.95781438 | N98: 0.95691807 | O98: 0.9560226 | P98: 0.95512796 | Q98: 0.95423415 | R98: 0.95334118 | S98: 0.95244903 | T98: 0.95155772 | U98: 0.95066723 | V98: 0.94977757 | W98: 0.94888873 | X98: 0.94800073 | Y98: 0.94711354 | Z98: 0.94622718 | AA98: 0.94534163 | AB98: 0.94445691 | AC98: 0.94357301 | AD98: 0.94268993 | AE98: 0.94180766 | AF98: 0.9409262 | AG98: 0.94004557 | AH98: 0.93916574 | AI98: 0.93828673 | AJ98: 0.93740853
A99: Share final exergy industry coal MTH | B99: Input | C99: 0 | D99: 0 | E99: 0 | F99: 0 | G99: 0 | H99: 0 | I99: 0 | J99: 0 | K99: 0 | L99: 0 | M99: 0 | N99: 0 | O99: 0 | P99: 0 | Q99: 0 | R99: 0 | S99: 0 | T99: 0 | U99: 0 | V99: 0 | W99: 0 | X99: 0 | Y99: 0 | Z99: 0 | AA99: 0 | AB99: 0 | AC99: 0 | AD99: 0 | AE99: 0 | AF99: 0 | AG99: 0 | AH99: 0 | AI99: 0 | AJ99: 0
A100: Share final exergy industry coal LTH1 | B100: Input | C100: 0 | D100: 0 | E100: 0 | F100: 0 | G100: 0 | H100: 0 | I100: 0 | J100: 0 | K100: 0 | L100: 0 | M100: 0 | N100: 0 | O100: 0 | P100: 0 | Q100: 0 | R100: 0 | S100: 0 | T100: 0 | U100: 0 | V100: 0 | W100: 0 | X100: 0 | Y100: 0 | Z100: 0 | AA100: 0 | AB100: 0 | AC100: 0 | AD100: 0 | AE100: 0 | AF100: 0 | AG100: 0 | AH100: 0 | AI100: 0 | AJ100: 0
A101: Share final exergy industry coal LTH2 | B101: Input | C101: 0 | D101: 0 | E101: 0 | F101: 0 | G101: 0 | H101: 0 | I101: 0 | J101: 0 | K101: 0 | L101: 0 | M101: 0 | N101: 0 | O101: 0 | P101: 0 | Q101: 0 | R101: 0 | S101: 0 | T101: 0 | U101: 0 | V101: 0 | W101: 0 | X101: 0 | Y101: 0 | Z101: 0 | AA101: 0 | AB101: 0 | AC101: 0 | AD101: 0 | AE101: 0 | AF101: 0 | AG101: 0 | AH101: 0 | AI101: 0 | AJ101: 0
A102: Share final exergy industry coal LTH3 | B102: Input | C102: 0 | D102: 0 | E102: 0 | F102: 0 | G102: 0 | H102: 0 | I102: 0 | J102: 0 | K102: 0 | L102: 0 | M102: 0 | N102: 0 | O102: 0 | P102: 0 | Q102: 0 | R102: 0 | S102: 0 | T102: 0 | U102: 0 | V102: 0 | W102: 0 | X102: 0 | Y102: 0 | Z102: 0 | AA102: 0 | AB102: 0 | AC102: 0 | AD102: 0 | AE102: 0 | AF102: 0 | AG102: 0 | AH102: 0 | AI102: 0 | AJ102: 0
A103: Share final exergy industry oil HTH | B103: Input | C103: 0.0014566748 | D103: 0.0010434608 | E103: 0.0010395558 | F103: 0.00073240396 | G103: 0.00059354653 | H103: 0.000499918 | I103: -1.0294409e-05 | J103: -0.00031539657 | K103: 0 | L103: 0 | M103: 0 | N103: 0 | O103: 0 | P103: 0 | Q103: 0 | R103: 0 | S103: 0 | T103: 0 | U103: 0 | V103: 0 | W103: 0 | X103: 0 | Y103: 0 | Z103: 0 | AA103: 0 | AB103: 0 | AC103: 0 | AD103: 0 | AE103: 0 | AF103: 0 | AG103: 0 | AH103: 0 | AI103: 0 | AJ103: 0
A104: Share final exergy industry oil HTH/MTH | B104: Input | C104: 0.10256733 | D104: 0.11993191 | E104: 0.10360982 | F104: 0.089575034 | G104: 0.096812209 | H104: 0.086535213 | I104: 0.094405399 | J104: 0.093265947 | K104: 0.092069365 | L104: 0.090902902 | M104: 0.089737149 | N104: 0.088572106 | O104: 0.087407773 | P104: 0.086244148 | Q104: 0.085081232 | R104: 0.083919023 | S104: 0.082757521 | T104: 0.081596726 | U104: 0.080436635 | V104: 0.07927725 | W104: 0.078118569 | X104: 0.076960592 | Y104: 0.075803318 | Z104: 0.074646746 | AA104: 0.073490876 | AB104: 0.072335707 | AC104: 0.071181238 | AD104: 0.070027469 | AE104: 0.0688744 | AF104: 0.067722029 | AG104: 0.066570355 | AH104: 0.065419379 | AI104: 0.064202635 | AJ104: 0.062752836
A105: Share final exergy industry oil MTH | B105: Input | C105: 0 | D105: 0 | E105: 0 | F105: 0 | G105: 0 | H105: 0 | I105: 0 | J105: 0 | K105: 0 | L105: 0 | M105: 0 | N105: 0 | O105: 0 | P105: 0 | Q105: 0 | R105: 0 | S105: 0 | T105: 0 | U105: 0 | V105: 0 | W105: 0 | X105: 0 | Y105: 0 | Z105: 0 | AA105: 0 | AB105: 0 | AC105: 0 | AD105: 0 | AE105: 0 | AF105: 0 | AG105: 0 | AH105: 0 | AI105: 0 | AJ105: 0
A106: Share final exergy industry oil LTH1 | B106: Input | C106: 0.21730035 | D106: 0.19395363 | E106: 0.16321178 | F106: 0.18614929 | G106: 0.16041475 | H106: 0.2055045 | I106: 0.18858267 | J106: 0.18837506 | K106: 0.18805075 | L106: 0.187786 | M106: 0.18752142 | N106: 0.18725699 | O106: 0.18699273 | P106: 0.18672862 | Q106: 0.18646468 | R106: 0.1862009 | S106: 0.18593728 | T106: 0.18567382 | U106: 0.18541051 | V106: 0.18514737 | W106: 0.18488439 | X106: 0.18462157 | Y106: 0.18435891 | Z106: 0.1840964 | AA106: 0.18383406 | AB106: 0.18357188 | AC106: 0.18330985 | AD106: 0.18304798 | AE106: 0.18278628 | AF106: 0.18252473 | AG106: 0.18226334 | AH106: 0.1820021 | AI106: 0.18155308 | AJ106: 0.18042584
A107: Share final exergy industry oil LTH2 | B107: Input | C107: 0.14795723 | D107: 0.14906812 | E107: 0.15821703 | F107: 0.14846874 | G107: 0.1342072 | H107: 0.13154627 | I107: 0.12500403 | J107: 0.12015605 | K107: 0.11523658 | L107: 0.11035796 | M107: 0.10548232 | N107: 0.10060964 | O107: 0.095739935 | P107: 0.090873192 | Q107: 0.086009412 | R107: 0.08114859 | S107: 0.076290724 | T107: 0.071435813 | U107: 0.066583852 | V107: 0.06173484 | W107: 0.056888773 | X107: 0.052045649 | Y107: 0.047205465 | Z107: 0.042368219 | AA107: 0.037533908 | AB107: 0.03270253 | AC107: 0.02787408 | AD107: 0.023048558 | AE107: 0.01822596 | AF107: 0.013406283 | AG107: 0.0085895256 | AH107: 0.0037756843 | AI107: 0 | AJ107: 0
A108: Share final exergy industry oil LTH3 | B108: Input | C108: 0 | D108: 0 | E108: 0 | F108: 0 | G108: 0 | H108: 0 | I108: 0 | J108: 0 | K108: 0 | L108: 0 | M108: 0 | N108: 0 | O108: 0 | P108: 0 | Q108: 0 | R108: 0 | S108: 0 | T108: 0 | U108: 0 | V108: 0 | W108: 0 | X108: 0 | Y108: 0 | Z108: 0 | AA108: 0 | AB108: 0 | AC108: 0 | AD108: 0 | AE108: 0 | AF108: 0 | AG108: 0 | AH108: 0 | AI108: 0 | AJ108: 0
... A179: Share Final Exergy Energy industry own use Electricity Generic | B179: Input | C179: 1 | D179: 1 | E179: 1 | F179: 1 | G179: 1 | H179: 1 | I179: 1 | J179: 1 | K179: 1 | L179: 1 | M179: 1 | N179: 1 | O179: 1 | P179: 1 | Q179: 1 | R179: 1 | S179: 1 | T179: 1 | U179: 1 | V179: 1 | W179: 1 | X179: 1 | Y179: 1 | Z179: 1 | AA179: 1 | AB179: 1 | AC179: 1 | AD179: 1 | AE179: 1 | AF179: 1 | AG179: 1 | AH179: 1 | AI179: 1 | AJ179: 1
...

Sheet BAU
A1: Scenarios - BAU 2025-2050 | C1: Historical | D1: Historical | E1: Historical | F1: Historical | G1: Historical | H1: Historical | I1: Scenarios
C2: 2017 | D2: 2018 | E2: 2019 | F2: 2020 | G2: 2021 | H2: 2022 | I2: 2023 | J2: 2024 | K2: 2025 | L2: 2026 | M2: 2027 | N2: 2028 | O2: 2029 | P2: 2030 | Q2: 2031 | R2: 2032 | S2: 2033 | T2: 2034 | U2: 2035 | V2: 2036 | W2: 2037 | X2: 2038 | Y2: 2039 | Z2: 2040 | AA2: 2041 | AB2: 2042 | AC2: 2043 | AD2: 2044 | AE2: 2045 | AF2: 2046 | AG2: 2047 | AH2: 2048 | AI2: 2049 | AJ2: 2050
A3: New Solar power [GW] | B3: Computed | D3: =D10-C10 -> 0.098 | E3: =E10-D10 -> 0.253 | F3: =F10-E10 -> 0.221 | G3: =G10-F10 -> 0.626 | H3: =H10-G10 -> 1 | I3: =I10-H10 -> 1.223 | J3: =J10-I10 -> 1.768 | K3: =K10-J10 -> 0.54584615 | ... AJ3: =AJ10-AI10 -> 0.54584615
A4: New Onshore Wind power [GW] | B4: Computed | D4: =D11-C11 -> 0.048 | E4: =E11-D11 -> 0.051 | F4: =F11-E11 -> -0.101 | G4: =G11-F11 -> 0.305 | H4: =H11-G11 -> 0.111 | I4: =I11-H11 -> 0 | J4: =J11-I11 -> 0.045 | K4: =K11-J11 -> 0.0677 | ... AJ4: =AJ11-AI11 -> 0.1427
A5: New Offshore Wind power [GW] | B5: Computed | D5: =D12-C12 -> 0 | E5: =E12-D12 -> 0 | F5: =F12-E12 -> 0.025 | G5: =G12-F12 -> 0 | H5: =H12-G12 -> 0 | I5: =I12-H12 -> 0 | J5: =J12-I12 -> 0 | K5: =K12-J12 -> 0 | ... AJ5: =AJ12-AI12 -> 0
A6: New Batteries [GWh] | B6: Computed | D6: =D13-C13 -> 0 | E6: =E13-D13 -> 0 | F6: =F13-E13 -> 0.02 | G6: =G13-F13 -> 0 | H6: =H13-G13 -> 0.03 | I6: =I13-H13 -> 0 | J6: =J13-I13 -> 0.01 | K6: =K13-J13 -> 0 | ... AJ6: =AJ13-AI13 -> 0
A7: New Hydrogen [GW] | B7: Computed | D7: =D14-C14 -> 0 | E7: =E14-D14 -> 0 | F7: =F14-E14 -> 0 | G7: =G14-F14 -> 0 | H7: =H14-G14 -> 0 | I7: =I14-H14 -> 0 | J7: =J14-I14 -> 0 | K7: =K14-J14 -> 0 | ... AJ7: =AJ14-AI14 -> 0
A8: New Hydropower [GW] | B8: Computed | D8: =D15-C15 -> 0.01 | E8: =E15-D15 -> 0.026 | F8: =F15-E15 -> -0.021 | G8: =G15-F15 -> 0.014 | H8: =H15-G15 -> 0.934 | I8: =I15-H15 -> -0.002 | J8: =J15-I15 -> 0.16 | K8: =K15-J15 -> 0 | ... AJ8: =AJ15-AI15 -> 0
A10: Solar power [GW] | B10: Input | C10: 0.619 | D10: 0.717 | E10: 0.97 | F10: 1.191 | G10: 1.817 | H10: 2.817 | I10: 4.04 | J10: 5.808 | K10: 6.3538462 | L10: 6.8996923 | M10: 7.4455385 | N10: 7.9913846 | O10: 8.5372308 | P10: 9.0830769 | Q10: 9.6289231 | R10: 10.174769 | S10: 10.720615 | T10: 11.266462 | U10: 11.812308 | V10: 12.358154 | W10: 12.904 | X10: 13.449846 | Y10: 13.995692 | Z10: 14.541538 | AA10: 15.087385 | AB10: 15.633231 | AC10: 16.179077 | AD10: 16.724923 | AE10: 17.270769 | AF10: 17.816615 | AG10: 18.362462 | AH10: 18.908308 | AI10: 19.454154 | AJ10: 20
A11: Onshore Wind power [GW] | B11: Input | C11: 5.124 | D11: 5.172 | E11: 5.223 | F11: 5.122 | G11: 5.427 | H11: 5.538 | I11: 5.538 | J11: 5.583 | K11: 5.6507 | L11: 5.7214 | M11: 5.7951 | N11: 5.8718 | O11: 5.9515 | P11: 6.0342 | Q11: 6.1199 | R11: 6.2086 | S11: 6.3003 | T11: 6.395 | U11: 6.4927 | V11: 6.5934 | W11: 6.6971 | X11: 6.8038 | Y11: 6.9135 | Z11: 7.0262 | AA11: 7.1419 | AB11: 7.2606 | AC11: 7.3823 | AD11: 7.507 | AE11: 7.6347 | AF11: 7.7654 | AG11: 7.8991 | AH11: 8.0358 | AI11: 8.1755 | AJ11: 8.3182
A12: Offshore Wind Power [GW] | B12: Input | C12: 0 | D12: 0 | E12: 0 | F12: 0.025 | G12: 0.025 | H12: 0.025 | I12: 0.025 | J12: 0.025 | K12: 0.025 | L12: 0.025 | M12: 0.025 | N12: 0.025 | O12: 0.025 | P12: 0.025 | Q12: 0.025 | R12: 0.025 | S12: 0.025 | T12: 0.025 | U12: 0.025 | V12: 0.025 | W12: 0.025 | X12: 0.025 | Y12: 0.025 | Z12: 0.025 | AA12: 0.025 | AB12: 0.025 | AC12: 0.025 | AD12: 0.025 | AE12: 0.025 | AF12: 0.025 | AG12: 0.025 | AH12: 0.025 | AI12: 0.025 | AJ12: 0.025
A13: Batteries [GWh] | B13: Input | C13: 0 | D13: 0 | E13: 0 | F13: 0.02 | G13: 0.02 | H13: 0.05 | I13: 0.05 | J13: 0.06 | K13: 0.06 | L13: 0.06 | M13: 0.06 | N13: 0.06 | O13: 0.06 | P13: 0.06 | Q13: 0.06 | R13: 0.06 | S13: 0.06 | T13: 0.06 | U13: 0.06 | V13: 0.06 | W13: 0.06 | X13: 0.06 | Y13: 0.06 | Z13: 0.06 | AA13: 0.06 | AB13: 0.06 | AC13: 0.06 | AD13: 0.06 | AE13: 0.06 | AF13: 0.06 | AG13: 0.06 | AH13: 0.06 | AI13: 0.06 | AJ13: 0.06
A14: Hydrogen [GW] | B14: Input | C14: 0 | D14: 0 | E14: 0 | F14: 0 | G14: 0 | H14: 0 | I14: 0 | J14: 0 | K14: 0 | L14: 0 | M14: 0 | N14: 0 | O14: 0 | P14: 0 | Q14: 0 | R14: 0 | S14: 0 | T14: 0 | U14: 0 | V14: 0 | W14: 0 | X14: 0 | Y14: 0 | Z14: 0 | AA14: 0 | AB14: 0 | AC14: 0 | AD14: 0 | AE14: 0 | AF14: 0 | AG14: 0 | AH14: 0 | AI14: 0 | AJ14: 0
A15: Hydro power [GW] | B15: Input | C15: 7.226 | D15: 7.236 | E15: 7.262 | F15: 7.241 | G15: 7.255 | H15: 8.189 | I15: 8.187 | J15: 8.347 | K15: 8.347 | L15: 8.347 | M15: 8.347 | N15: 8.347 | O15: 8.347 | P15: 8.347 | Q15: 8.347 | R15: 8.347 | S15: 8.347 | T15: 8.347 | U15: 8.347 | V15: 8.347 | W15: 8.347 | X15: 8.347 | Y15: 8.347 | Z15: 8.347 | AA15: 8.347 | AB15: 8.347 | AC15: 8.347 | AD15: 8.347 | AE15: 8.347 | AF15: 8.347 | AG15: 8.347 | AH15: 8.347 | AI15: 8.347 | AJ15: 8.347
A16: Total Renewable [GW] | C16: =SUM(C10:C15) -> 12.969 | D16: =SUM(D10:D15) -> 13.125 | E16: =SUM(E10:E15) -> 13.455 | F16: =SUM(F10:F15) -> 13.599 | G16: =SUM(G10:G15) -> 14.544 | H16: =SUM(H10:H15) -> 16.619 | I16: =SUM(I10:I15) -> 17.84 | J16: =SUM(J10:J15) -> 19.823 | ... AJ16: =SUM(AJ10:AJ15) -> 36.7502
A18: Cost per GW solar [Euro/GW] | B18: Input | C18: 1446720000 | D18: 1236400000 | E18: 1021680000 | F18: 896720000 | G18: 836000000 | H18: 799040000 | I18: 667040000 | J18: 5.2253277e+08 | K18: 4.4974812e+08 | L18: 3.8710179e+08 | M18: 3.331816e+08 | N18: 2.8677206e+08 | O18: 2.46827e+08 | P18: 2.1244597e+08 | Q18: 1.8285394e+08 | R18: 1.5738384e+08 | S18: 1.3546153e+08 | T18: 1.1659282e+08 | U18: 1.0035237e+08 | V18: 100000000 | W18: 100000000 | X18: 100000000 | Y18: 100000000 | Z18: 100000000 | AA18: 100000000 | AB18: 100000000 | AC18: 100000000 | AD18: 100000000 | AE18: 100000000 | AF18: 100000000 | AG18: 100000000 | AH18: 100000000 | AI18: 100000000 | AJ18: 100000000
A19: Cost per GW of Onshore wind [Euro/GW] | B19: Input | C19: 1686960000 | D19: 1600720000 | E19: 1518000000 | F19: 1365760000 | G19: 1294480000 | H19: 1163360000 | I19: 1020800000 | J19: 1.0655588e+09 | K19: 1.0135909e+09 | L19: 9.6415749e+08 | M19: 9.1713498e+08 | N19: 8.7240578e+08 | O19: 8.2985805e+08 | P19: 7.8938539e+08 | Q19: 7.5088661e+08 | R19: 7.1426544e+08 | S19: 6.794303e+08 | T19: 6.462941e+08 | U19: 6.1477396e+08 | V19: 5.8479108e+08 | W19: 5.5627048e+08 | X19: 5.2914085e+08 | Y19: 5.0333435e+08 | Z19: 4.7878644e+08 | AA19: 4.5543575e+08 | AB19: 4.3322389e+08 | AC19: 4.1209531e+08 | AD19: 3.9199718e+08 | AE19: 3.7287926e+08 | AF19: 3.5469372e+08 | AG19: 3.373951e+08 | AH19: 3.2094015e+08 | AI19: 3.0528771e+08 | AJ19: 2.9039866e+08
A20: Cost per GW of Offshore wind [Euro/GW] | B20: Input | C20: 4788960000 | D20: 4684240000 | E20: 4684240000 | F20: 3753200000 | G20: 3177680000 | H20: 2785200000 | I20: 3060640000 | J20: 2464000000 | K20: 2.7915727e+09 | L20: 2.6554261e+09 | M20: 2.5259195e+09 | N20: 2.4027289e+09 | O20: 2.2855464e+09 | P20: 2.174079e+09 | Q20: 2.0680479e+09 | R20: 1.9671881e+09 | S20: 1.8712472e+09 | T20: 1.7799854e+09 | U20: 1.6931744e+09 | V20: 1.6105974e+09 | W20: 1.5320476e+09 | X20: 1.4573288e+09 | Y20: 1.386254e+09 | Z20: 1.3186456e+09 | AA20: 1.2543345e+09 | AB20: 1.1931599e+09 | AC20: 1.1349688e+09 | AD20: 1.0796157e+09 | AE20: 1.0269622e+09 | AF20: 9.7687668e+08 | AG20: 9.2923384e+08 | AH20: 8.8391457e+08 | AI20: 8.4080555e+08 | AJ20: 7.9979898e+08
A21: Cost per GW batteries [Euro/GW] | B21: Input | C21: 660000000 | D21: 616000000 | E21: 281600000 | F21: 264000000 | G21: 249040000 | H21: 315040000 | I21: 240240000 | J21: 1.5698899e+08 | K21: 1.2853171e+08 | L21: 1.0523287e+08 | M21: 86157384 | N21: 70539700 | O21: 57753021 | P21: 47284175 | Q21: 38713008 | R21: 31695530 | S21: 30000000 | T21: 30000000 | U21: 30000000 | V21: 30000000 | W21: 30000000 | X21: 30000000 | Y21: 30000000 | Z21: 30000000 | AA21: 30000000 | AB21: 30000000 | AC21: 30000000 | AD21: 30000000 | AE21: 30000000 | AF21: 30000000 | AG21: 30000000 | AH21: 30000000 | AI21: 30000000 | AJ21: 30000000
A22: Cost per GW hydrogen [Euro/GW] | B22: Input | C22: 880000000 | D22: 880000000 | E22: 880000000 | F22: 880000000 | G22: 8.5653333e+08 | H22: 8.3306667e+08 | I22: 809600000 | J22: 7.8613333e+08 | K22: 7.6266667e+08 | L22: 739200000 | M22: 7.1573333e+08 | N22: 6.9226667e+08 | O22: 668800000 | P22: 6.4533333e+08 | Q22: 6.2186667e+08 | R22: 598400000 | S22: 5.7493333e+08 | T22: 5.5146667e+08 | U22: 528000000 | V22: 5.0453333e+08 | W22: 4.8106667e+08 | X22: 457600000 | Y22: 4.3413333e+08 | Z22: 4.1066667e+08 | AA22: 387200000 | AB22: 3.6373333e+08 | AC22: 3.4026667e+08 | AD22: 316800000 | AE22: 2.9333333e+08 | AF22: 2.6986667e+08 | AG22: 246400000 | AH22: 2.2293333e+08 | AI22: 1.9946667e+08 | AJ22: 176000000
A23: Cost per GW hydropower [Euro/GW] | B23: Input | C23: 1874400000 | D23: 1468720000 | E23: 1806640000 | F23: 1892880000 | G23: 2081200000 | H23: 2686640000 | I23: 2469280000 | J23: 2469280000 | K23: 2469280000 | L23: 2469280000 | M23: 2469280000 | N23: 2469280000 | O23: 2469280000 | P23: 2469280000 | Q23: 2469280000 | R23: 2469280000 | S23: 2469280000 | T23: 2469280000 | U23: 2469280000 | V23: 2469280000 | W23: 2469280000 | X23: 2469280000 | Y23: 2469280000 | Z23: 2469280000 | AA23: 2469280000 | AB23: 2469280000 | AC23: 2469280000 | AD23: 2469280000 | AE23: 2469280000 | AF23: 2469280000 | AG23: 2469280000 | AH23: 2469280000 | AI23: 2469280000 | AJ23: 2469280000
A25: Cost Solar [Euro] | B25: Computed | C25: =+C18*C3 -> 0 | D25: =+D18*D3 -> 1.211672e+08 | E25: =+E18*E3 -> 258485040 | F25: =+F18*F3 -> 1.9817512e+08 | G25: =+G18*G3 -> 5.23336e+08 | H25: =+H18*H3 -> 7.9904e+08 | I25: =+I18*I3 -> 8.1578992e+08 | J25: =+J18*J3 -> 9.2383793e+08 | ... AJ25: =+AJ18*AJ3 -> 54584615
A26: Cost Onshore Wind [Euro] | B26: Computed | C26: =+C19*C4 -> 0 | D26: =+D19*D4 -> 76834560 | E26: =+E19*E4 -> 77418000 | F26: =+F19*F4 -> -1.3794176e+08 | G26: =+G19*G4 -> 3.948164e+08 | H26: =+H19*H4 -> 1.2913296e+08 | I26: =+I19*I4 -> 0 | J26: =+J19*J4 -> 47950147 | ... AJ26: =+AJ19*AJ4 -> 41439888
A27: Cost Offshore Wind [Euro] | B27: Computed | D27: =+D20*D5 -> 0 | E27: =+E20*E5 -> 0 | F27: =+F20*F5 -> 93830000 | G27: =+G20*G5 -> 0 | H27: =+H20*H5 -> 0 | I27: =+I20*I5 -> 0 | J27: =+J20*J5 -> 0 | K27: =+K20*K5 -> 0 | ... AJ27: =+AJ20*AJ5 -> 0
A28: Cost Batteries [Euro] | B28: Computed | D28: =+D21*D6 -> 0 | E28: =+E21*E6 -> 0 | F28: =+F21*F6 -> 5280000 | G28: =+G21*G6 -> 0 | H28: =+H21*H6 -> 9451200 | I28: =+I21*I6 -> 0 | J28: =+J21*J6 -> 1569889.9 | K28: =+K21*K6 -> 0 | ... AJ28: =+AJ21*AJ6 -> 0
A29: Cost Hydropower [Euro] | B29: Computed | D29: =+D23*D7 -> 0 | E29: =+E23*E7 -> 0 | F29: =+F23*F7 -> 0 | G29: =+G23*G7 -> 0 | H29: =+H23*H7 -> 0 | I29: =+I23*I7 -> 0 | J29: =+J23*J7 -> 0 | K29: =+K23*K7 -> 0 | ... AJ29: =+AJ23*AJ7 -> 0
A30: Cost tot [Mrd Euros] | B30: Computed | C30: =+(SUM(C25:C29)/10^9) -> 0 | D30: =+(SUM(D25:D29)/10^9) -> 0.19800176 | E30: =+(SUM(E25:E29)/10^9) -> 0.33590304 | F30: =+(SUM(F25:F29)/10^9) -> 0.15934336 | G30: =+(SUM(G25:G29)/10^9) -> 0.9181524 | H30: =+(SUM(H25:H29)/10^9) -> 0.93762416 | I30: =+(SUM(I25:I29)/10^9) -> 0.81578992 | J30: =+(SUM(J25:J29)/10^9) -> 0.97335797 | ... AJ30: =+(SUM(AJ25:AJ29)/10^9) -> 0.096024504
A33: Investment Industry [Mrd Euros] | B33: Computed | C33: 8.0532 | D33: 8.5546 | E33: 8.5605 | F33: 8.3117 | G33: 9.503 | H33: 10.0172 | I33: =0.182512988419182*H64 -> 8.718413 | J33: =0.182512988419182*I64 -> 6.7362148 | K33: =0.182512988419182*J64 -> 6.686337 | L33: =0.182512988419182*K64 -> 6.6210117 | M33: =0.182512988419182*L64 -> 6.5556282 | N33: =0.182512988419182*M64 -> 6.4900621 | O33: =0.182512988419182*N64 -> 6.4240236 | P33: =0.182512988419182*O64 -> 6.3575657 | ... AJ33: =0.182512988419182*AI64 -> 5.1661596
A34: Investment Transport [Mrd Euros] | B34: Computed | C34: 1.9438 | D34: 1.8375 | E34: 2.0515 | F34: 1.9884 | G34: 2.1811 | H34: 2.6349 | I34: =0.140684457604253*H65 -> 1.8913891 | J34: =0.140684457604253*I65 -> 1.4613673 | K34: =0.140684457604253*J65 -> 1.4505467 | L34: =0.140684457604253*K65 -> 1.4363749 | M34: =0.140684457604253*L65 -> 1.4221904 | N34: =0.140684457604253*M65 -> 1.4079664 | O34: =0.140684457604253*N65 -> 1.3936399 | P34: =0.140684457604253*O65 -> 1.3792224 | ... AJ34: =0.140684457604253*AI65 -> 1.1207565
A35: Investment Residential [Mrd EURO] | B35: Computed | C35: 5.3217 | D35: 5.663 | E35: 5.7613 | F35: 5.3511 | G35: 6.1815 | H35: 6.3237 | I35: =0.201851534153057*H66 -> 4.9412385 | J35: =0.201851534153057*I66 -> 3.81781 | K35: =0.201851534153057*J66 -> 3.7895413 | L35: =0.201851534153057*K66 -> 3.7525176 | M35: =0.201851534153057*L66 -> 3.7154609 | N35: =0.201851534153057*M66 -> 3.6783007 | O35: =0.201851534153057*N66 -> 3.6408728 | P35: =0.201851534153057*O66 -> 3.6032072 | ... AJ35: =0.201851534153057*AI66 -> 2.9279672
A36: Investment Services [Mrd EURO] | B36: Computed | C36: 16.9093 | D36: 17.9789 | E36: 19.5213 | F36: 19.3649 | G36: 19.9656 | H36: 20.5271 | I36: =0.160891037874836*H67 -> 17.978707 | J36: =0.160891037874836*I67 -> 13.89111 | K36: =0.160891037874836*J67 -> 13.788254 | L36: =0.160891037874836*K67 -> 13.653543 | M36: =0.160891037874836*L67 -> 13.518712 | N36: =0.160891037874836*M67 -> 13.383505 | O36: =0.160891037874836*N67 -> 13.247323 | P36: =0.160891037874836*O67 -> 13.110277 | ... AJ36: =0.160891037874836*AI67 -> 10.653415
A37: Investment Agriculture/Forestry/Fishing [Mrd EURO] | B37: Computed | C37: 1.1382 | D37: 1.1194 | E37: 1.129 | F37: 1.1885 | G37: 1.2523 | H37: 1.1821 | I37: =0.120203494864176*H68 -> 1.185555 | J37: =0.120203494864176*I68 -> 0.91600998 | K37: =0.120203494864176*J68 -> 0.90922746 | L37: =0.120203494864176*K68 -> 0.90034433 | M37: =0.120203494864176*L68 -> 0.89145329 | N37: =0.120203494864176*M68 -> 0.88253742 | O37: =0.120203494864176*N68 -> 0.87355732 | P37: =0.120203494864176*O68 -> 0.86452019 | ... AJ37: =0.120203494864176*AI68 -> 0.70250934
A38: Total Investment | B38: Computed | C38: =+SUM(C33:C37) -> 33.3662 | D38: =+SUM(D33:D37) -> 35.1534 | E38: =+SUM(E33:E37) -> 37.0236 | F38: =+SUM(F33:F37) -> 36.2046 | G38: =+SUM(G33:G37) -> 39.0835 | H38: =+SUM(H33:H37) -> 40.685 | I38: =+SUM(I33:I37) -> 34.715302 | J38: =+SUM(J33:J37) -> 26.822512 | ... AJ38: =+SUM(AJ33:AJ37) -> 20.570807
A40: Depreciation Industry [Mrd Euros] | B40: Computed | C40: 6.8306 | D40: 7.0159 | E40: 7.2788 | F40: 7.507 | G40: 7.657 | H40: 7.9939 | I40: =0.0854053900119604*H47 -> 7.5248554 | J40: =0.0854053900119604*I47 -> 7.6267916 | K40: =0.0854053900119604*J47 -> 7.5507316 | L40: =0.0854053900119604*K47 -> 7.4769076 | M40: =0.0854053900119604*L47 -> 7.4038095 | N40: =0.0854053900119604*M47 -> 7.3313703 | O40: =0.0854053900119604*N47 -> 7.259518 | P40: =0.0854053900119604*O47 -> 7.1881623 | ... AJ40: =0.0854053900119604*AI47 -> 5.8480355
A41: Depreciation Transport [Mrd Euros] | B41: Computed | C41: 1.9801 | D41: 1.9425 | E41: 1.97 | F41: 2.011 | G41: 2.2206 | H41: 2.2665 | I41: =0.0747889159710027*H48 -> 2.0418122 | J41: =0.0747889159710027*I48 -> 2.0305622 | K41: =0.0747889159710027*J48 -> 1.9879927 | L41: =0.0747889159710027*K48 -> 1.9477977 | M41: =0.0747889159710027*L48 -> 1.909549 | N41: =0.0747889159710027*M48 -> 1.8731 | O41: =0.0747889159710027*N48 -> 1.8383131 | P41: =0.0747889159710027*O48 -> 1.8050565 | ... AJ41: =0.0747889159710027*AI48 -> 1.3391822
A42: Depreciation Residential [Mrd EURO] | B42: Computed | C42: 9.368 | D42: 9.2889 | E42: 9.2216 | F42: 9.158 | G42: 9.082 | H42: 9.0321 | I42: =0.0386761793725209*H49 -> 8.7241432 | J42: =0.0386761793725209*I49 -> 8.5778349 | K42: =0.0386761793725209*J49 -> 8.3937354 | L42: =0.0386761793725209*K49 -> 8.2156627 | M42: =0.0386761793725209*L49 -> 8.0430453 | N42: =0.0386761793725209*M49 -> 7.8756709 | O42: =0.0386761793725209*N49 -> 7.7133326 | P42: =0.0386761793725209*O49 -> 7.5558255 | ... AJ42: =0.0386761793725209*AI49 -> 5.1860419
A43: Depreciation Services [Mrd EURO] | B43: Computed | C43: 16.7645 | D43: 17.1296 | E43: 17.6437 | F43: 18.4122 | G43: 18.4823 | H43: 19.0888 | I43: =0.0973324743081864*H50 -> 17.682011 | J43: =0.0973324743081864*I50 -> 17.710889 | K43: =0.0973324743081864*J50 -> 17.339101 | L43: =0.0973324743081864*K50 -> 16.993488 | M43: =0.0973324743081864*L50 -> 16.668403 | N43: =0.0973324743081864*M50 -> 16.361836 | O43: =0.0973324743081864*N50 -> 16.071947 | P43: =0.0973324743081864*O50 -> 15.79702 | ... AJ43: =0.0973324743081864*AI50 -> 12.017849
A44: Depreciation Agriculture/Forestry/Fishing [Mrd EURO] | B44: Computed | C44: 1.0005 | D44: 0.9901 | E44: 0.9827 | F44: 0.9994 | G44: 1.0046 | H44: 1.0195 | I44: =0.0980065492623211*H51 -> 1.0826195 | J44: =0.0980065492623211*I51 -> 1.0927079 | K44: =0.0980065492623211*J51 -> 1.0753903 | L44: =0.0980065492623211*K51 -> 1.0591053 | M44: =0.0980065492623211*L51 -> 1.0435457 | N44: =0.0980065492623211*M51 -> 1.0286396 | O44: =0.0980065492623211*N51 -> 1.0143207 | P44: =0.0980065492623211*O51 -> 1.0005249 | ... AJ44: =0.0980065492623211*AI51 -> 0.78656287
A45: Total Depreciation | B45: Computed | C45: =+SUM(C40:C44) -> 35.9437 | D45: =+SUM(D40:D44) -> 36.367 | E45: =+SUM(E40:E44) -> 37.0968 | F45: =+SUM(F40:F44) -> 38.0876 | G45: =+SUM(G40:G44) -> 38.4465 | H45: =+SUM(H40:H44) -> 39.4008 | I45: =SUM(I40:I44) -> 37.055441 | J45: =SUM(J40:J44) -> 37.038786 | K45: =SUM(K40:K44) -> 36.346951 | L45: =SUM(L40:L44) -> 35.692961 | M45: =SUM(M40:M44) -> 35.068352 | N45: =SUM(N40:N44) -> 34.470616 | O45: =SUM(O40:O44) -> 33.897432 | P45: =SUM(P40:P44) -> 33.346589 | ... AJ45: =SUM(AJ40:AJ44) -> 25.177672
A47: Capital Industry [Mrd Euros] | B47: Computed | C47: 80.6131 | D47: 82.1518 | E47: 83.4335 | F47: 84.2382 | G47: 86.0842 | H47: 88.1075 | I47: =+H47+I33-I40 -> 89.301058 | J47: =+I47+J33-J40 -> 88.410481 | K47: =+J47+K33-K40 -> 87.546086 | L47: =+K47+L33-L40 -> 86.69019 | M47: =+L47+M33-M40 -> 85.842009 | N47: =+M47+N33-N40 -> 85.000701 | O47: =+N47+O33-O40 -> 84.165206 | P47: =+O47+P33-P40 -> 83.33461 | ... AJ47: =+AI47+AJ33-AJ40 -> 67.79197
A48: Capital Transport [Mrd Euros] | B48: Computed | C48: 27.0182 | D48: 26.9132 | E48: 26.9947 | F48: 26.9721 | G48: 26.9326 | H48: 27.301 | I48: =+H48+I34-I41 -> 27.150577 | J48: =+I48+J34-J41 -> 26.581382 | K48: =+J48+K34-K41 -> 26.043936 | L48: =+K48+L34-L41 -> 25.532513 | M48: =+L48+M34-M41 -> 25.045155 | N48: =+M48+N34-N41 -> 24.580021 | O48: =+N48+O34-O41 -> 24.135348 | P48: =+O48+P34-P41 -> 23.709514 | ... AJ48: =+AI48+AJ34-AJ41 -> 17.687734
A49: Capital Residential [Mrd EURO] | B49: Computed | C49: 242.0709 | D49: 238.445 | E49: 234.9847 | F49: 231.1778 | G49: 228.2773 | H49: 225.5689 | I49: =+H49+I35-I42 -> 221.786 | J49: =+I49+J35-J42 -> 217.02597 | K49: =+J49+K35-K42 -> 212.42178 | L49: =+K49+L35-L42 -> 207.95863 | M49: =+L49+M35-M42 -> 203.63105 | N49: =+M49+N35-N42 -> 199.43368 | O49: =+N49+O35-O42 -> 195.36122 | P49: =+O49+P35-P42 -> 191.4086 | ... AJ49: =+AI49+AJ35-AJ42 -> 131.83071
A50: Capital Services [Mrd EURO] | B50: Computed | C50: 175.0649 | D50: 175.9142 | E50: 177.7918 | F50: 178.7445 | G50: 180.2278 | H50: 181.6661 | I50: =+H50+I36-I43 -> 181.9628 | J50: =+I50+J36-J43 -> 178.14302 | K50: =+J50+K36-K43 -> 174.59217 | L50: =+K50+L36-L43 -> 171.25222 | M50: =+L50+M36-M43 -> 168.10253 | N50: =+M50+N36-N43 -> 165.1242 | O50: =+N50+O36-O43 -> 162.29958 | P50: =+O50+P36-P43 -> 159.61284 | ... AJ50: =+AI50+AJ36-AJ43 -> 122.10771
A51: Capital Agriculture/Forestry/Fishing [Mrd EURO] | B51: Computed | C51: 10.1714 | D51: 10.3007 | E51: 10.447 | F51: 10.6361 | G51: 10.8838 | H51: 11.0464 | I51: =+H51+I37-I44 -> 11.149335 | J51: =+I51+J37-J44 -> 10.972638 | K51: =+J51+K37-K44 -> 10.806475 | L51: =+K51+L37-L44 -> 10.647714 | M51: =+L51+M37-M44 -> 10.495621 | N51: =+M51+N37-N44 -> 10.349519 | O51: =+N51+O37-O44 -> 10.208756 | P51: =+O51+P37-P44 -> 10.072751 | ... AJ51: =+AI51+AJ37-AJ44 -> 7.9415619
A52: Total Capital [Mrd EURO] | B52: Computed | C52: =+SUM(C47:C51) -> 534.9385 | D52: =+SUM(D47:D51) -> 533.7249 | E52: =+SUM(E47:E51) -> 533.6517 | F52: =+SUM(F47:F51) -> 531.7687 | G52: =+SUM(G47:G51) -> 532.4057 | H52: =+SUM(H47:H51) -> 533.6899 | I52: =+SUM(I47:I51) -> 531.34976 | J52: =+SUM(J47:J51) -> 521.13349 | ... AJ52: =+SUM(AJ47:AJ51) -> 347.35968
A55: Average Hours Worked by an engaged individual (H) gives | B55: Input | C55: 1873.6191 | D55: 1867.852 | E55: 1864.5884 | F55: 1864.5884 | G55: 1864.5884 | H55: 1864.5884 | I55: 1864.5884 | J55: 1864.5884 | K55: 1864.5884 | L55: 1864.5884 | M55: 1864.5884 | N55: 1864.5884 | O55: 1864.5884 | P55: 1864.5884 | Q55: 1864.5884 | R55: 1864.5884 | S55: 1864.5884 | T55: 1864.5884 | U55: 1864.5884 | V55: 1864.5884 | W55: 1864.5884 | X55: 1864.5884 | Y55: 1864.5884 | Z55: 1864.5884 | AA55: 1864.5884 | AB55: 1864.5884 | AC55: 1864.5884 | AD55: 1864.5884 | AE55: 1864.5884 | AF55: 1864.5884 | AG55: 1864.5884 | AH55: 1864.5884 | AI55: 1864.5884 | AJ55: 1864.5884
A56: Unemployment rate (u) | B56: Input | C56: 0.092 | D56: 0.072 | E56: 0.066 | F56: 0.07 | G56: 0.067 | H56: 0.061 | I56: 0.065 | J56: 0.064 | K56: 0.064 | L56: 0.064 | M56: 0.064 | N56: 0.064 | O56: 0.064 | P56: 0.064 | Q56: 0.064 | R56: 0.064 | S56: 0.064 | T56: 0.064 | U56: 0.064 | V56: 0.064 | W56: 0.064 | X56: 0.064 | Y56: 0.064 | Z56: 0.064 | AA56: 0.064 | AB56: 0.064 | AC56: 0.064 | AD56: 0.064 | AE56: 0.064 | AF56: 0.064 | AG56: 0.064 | AH56: 0.064 | AI56: 0.064 | AJ56: 0.064
A57: Working age population | B57: Input | C57: 6657888 | D57: 6624826 | E57: 6587247.2 | F57: 6549668.5 | G57: 6512089.7 | H57: 6474510.9 | I57: 6436932.2 | J57: 6399353.4 | K57: 6361774.6 | L57: 6324195.8 | M57: 6286617.1 | N57: 6249038.3 | O57: 6211459.5 | P57: 6173880.8 | Q57: 6136302 | R57: 6098723.2 | S57: 6061144.5 | T57: 6023565.7 | U57: 5985986.9 | V57: 5948408.2 | W57: 5910829.4 | X57: 5873250.6 | Y57: 5835671.8 | Z57: 5798093.1 | AA57: 5760514.3 | AB57: 5722935.5 | AC57: 5685356.8 | AD57: 5647778 | AE57: 5610199.2 | AF57: 5572620.5 | AG57: 5535041.7 | AH57: 5497462.9 | AI57: 5459884.2 | AJ57: 5422305.4
A58: Labour Force Participation Rate | B58: Input | C58: 0.75 | D58: 0.757 | E58: 0.76 | F58: 0.749 | G58: 0.76 | H58: 0.774 | I58: 0.788 | J58: 0.792 | K58: 0.79423077 | L58: 0.79646154 | M58: 0.79869231 | N58: 0.80092308 | O58: 0.80315385 | P58: 0.80538462 | Q58: 0.80761538 | R58: 0.80984615 | S58: 0.81207692 | T58: 0.81430769 | U58: 0.81653846 | V58: 0.81876923 | W58: 0.821 | X58: 0.82323077 | Y58: 0.82546154 | Z58: 0.82769231 | AA58: 0.82992308 | AB58: 0.83215385 | AC58: 0.83438462 | AD58: 0.83661538 | AE58: 0.83884615 | AF58: 0.84107692 | AG58: 0.84330769 | AH58: 0.84553846 | AI58: 0.84776923 | AJ58: 0.85
A59: Labour [Hours worked by engaged people] | B59: Computed | C59: =C55*(1-C56)*C57*C58 -> 8.4950296e+09 | D59: =D55*(1-D56)*D57*D58 -> 8.6928222e+09 | E59: =E55*(1-E56)*E57*E58 -> 8.718613e+09 | F59: =F55*(1-F56)*F57*F58 -> 8.5068162e+09 | G59: =G55*(1-G56)*G57*G58 -> 8.6099093e+09 | H59: =H55*(1-H56)*H57*H58 -> 8.773977e+09 | I59: =I55*(1-I56)*I57*I58 -> 8.8430021e+09 | J59: =J55*(1-J56)*J57*J58 -> 8.8454533e+09 | ... AJ59: =AJ55*(1-AJ56)*AJ57*AJ58 -> 8.0438084e+09
A61: TFP | B61: Computed | C61: - | D61: =+((D462/0.14)^1.93)*0.00000102 + 0.00000039 -> 3.1326113e-06 | E61: =+((E462/0.14)^1.93)*0.00000102 + 0.00000039 -> 3.0789659e-06 | F61: =+((F462/0.14)^1.93)*0.00000102 + 0.00000039 -> 3.1379239e-06 | G61: =+((G462/0.14)^1.93)*0.00000102 + 0.00000039 -> 3.0652364e-06 | H61: =+((H462/0.14)^1.93)*0.00000102 + 0.00000039 -> 3.0557918e-06 | I61: =+((I462/0.14)^1.93)*0.00000102 + 0.00000039 -> 2.6567081e-06 | J61: =+((J462/0.14)^1.93)*0.00000102 + 0.00000039 -> 2.6519258e-06 | K61: =+((K462/0.14)^1.93)*0.00000102 + 0.00000039 -> 2.6465901e-06 | ... AJ61: =+((AJ462/0.14)^1.93)*0.00000102 + 0.00000039 -> 2.4518991e-06
A63: GDP [Mrd Euros] | B63: Computed | C63: =189.1 -> 189.1 | D63: =194.6 -> 194.6 | E63: =200 -> 200 | F63: =183.6 -> 183.6 | G63: =193.8 -> 193.8 | H63: =207.3 -> 207.3 | I63: =+((I61*((I52)^0.3)*(I59^0.7))) -> 160.16875 | J63: =+((J61*((J52)^0.3)*(J59^0.7))) -> 158.9828 | K63: =+((K61*((K52)^0.3)*(K59^0.7))) -> 157.42954 | L63: =+((L61*((L52)^0.3)*(L59^0.7))) -> 155.8749 | M63: =+((M61*((M52)^0.3)*(M59^0.7))) -> 154.31591 | N63: =+((N61*((N52)^0.3)*(N59^0.7))) -> 152.7457 | O63: =+((O61*((O52)^0.3)*(O59^0.7))) -> 151.16551 | P63: =+((P61*((P52)^0.3)*(P59^0.7))) -> 149.56725 | ... AJ63: =+((AJ61*((AJ52)^0.3)*(AJ59^0.7))) -> 121.77542
A64: GDP Industry [Mrd Euro] | B64: Computed | C64: =0.230432832489315*C63 -> 43.574849 | D64: =0.230432832489315*D63 -> 44.842229 | E64: =0.230432832489315*E63 -> 46.086566 | F64: =0.230432832489315*F63 -> 42.307468 | G64: =0.230432832489315*G63 -> 44.657883 | H64: =0.230432832489315*H63 -> 47.768726 | I64: =0.230432832489315*I63 -> 36.908139 | J64: =0.230432832489315*J63 -> 36.634856 | ... AJ64: =0.230432832489315*AJ63 -> 28.061054
A65: GDP Transport [Mrd Euro] | B65: Computed | C65: =0.0648538045034303*C63 -> 12.263854 | D65: =0.0648538045034303*D63 -> 12.62055 | E65: =0.0648538045034303*E63 -> 12.970761 | F65: =0.0648538045034303*F63 -> 11.907159 | G65: =0.0648538045034303*G63 -> 12.568667 | H65: =0.0648538045034303*H63 -> 13.444194 | I65: =0.0648538045034303*I63 -> 10.387553 | J65: =0.0648538045034303*J63 -> 10.310639 | ... AJ65: =0.0648538045034303*AJ63 -> 7.897599
A66: GDP Residential [Mrd Euro] | B66: Computed | C66: =0.11808764418997*C63 -> 22.330374 | D66: =0.11808764418997*D63 -> 22.979856 | E66: =0.11808764418997*E63 -> 23.617529 | F66: =0.11808764418997*F63 -> 21.680891 | G66: =0.11808764418997*G63 -> 22.885385 | H66: =0.11808764418997*H63 -> 24.479569 | I66: =0.11808764418997*I63 -> 18.913951 | J66: =0.11808764418997*J63 -> 18.773904 | ... AJ66: =0.11808764418997*AJ63 -> 14.380172
A67: GDP Services [Mrd Euro] | B67: Computed | C67: =0.53904781352922*C63 -> 101.93394 | D67: =0.53904781352922*D63 -> 104.8987 | E67: =0.53904781352922*E63 -> 107.80956 | F67: =0.53904781352922*F63 -> 98.969179 | G67: =0.53904781352922*G63 -> 104.46747 | H67: =0.53904781352922*H63 -> 111.74461 | I67: =0.53904781352922*I63 -> 86.338616 | J67: =0.53904781352922*J63 -> 85.699328 | ... AJ67: =0.53904781352922*AJ63 -> 65.642772
A68: GDP Agriculture/Forestry/Fishing [Mrd Euro] | B68: Computed | C68: =0.0475779052880645*C63 -> 8.9969819 | D68: =0.0475779052880645*D63 -> 9.2586604 | E68: =0.0475779052880645*E63 -> 9.5155811 | F68: =0.0475779052880645*F63 -> 8.7353034 | G68: =0.0475779052880645*G63 -> 9.220598 | H68: =0.0475779052880645*H63 -> 9.8628998 | I68: =0.0475779052880645*I63 -> 7.6204938 | J68: =0.0475779052880645*J63 -> 7.5640684 | ... AJ68: =0.0475779052880645*AJ63 -> 5.7938192
A71: Total Useful exergy [TJ] | B71: Computed | C71: 184372.38 | D71: 184124.9 | E71: 183477.17 | F71: 170891.44 | G71: 174119.51 | H71: 177140.85 | I71: =+I63*10^3 -> 160168.75 | J71: =+J63*10^3 -> 158982.8 | K71: =+K63*10^3 -> 157429.54 | L71: =+L63*10^3 -> 155874.9 | M71: =+M63*10^3 -> 154315.91 | N71: =+N63*10^3 -> 152745.7 | O71: =+O63*10^3 -> 151165.51 | P71: =+P63*10^3 -> 149567.25 | ... AJ71: =+AJ63*10^3 -> 121775.42
A72: Total Final exergy [TJ] | C72: 774063.77 | D72: 755634.98 | E72: 778696.11 | F72: 724009.39 | G72: 743241.04 | H72: 752302.28 | I72: =+I71/I462 -> 756420.01 | J72: =+J71/J462 -> 751641.24 | K72: =+K71/K462 -> 745209.07 | L72: =+L71/L462 -> 738845.07 | M72: =+M71/M462 -> 732538.32 | N72: =+N71/N462 -> 726270.79 | O72: =+O71/O462 -> 720039.58 | P72: =+P71/P462 -> 713824.75 | ... AJ72: =+AJ71/AJ462 -> 604024.81
A74: Share final exergy industry [-] | C74: =Aggregate_Efficiency_BAU!C5 -> 0.27142931 | D74: =Aggregate_Efficiency_BAU!D5 -> 0.27119604 | E74: =Aggregate_Efficiency_BAU!E5 -> 0.2732505 | F74: =Aggregate_Efficiency_BAU!F5 -> 0.28555072 | G74: =Aggregate_Efficiency_BAU!G5 -> 0.28462773 | H74: =Aggregate_Efficiency_BAU!H5 -> 0.27572585 | I74: =Aggregate_Efficiency_BAU!I5 -> 0.25944504 | J74: =Aggregate_Efficiency_BAU!J5 -> 0.25617084 | ... AJ74: =Aggregate_Efficiency_BAU!AJ5 -> 0.17104153
A75: Share final exergy transport [-] | C75: =Aggregate_Efficiency_BAU!C6 -> 0.3546432 | D75: =Aggregate_Efficiency_BAU!D6 -> 0.35679786 | E75: =Aggregate_Efficiency_BAU!E6 -> 0.36315882 | F75: =Aggregate_Efficiency_BAU!F6 -> 0.32899597 | G75: =Aggregate_Efficiency_BAU!G6 -> 0.34997126 | H75: =Aggregate_Efficiency_BAU!H6 -> 0.36009084 | I75: =Aggregate_Efficiency_BAU!I6 -> 0.372118 | J75: =Aggregate_Efficiency_BAU!J6 -> 0.37430883 | ... AJ75: =Aggregate_Efficiency_BAU!AJ6 -> 0.4312704
A76: Share final exergy services [-] | C76: =Aggregate_Efficiency_BAU!C7 -> 0.11098227 | D76: =Aggregate_Efficiency_BAU!D7 -> 0.11418082 | E76: =Aggregate_Efficiency_BAU!E7 -> 0.11117733 | F76: =Aggregate_Efficiency_BAU!F7 -> 0.10630522 | G76: =Aggregate_Efficiency_BAU!G7 -> 0.10424487 | H76: =Aggregate_Efficiency_BAU!H7 -> 0.10934643 | I76: =Aggregate_Efficiency_BAU!I7 -> 0.15300365 | J76: =Aggregate_Efficiency_BAU!J7 -> 0.15238571 | ... AJ76: =Aggregate_Efficiency_BAU!AJ7 -> 0.13631935
A77: Share final exergy residencial [-] | C77: =Aggregate_Efficiency_BAU!C8 -> 0.15680348 | D77: =Aggregate_Efficiency_BAU!D8 -> 0.15992742 | E77: =Aggregate_Efficiency_BAU!E8 -> 0.15925696 | F77: =Aggregate_Efficiency_BAU!F8 -> 0.17964943 | G77: =Aggregate_Efficiency_BAU!G8 -> 0.17499831 | H77: =Aggregate_Efficiency_BAU!H8 -> 0.16410964 | I77: =Aggregate_Efficiency_BAU!I8 -> 0.12335774 | J77: =Aggregate_Efficiency_BAU!J8 -> 0.12518344 | ... AJ77: =Aggregate_Efficiency_BAU!AJ8 -> 0.17265148
A78: Share Final Exergy Agriculture/forestry/Fishing [-] | C78: =Aggregate_Efficiency_BAU!C9 -> 0.027798035 | D78: =Aggregate_Efficiency_BAU!D9 -> 0.028064646 | E78: =Aggregate_Efficiency_BAU!E9 -> 0.028618365 | F78: =Aggregate_Efficiency_BAU!F9 -> 0.032768238 | G78: =Aggregate_Efficiency_BAU!G9 -> 0.03372055 | H78: =Aggregate_Efficiency_BAU!H9 -> 0.029928558 | I78: =Aggregate_Efficiency_BAU!I9 -> 0.023282591 | J78: =Aggregate_Efficiency_BAU!J9 -> 0.022797523 | ... AJ78: =Aggregate_Efficiency_BAU!AJ9 -> 0.010185772
A79: Share Final Exergy Energy industry own use [-] | C79: =Aggregate_Efficiency_BAU!C10 -> 0.078343711 | D79: =Aggregate_Efficiency_BAU!D10 -> 0.069833206 | E79: =Aggregate_Efficiency_BAU!E10 -> 0.06453802 | F79: =Aggregate_Efficiency_BAU!F10 -> 0.066730424 | G79: =Aggregate_Efficiency_BAU!G10 -> 0.05243729 | H79: =Aggregate_Efficiency_BAU!H10 -> 0.060798684 | I79: =Aggregate_Efficiency_BAU!I10 -> 0.068792975 | J79: =Aggregate_Efficiency_BAU!J10 -> 0.06915366 | ... AJ79: =Aggregate_Efficiency_BAU!AJ10 -> 0.078531474
A81: Final exergy Industry [TJ] | B81: Computed | C81: =+C74*C$72 -> 210103.59 | D81: =+D74*D$72 -> 204925.21 | E81: =+E74*E$72 -> 212779.1 | F81: =+F74*F$72 -> 206741.4 | G81: =+G74*G$72 -> 211547.01 | H81: =+H74*H$72 -> 207429.19 | I81: =+I74*I$72 -> 196249.42 | J81: =+J74*J$72 -> 192548.57 | ... AJ81: =+AJ74*AJ$72 -> 103313.33
A82: Final exergy Transport [TJ] | B82: Computed | C82: =+C75*C$72 -> 274516.45 | D82: =+D75*D$72 -> 269608.95 | E82: =+E75*E$72 -> 282790.36 | F82: =+F75*F$72 -> 238196.17 | G82: =+G75*G$72 -> 260113 | H82: =+H75*H$72 -> 270897.16 | I82: =+I75*I$72 -> 281477.5 | J82: =+J75*J$72 -> 281345.95 | ... AJ82: =+AJ75*AJ$72 -> 260498.02
A83: Final exergy Services [TJ] | B83: Computed | C83: =+C76*C$72 -> 85907.357 | D83: =+D76*D$72 -> 86279.024 | E83: =+E76*E$72 -> 86573.356 | F83: =+F76*F$72 -> 76965.977 | G83: =+G76*G$72 -> 77479.063 | H83: =+H76*H$72 -> 82261.565 | I83: =+I76*I$72 -> 115735.02 | J83: =+J76*J$72 -> 114539.39 | ... AJ83: =+AJ76*AJ$72 -> 82340.267
A84: Final exergy Residencial [TJ] | B84: Computed | C84: =+C77*C$72 -> 121375.89 | D84: =+D77*D$72 -> 120846.75 | E84: =+E77*E$72 -> 124012.78 | F84: =+F77*F$72 -> 130067.87 | G84: =+G77*G$72 -> 130065.92 | H84: =+H77*H$72 -> 123460.06 | I84: =+I77*I$72 -> 93310.265 | J84: =+J77*J$72 -> 94093.033 | ... AJ84: =+AJ77*AJ$72 -> 104285.77
A85: Final Exergy Agriculture/Forestry/fishing [TJ] | B85: Computed | C85: =+C78*C$72 -> 21517.452 | D85: =+D78*D$72 -> 21206.628 | E85: =+E78*E$72 -> 22285.01 | F85: =+F78*F$72 -> 23724.512 | G85: =+G78*G$72 -> 25062.497 | H85: =+H78*H$72 -> 22515.322 | I85: =+I78*I$72 -> 17611.418 | J85: =+J78*J$72 -> 17135.559 | ... AJ85: =+AJ78*AJ$72 -> 6152.4591
A86: Final Exergy Energy industry own use [TJ] | B86: Computed | C86: =+C79*C$72 -> 60643.029 | D86: =+D79*D$72 -> 52768.413 | E86: =+E79*E$72 -> 50255.505 | F86: =+F79*F$72 -> 48313.454 | G86: =+G79*G$72 -> 38973.546 | H86: =+H79*H$72 -> 45738.988 | I86: =+I79*I$72 -> 52036.383 | J86: =+J79*J$72 -> 51978.743 | ... AJ86: =+AJ79*AJ$72 -> 47434.958
A88: Share final exergy industry electricity | C88: =Aggregate_Efficiency_BAU!C19 -> 0.2970747 | D88: =Aggregate_Efficiency_BAU!D19 -> 0.30075756 | E88: =Aggregate_Efficiency_BAU!E19 -> 0.30235708 | F88: =Aggregate_Efficiency_BAU!F19 -> 0.30163627 | G88: =Aggregate_Efficiency_BAU!G19 -> 0.30591526 | H88: =Aggregate_Efficiency_BAU!H19 -> 0.31318182 | I88: =Aggregate_Efficiency_BAU!I19 -> 0.31035417 | J88: =Aggregate_Efficiency_BAU!J19 -> 0.31226091 | ... AJ88: =Aggregate_Efficiency_BAU!AJ19 -> 0.3424064
A89: Share final exergy transport electricity | C89: =Aggregate_Efficiency_BAU!C20 -> 0.0068374586 | D89: =Aggregate_Efficiency_BAU!D20 -> 0.0068392983 | E89: =Aggregate_Efficiency_BAU!E20 -> 0.0067376336 | F89: =Aggregate_Efficiency_BAU!F20 -> 0.0070045484 | G89: =Aggregate_Efficiency_BAU!G20 -> 0.0070586514 | H89: =Aggregate_Efficiency_BAU!H20 -> 0.0070199832 | I89: =Aggregate_Efficiency_BAU!I20 -> 0.0076482888 | J89: =Aggregate_Efficiency_BAU!J20 -> 0.0079060577 | ... AJ89: =Aggregate_Efficiency_BAU!AJ20 -> 0.014608048
A90: Share final exergy services electricity | C90: =Aggregate_Efficiency_BAU!C21 -> 0.73677033 | D90: =Aggregate_Efficiency_BAU!D21 -> 0.72971057 | E90: =Aggregate_Efficiency_BAU!E21 -> 0.73192341 | F90: =Aggregate_Efficiency_BAU!F21 -> 0.7583611 | G90: =Aggregate_Efficiency_BAU!G21 -> 0.73914204 | H90: =Aggregate_Efficiency_BAU!H21 -> 0.75301205 | I90: =Aggregate_Efficiency_BAU!I21 -> 0.74281677 | J90: =Aggregate_Efficiency_BAU!J21 -> 0.7426465 | ... AJ90: =Aggregate_Efficiency_BAU!AJ21 -> 0.72764558
A91: Share final exergy residencial electricity | C91: =Aggregate_Efficiency_BAU!C22 -> 0.40105887 | D91: =Aggregate_Efficiency_BAU!D22 -> 0.41096146 | E91: =Aggregate_Efficiency_BAU!E22 -> 0.41088932 | F91: =Aggregate_Efficiency_BAU!F22 -> 0.40750368 | G91: =Aggregate_Efficiency_BAU!G22 -> 0.42720606 | H91: =Aggregate_Efficiency_BAU!H22 -> 0.43001357 | I91: =Aggregate_Efficiency_BAU!I22 -> 0.43031559 | J91: =Aggregate_Efficiency_BAU!J22 -> 0.43471854 | ... AJ91: =Aggregate_Efficiency_BAU!AJ22 -> 0.53758466
A92: Share final exergy Agriculture/forestry/Fishing electricity | C92: =Aggregate_Efficiency_BAU!C23 -> 0.17678412 | D92: =Aggregate_Efficiency_BAU!D23 -> 0.18850159 | E92: =Aggregate_Efficiency_BAU!E23 -> 0.16560611 | F92: =Aggregate_Efficiency_BAU!F23 -> 0.16584001 | G92: =Aggregate_Efficiency_BAU!G23 -> 0.17929811 | H92: =Aggregate_Efficiency_BAU!H23 -> 0.16275005 | I92: =Aggregate_Efficiency_BAU!I23 -> 0.1699724 | J92: =Aggregate_Efficiency_BAU!J23 -> 0.17022649 | ... AJ92: =Aggregate_Efficiency_BAU!AJ23 -> 0.17575267
A93: Share final exergy Energy industry own electricity | C93: =Aggregate_Efficiency_BAU!C24 -> 0.20857445 | D93: =Aggregate_Efficiency_BAU!D24 -> 0.19412629 | E93: =Aggregate_Efficiency_BAU!E24 -> 0.17649312 | F93: =Aggregate_Efficiency_BAU!F24 -> 0.17373555 | G93: =Aggregate_Efficiency_BAU!G24 -> 0.18464616 | H93: =Aggregate_Efficiency_BAU!H24 -> 0.17476388 | I93: =Aggregate_Efficiency_BAU!I24 -> 0.17891093 | J93: =Aggregate_Efficiency_BAU!J24 -> 0.17800461 | ... AJ93: =Aggregate_Efficiency_BAU!AJ24 -> 0.15207889
A94: Share final exergy industry coal/coke | C94: =Aggregate_Efficiency_BAU!C25 -> 0.069253404 | D94: =Aggregate_Efficiency_BAU!D25 -> 0.061170092 | E94: =Aggregate_Efficiency_BAU!E25 -> 0.059562702 | F94: =Aggregate_Efficiency_BAU!F25 -> 0.064743037 | G94: =Aggregate_Efficiency_BAU!G25 -> 0.054408395 | H94: =Aggregate_Efficiency_BAU!H25 -> 0.06007097 | I94: =Aggregate_Efficiency_BAU!I25 -> 0.052651272 | J94: =Aggregate_Efficiency_BAU!J25 -> 0.049897148 | ... AJ94: =Aggregate_Efficiency_BAU!AJ25 -> 0
A95: Share final exergy industry oil | C95: =Aggregate_Efficiency_BAU!C26 -> 0.078378662 | D95: =Aggregate_Efficiency_BAU!D26 -> 0.077637821 | E95: =Aggregate_Efficiency_BAU!E26 -> 0.069863979 | F95: =Aggregate_Efficiency_BAU!F26 -> 0.070795621 | G95: =Aggregate_Efficiency_BAU!G26 -> 0.069265914 | H95: =Aggregate_Efficiency_BAU!H26 -> 0.082289434 | I95: =Aggregate_Efficiency_BAU!I26 -> 0.070176562 | J95: =Aggregate_Efficiency_BAU!J26 -> 0.068490573 | ... AJ95: =Aggregate_Efficiency_BAU!AJ26 -> 0.023330965
A96: Share final exergy industry natural gas | C96: =Aggregate_Efficiency_BAU!C27 -> 0.27024948 | D96: =Aggregate_Efficiency_BAU!D27 -> 0.2755297 | E96: =Aggregate_Efficiency_BAU!E27 -> 0.27458465 | F96: =Aggregate_Efficiency_BAU!F27 -> 0.2640436 | G96: =Aggregate_Efficiency_BAU!G27 -> 0.29137166 | H96: =Aggregate_Efficiency_BAU!H27 -> 0.25694602 | I96: =Aggregate_Efficiency_BAU!I27 -> 0.28170259 | J96: =Aggregate_Efficiency_BAU!J27 -> 0.28512852 | ... AJ96: =Aggregate_Efficiency_BAU!AJ27 -> 0.35410875
A97: Share final exergy industry waste/c. renewables | C97: =Aggregate_Efficiency_BAU!C28 -> 0.26201817 | D97: =Aggregate_Efficiency_BAU!D28 -> 0.25876213 | E97: =Aggregate_Efficiency_BAU!E28 -> 0.26551584 | F97: =Aggregate_Efficiency_BAU!F28 -> 0.27237961 | G97: =Aggregate_Efficiency_BAU!G28 -> 0.25652296 | H97: =Aggregate_Efficiency_BAU!H28 -> 0.27022414 | I97: =Aggregate_Efficiency_BAU!I28 -> 0.26829567 | J97: =Aggregate_Efficiency_BAU!J28 -> 0.26932365 | ... AJ97: =Aggregate_Efficiency_BAU!AJ28 -> 0.28015389
A98: Share final exergy industry heat | C98: =Aggregate_Efficiency_BAU!C29 -> 0.023025582 | D98: =Aggregate_Efficiency_BAU!D29 -> 0.026142703 | E98: =Aggregate_Efficiency_BAU!E29 -> 0.028115736 | F98: =Aggregate_Efficiency_BAU!F29 -> 0.026401859 | G98: =Aggregate_Efficiency_BAU!G29 -> 0.022515809 | H98: =Aggregate_Efficiency_BAU!H29 -> 0.017287611 | I98: =Aggregate_Efficiency_BAU!I29 -> 0.016819733 | J98: =Aggregate_Efficiency_BAU!J29 -> 0.014899195 | ... AJ98: =Aggregate_Efficiency_BAU!AJ29 -> 0
A99: Share final exergy transport coal/coke | C99: =Aggregate_Efficiency_BAU!C30 -> 0 | D99: =Aggregate_Efficiency_BAU!D30 -> 0 | E99: =Aggregate_Efficiency_BAU!E30 -> 0 | F99: =Aggregate_Efficiency_BAU!F30 -> 0 | G99: =Aggregate_Efficiency_BAU!G30 -> 0 | H99: =Aggregate_Efficiency_BAU!H30 -> 0 | I99: =Aggregate_Efficiency_BAU!I30 -> 0 | J99: =Aggregate_Efficiency_BAU!J30 -> 0 | ... AJ99: =Aggregate_Efficiency_BAU!AJ30 -> 0
... A125: Share Final Exergy Energy industry own use Heat | C125: =Aggregate_Efficiency_BAU!C56 -> 0.11153732 | D125: =Aggregate_Efficiency_BAU!D56 -> 0.12514663 | E125: =Aggregate_Efficiency_BAU!E56 -> 0.13516367 | F125: =Aggregate_Efficiency_BAU!F56 -> 0.14874172 | G125: =Aggregate_Efficiency_BAU!G56 -> 0.13776063 | H125: =Aggregate_Efficiency_BAU!H56 -> 0.069597049 | I125: =Aggregate_Efficiency_BAU!I56 -> 0.12263458 | J125: =Aggregate_Efficiency_BAU!J56 -> 0.12385827 | ... AJ125: =Aggregate_Efficiency_BAU!AJ56 -> 0.15329375
A127: Final exergy industry electricity [TJ] | B127: Computed | C127: =+C88*C81 -> 62416.462 | D127: =+D88*D81 -> 61632.807 | E127: =+E88*E81 -> 64335.268 | F127: =+F88*F81 -> 62360.707 | G127: =+G88*G81 -> 64715.458 | H127: =+H88*H81 -> 64963.051 | I127: =+I88*I81 -> 60906.826 | J127: =+J88*J81 -> 60125.39 | ... AJ127: =+AJ88*AJ81 -> 35375.145
A128: Final exergy transport electricity [TJ] | B128: Computed | C128: =+C89*C82 -> 1876.9949 | D128: =+D89*D82 -> 1843.936 | E128: =+E89*E82 -> 1905.3378 | F128: =+F89*F82 -> 1668.4566 | G128: =+G89*G82 -> 1836.047 | H128: =+H89*H82 -> 1901.6935 | I128: =+I89*I82 -> 2152.8212 | J128: =+J89*J82 -> 2224.3373 | ... AJ128: =+AJ89*AJ82 -> 3805.3676
A129: Final exergy services electricity [TJ] | B129: Computed | C129: =+C90*C83 -> 63293.991 | D129: =+D90*D83 -> 62958.716 | E129: =+E90*E83 -> 63365.066 | F129: =+F90*F83 -> 58368.003 | G129: =+G90*G83 -> 57268.032 | H129: =+H90*H83 -> 61943.949 | I129: =+I90*I83 -> 85969.917 | J129: =+J90*J83 -> 85062.275 | ... AJ129: =+AJ90*AJ83 -> 59914.532
A130: Final exergy residencial electricity [TJ] | B130: Computed | C130: =+C91*C84 -> 48678.877 | D130: =+D91*D84 -> 49663.359 | E130: =+E91*E84 -> 50955.526 | F130: =+F91*F84 -> 53003.138 | G130: =+G91*G84 -> 55564.951 | H130: =+H91*H84 -> 53089.5 | I130: =+I91*I84 -> 40152.862 | J130: =+J91*J84 -> 40903.986 | ... AJ130: =+AJ91*AJ84 -> 56062.433
A131: Final Exergy Agriculture/Forestry/fishing electricity [TJ] | B131: Computed | C131: =+C92*C85 -> 3803.9437 | D131: =+D92*D85 -> 3997.483 | E131: =+E92*E85 -> 3690.5337 | F131: =+F92*F85 -> 3934.4732 | G131: =+G92*G85 -> 4493.6582 | H131: =+H92*H85 -> 3664.3698 | I131: =+I92*I85 -> 2993.455 | J131: =+J92*J85 -> 2916.926 | ... AJ131: =+AJ92*AJ85 -> 1081.3111
A132: Final Exergy Energy industry own use electricity [TJ] | B132: Computed | C132: =+C93*C86 -> 12648.586 | D132: =+D93*D86 -> 10243.736 | E132: =+E93*E86 -> 8869.7511 | F132: =+F93*F86 -> 8393.7643 | G132: =+G93*G86 -> 7196.3154 | H132: =+H93*H86 -> 7993.5231 | I132: =+I93*I86 -> 9309.8775 | J132: =+J93*J86 -> 9252.456 | ... AJ132: =+AJ93*AJ86 -> 7213.856
A133: Final exergy industry coal/coke [TJ] | B133: Computed | C133: =+C94*C$81 -> 14550.389 | D133: =+D94*D$81 -> 12535.294 | E133: =+E94*E$81 -> 12673.698 | F133: =+F94*F$81 -> 13385.066 | G133: =+G94*G$81 -> 11509.933 | H133: =+H94*H$81 -> 12460.473 | I133: =+I94*I$81 -> 10332.782 | J133: =+J94*J$81 -> 9607.6243 | ... AJ133: =+AJ94*AJ$81 -> 0
A134: Final exergy industry oil [TJ] | B134: Computed | C134: =+C95*C$81 -> 16467.639 | D134: =+D95*D$81 -> 15909.947 | E134: =+E95*E$81 -> 14865.595 | F134: =+F95*F$81 -> 14636.386 | G134: =+G95*G$81 -> 14652.997 | H134: =+H95*H$81 -> 17069.23 | I134: =+I95*I$81 -> 13772.11 | J134: =+J95*J$81 -> 13187.762 | ... AJ134: =+AJ95*AJ$81 -> 2410.3996
A135: Final exergy industry natural gas [TJ] | B135: Computed | C135: =+C96*C$81 -> 56780.386 | D135: =+D96*D$81 -> 56462.984 | E135: =+E96*E$81 -> 58425.875 | F135: =+F96*F$81 -> 54588.744 | G135: =+G96*G$81 -> 61638.804 | H135: =+H96*H$81 -> 53298.105 | I135: =+I96*I$81 -> 55283.971 | J135: =+J96*J$81 -> 54901.087 | ... AJ135: =+AJ96*AJ$81 -> 36584.153
A136: Final exergy industry c. renewables/waste [TJ] | B136: Computed | C136: =+C97*C$81 -> 55050.96 | D136: =+D97*D$81 -> 53026.884 | E136: =+E97*E$81 -> 56496.222 | F136: =+F97*F$81 -> 56312.143 | G136: =+G97*G$81 -> 54266.665 | H136: =+H97*H$81 -> 56052.374 | I136: =+I97*I$81 -> 52652.871 | J136: =+J97*J$81 -> 51857.883 | ... AJ136: =+AJ97*AJ$81 -> 28943.631
A137: Final exergy industry heat [TJ] | B137: Computed | C137: =+C98*C$81 -> 4837.7575 | D137: =+D98*D$81 -> 5357.2991 | E137: =+E98*E$81 -> 5982.441 | F137: =+F98*F$81 -> 5458.3575 | G137: =+G98*G$81 -> 4763.1521 | H137: =+H98*H$81 -> 3585.9551 | I137: =+I98*I$81 -> 3300.8629 | J137: =+J98*J$81 -> 2868.8186 | ... AJ137: =+AJ98*AJ$81 -> 0
A138: Final exergy transport coal/coke [TJ] | B138: Computed | C138: =+C$82*C99 -> 0 | D138: =+D$82*D99 -> 0 | E138: =+E$82*E99 -> 0 | F138: =+F$82*F99 -> 0 | G138: =+G$82*G99 -> 0 | H138: =+H$82*H99 -> 0 | I138: =+I$82*I99 -> 0 | J138: =+J$82*J99 -> 0 | ... AJ138: =+AJ$82*AJ99 -> 0
A139: Final exergy transport oil [TJ] | B139: Computed | C139: =+C$82*C100 -> 259830.69 | D139: =+D$82*D100 -> 254304.78 | E139: =+E$82*E100 -> 266536.6 | F139: =+F$82*F100 -> 223400.91 | G139: =+G$82*G100 -> 241194.51 | H139: =+H$82*H100 -> 251315.9 | I139: =+I$82*I100 -> 262425.25 | J139: =+J$82*J100 -> 262008.71 | ... AJ139: =+AJ$82*AJ100 -> 235518.65
A140: Final exergy transport natural gas [TJ] | B140: Computed | C140: =+C$82*C101 -> 686.36884 | D140: =+D$82*D101 -> 727.69041 | E140: =+E$82*E101 -> 813.06146 | F140: =+F$82*F101 -> 939.79023 | G140: =+G$82*G101 -> 1116.503 | H140: =+H$82*H101 -> 1506.0274 | I140: =+I$82*I101 -> 1339.0285 | J140: =+J$82*J101 -> 1419.3831 | ... AJ140: =+AJ$82*AJ101 -> 3263.6762
A141: Final exergy transport c. renewables/waste [TJ] | B141: Computed | C141: =+C$82*C102 -> 12122.396 | D141: =+D$82*D102 -> 12732.541 | E141: =+E$82*E102 -> 13535.368 | F141: =+F$82*F102 -> 12187.01 | G141: =+G$82*G102 -> 15965.945 | H141: =+H$82*H102 -> 16173.534 | I141: =+I$82*I102 -> 15560.398 | J141: =+J$82*J102 -> 15693.518 | ... AJ141: =+AJ$82*AJ102 -> 17910.327
A142: Final exergy transport heat [TJ] | B142: Computed | C142: =+C$82*C103 -> 0 | D142: =+D$82*D103 -> 0 | E142: =+E$82*E103 -> 0 | F142: =+F$82*F103 -> 0 | G142: =+G$82*G103 -> 0 | H142: =+H$82*H103 -> 0 | I142: =+I$82*I103 -> 0 | J142: =+J$82*J103 -> 0 | ... AJ142: =+AJ$82*AJ103 -> 0
...

Sheet Aggregate_Efficiency_Decarboniz
A1: Scenarios from 2023 onwards - National Roadmap 2050
C2: 2017 | D2: 2018 | E2: 2019 | F2: 2020 | G2: 2021 | H2: 2022 | I2: 2023 | J2: 2024 | K2: 2025 | L2: 2026 | M2: 2027 | N2: 2028 | O2: 2029 | P2: 2030 | Q2: 2031 | R2: 2032 | S2: 2033 | T2: 2034 | U2: 2035 | V2: 2036 | W2: 2037 | X2: 2038 | Y2: 2039 | Z2: 2040 | AA2: 2041 | AB2: 2042 | AC2: 2043 | AD2: 2044 | AE2: 2045 | AF2: 2046 | AG2: 2047 | AH2: 2048 | AI2: 2049 | AJ2: 2050
A3: Total Final exergy [TJ] | C3: 1 | D3: 1 | E3: 1 | F3: 1 | G3: 1 | H3: 1 | I3: 1 | J3: 1 | K3: 1 | L3: 1 | M3: 1 | N3: 1 | O3: 1 | P3: 1 | Q3: 1 | R3: 1 | S3: 1 | T3: 1 | U3: 1 | V3: 1 | W3: 1 | X3: 1 | Y3: 1 | Z3: 1 | AA3: 1 | AB3: 1 | AC3: 1 | AD3: 1 | AE3: 1 | AF3: 1 | AG3: 1 | AH3: 1 | AI3: 1 | AJ3: 1
A5: Share final exergy industry [-] | B5: Input | C5: 0.27142931 | D5: 0.27119604 | E5: 0.2732505 | F5: 0.28555072 | G5: 0.28462773 | H5: 0.27572585 | I5: 0.27588512 | J5: 0.27604439 | K5: 0.27620366 | L5: 0.27636293 | M5: 0.2765222 | N5: 0.27668146 | O5: 0.27684073 | P5: 0.277 | Q5: 0.2833 | R5: 0.2896 | S5: 0.2959 | T5: 0.3022 | U5: 0.3085 | V5: 0.3148 | W5: 0.3211 | X5: 0.3274 | Y5: 0.3337 | Z5: 0.34 | AA5: 0.3445 | AB5: 0.349 | AC5: 0.3535 | AD5: 0.358 | AE5: 0.3625 | AF5: 0.367 | AG5: 0.3715 | AH5: 0.376 | AI5: 0.3805 | AJ5: 0.385
A6: Share final exergy transport [-] | B6: Input | C6: 0.3546432 | D6: 0.35679786 | E6: 0.36315882 | F6: 0.32899597 | G6: 0.34997126 | H6: 0.36009084 | I6: 0.35382948 | J6: 0.34756813 | K6: 0.34130677 | L6: 0.33504542 | M6: 0.32878406 | N6: 0.32252271 | O6: 0.31626135 | P6: 0.31 | Q6: 0.302 | R6: 0.294 | S6: 0.286 | T6: 0.278 | U6: 0.27 | V6: 0.262 | W6: 0.254 | X6: 0.246 | Y6: 0.238 | Z6: 0.23 | AA6: 0.226 | AB6: 0.222 | AC6: 0.218 | AD6: 0.214 | AE6: 0.21 | AF6: 0.206 | AG6: 0.202 | AH6: 0.198 | AI6: 0.194 | AJ6: 0.19
A7: Share final exergy services [-] | B7: Input | C7: 0.11098227 | D7: 0.11418082 | E7: 0.11117733 | F7: 0.10630522 | G7: 0.10424487 | H7: 0.10934643 | I7: 0.11442812 | J7: 0.11950982 | K7: 0.12459152 | L7: 0.12967321 | M7: 0.13475491 | N7: 0.13983661 | O7: 0.1449183 | P7: 0.15 | Q7: 0.15 | R7: 0.15 | S7: 0.15 | T7: 0.15 | U7: 0.15 | V7: 0.15 | W7: 0.15 | X7: 0.15 | Y7: 0.15 | Z7: 0.15 | AA7: 0.152 | AB7: 0.154 | AC7: 0.156 | AD7: 0.158 | AE7: 0.16 | AF7: 0.162 | AG7: 0.164 | AH7: 0.166 | AI7: 0.168 | AJ7: 0.17
A8: Share final exergy residencial [-] | B8: Input | C8: 0.15680348 | D8: 0.15992742 | E8: 0.15925696 | F8: 0.17964943 | G8: 0.17499831 | H8: 0.16410964 | I8: 0.16609594 | J8: 0.16808223 | K8: 0.17006853 | L8: 0.17205482 | M8: 0.17404112 | N8: 0.17602741 | O8: 0.17801371 | P8: 0.18 | Q8: 0.182 | R8: 0.184 | S8: 0.186 | T8: 0.188 | U8: 0.19 | V8: 0.192 | W8: 0.194 | X8: 0.196 | Y8: 0.198 | Z8: 0.2 | AA8: 0.198 | AB8: 0.196 | AC8: 0.194 | AD8: 0.192 | AE8: 0.19 | AF8: 0.188 | AG8: 0.186 | AH8: 0.184 | AI8: 0.182 | AJ8: 0.18
A9: Share Final Exergy Agriculture/forestry/Fishing [-] | B9: Input | C9: 0.027798035 | D9: 0.028064646 | E9: 0.028618365 | F9: 0.032768238 | G9: 0.03372055 | H9: 0.029928558 | I9: 0.029937488 | J9: 0.029946419 | K9: 0.029955349 | L9: 0.029964279 | M9: 0.029973209 | N9: 0.02998214 | O9: 0.02999107 | P9: 0.03 | Q9: 0.03 | R9: 0.03 | S9: 0.03 | T9: 0.03 | U9: 0.03 | V9: 0.03 | W9: 0.03 | X9: 0.03 | Y9: 0.03 | Z9: 0.03 | AA9: 0.03 | AB9: 0.03 | AC9: 0.03 | AD9: 0.03 | AE9: 0.03 | AF9: 0.03 | AG9: 0.03 | AH9: 0.03 | AI9: 0.03 | AJ9: 0.03
A10: Share Final Exergy Energy industry own use [-] | B10: Input | C10: 0.078343711 | D10: 0.069833206 | E10: 0.06453802 | F10: 0.066730424 | G10: 0.05243729 | H10: 0.060798684 | I10: 0.059823848 | J10: 0.058849013 | K10: 0.057874177 | L10: 0.056899342 | M10: 0.055924506 | N10: 0.054949671 | O10: 0.053974835 | P10: 0.053 | Q10: 0.0527 | R10: 0.0524 | S10: 0.0521 | T10: 0.0518 | U10: 0.0515 | V10: 0.0512 | W10: 0.0509 | X10: 0.0506 | Y10: 0.0503 | Z10: 0.05 | AA10: 0.0495 | AB10: 0.049 | AC10: 0.0485 | AD10: 0.048 | AE10: 0.0475 | AF10: 0.047 | AG10: 0.0465 | AH10: 0.046 | AI10: 0.0455 | AJ10: 0.045
A12: Final exergy Industry [TJ] | B12: Computed | C12: =+C5*C$3 -> 0.27142931 | D12: =+D5*D$3 -> 0.27119604 | E12: =+E5*E$3 -> 0.2732505 | F12: =+F5*F$3 -> 0.28555072 | G12: =+G5*G$3 -> 0.28462773 | H12: =+H5*H$3 -> 0.27572585 | I12: =+I5*I$3 -> 0.27588512 | J12: =+J5*J$3 -> 0.27604439 | ... AJ12: =+AJ5*AJ$3 -> 0.385
A13: Final exergy Transport [TJ] | B13: Computed | C13: =+C6*C$3 -> 0.3546432 | D13: =+D6*D$3 -> 0.35679786 | E13: =+E6*E$3 -> 0.36315882 | F13: =+F6*F$3 -> 0.32899597 | G13: =+G6*G$3 -> 0.34997126 | H13: =+H6*H$3 -> 0.36009084 | I13: =+I6*I$3 -> 0.35382948 | J13: =+J6*J$3 -> 0.34756813 | ... AJ13: =+AJ6*AJ$3 -> 0.19
A14: Final exergy Services [TJ] | B14: Computed | C14: =+C7*C$3 -> 0.11098227 | D14: =+D7*D$3 -> 0.11418082 | E14: =+E7*E$3 -> 0.11117733 | F14: =+F7*F$3 -> 0.10630522 | G14: =+G7*G$3 -> 0.10424487 | H14: =+H7*H$3 -> 0.10934643 | I14: =+I7*I$3 -> 0.11442812 | J14: =+J7*J$3 -> 0.11950982 | ... AJ14: =+AJ7*AJ$3 -> 0.17
A15: Final exergy Residencial [TJ] | B15: Computed | C15: =+C8*C$3 -> 0.15680348 | D15: =+D8*D$3 -> 0.15992742 | E15: =+E8*E$3 -> 0.15925696 | F15: =+F8*F$3 -> 0.17964943 | G15: =+G8*G$3 -> 0.17499831 | H15: =+H8*H$3 -> 0.16410964 | I15: =+I8*I$3 -> 0.16609594 | J15: =+J8*J$3 -> 0.16808223 | ... AJ15: =+AJ8*AJ$3 -> 0.18
A16: Final Exergy Agriculture/Forestry/fishing [TJ] | B16: Computed | C16: =+C9*C$3 -> 0.027798035 | D16: =+D9*D$3 -> 0.028064646 | E16: =+E9*E$3 -> 0.028618365 | F16: =+F9*F$3 -> 0.032768238 | G16: =+G9*G$3 -> 0.03372055 | H16: =+H9*H$3 -> 0.029928558 | I16: =+I9*I$3 -> 0.029937488 | J16: =+J9*J$3 -> 0.029946419 | ... AJ16: =+AJ9*AJ$3 -> 0.03
A17: Final Exergy Energy industry own use [TJ] | B17: Computed | C17: =+C10*C$3 -> 0.078343711 | D17: =+D10*D$3 -> 0.069833206 | E17: =+E10*E$3 -> 0.06453802 | F17: =+F10*F$3 -> 0.066730424 | G17: =+G10*G$3 -> 0.05243729 | H17: =+H10*H$3 -> 0.060798684 | I17: =+I10*I$3 -> 0.059823848 | J17: =+J10*J$3 -> 0.058849013 | ... AJ17: =+AJ10*AJ$3 -> 0.045
A19: Share final exergy industry electricity | B19: Input | C19: 0.2970747 | D19: 0.30075756 | E19: 0.30235708 | F19: 0.30163627 | G19: 0.30591526 | H19: 0.31318182 | I19: 0.31407823 | J19: 0.31497465 | K19: 0.31587106 | L19: 0.31676747 | M19: 0.31766388 | N19: 0.31856029 | O19: 0.3194567 | P19: 0.32035311 | Q19: 0.32710662 | R19: 0.33386012 | S19: 0.34061363 | T19: 0.34736713 | U19: 0.35412063 | V19: 0.36087414 | W19: 0.36762764 | X19: 0.37438115 | Y19: 0.38113465 | Z19: 0.38788815 | AA19: 0.40440244 | AB19: 0.42091672 | AC19: 0.43743101 | AD19: 0.45394529 | AE19: 0.47045958 | AF19: 0.48697386 | AG19: 0.50348815 | AH19: 0.52000243 | AI19: 0.53651672 | AJ19: 0.553031
A20: Share final exergy transport electricity | B20: Input | C20: 0.0068374586 | D20: 0.0068392983 | E20: 0.0067376336 | F20: 0.0070045484 | G20: 0.0070586514 | H20: 0.0070199832 | I20: 0.020547839 | J20: 0.034075694 | K20: 0.04760355 | L20: 0.061131405 | M20: 0.074659261 | N20: 0.088187116 | O20: 0.10171497 | P20: 0.11524283 | Q20: 0.15554516 | R20: 0.1958475 | S20: 0.23614984 | T20: 0.27645218 | U20: 0.31675451 | V20: 0.35705685 | W20: 0.39735919 | X20: 0.43766153 | Y20: 0.47796386 | Z20: 0.5182662 | AA20: 0.53528284 | AB20: 0.55229949 | AC20: 0.56931613 | AD20: 0.58633277 | AE20: 0.60334941 | AF20: 0.62036606 | AG20: 0.6373827 | AH20: 0.65439934 | AI20: 0.67141598 | AJ20: 0.68843263
A21: Share final exergy services electricity | B21: Input | C21: 0.73677033 | D21: 0.72971057 | E21: 0.73192341 | F21: 0.7583611 | G21: 0.73914204 | H21: 0.75301205 | I21: 0.75138554 | J21: 0.74975904 | K21: 0.74813253 | L21: 0.74650602 | M21: 0.74487952 | N21: 0.74325301 | O21: 0.74162651 | P21: 0.74 | Q21: 0.748 | R21: 0.756 | S21: 0.764 | T21: 0.772 | U21: 0.78 | V21: 0.788 | W21: 0.796 | X21: 0.804 | Y21: 0.812 | Z21: 0.82 | AA21: 0.826 | AB21: 0.832 | AC21: 0.838 | AD21: 0.844 | AE21: 0.85 | AF21: 0.856 | AG21: 0.862 | AH21: 0.868 | AI21: 0.874 | AJ21: 0.88
A22: Share final exergy residencial electricity | B22: Input | C22: 0.40105887 | D22: 0.41096146 | E22: 0.41088932 | F22: 0.40750368 | G22: 0.42720606 | H22: 0.43001357 | I22: 0.43126188 | J22: 0.43251018 | K22: 0.43375848 | L22: 0.43500679 | M22: 0.43625509 | N22: 0.43750339 | O22: 0.4387517 | P22: 0.44 | Q22: 0.459 | R22: 0.478 | S22: 0.497 | T22: 0.516 | U22: 0.535 | V22: 0.554 | W22: 0.573 | X22: 0.592 | Y22: 0.611 | Z22: 0.63 | AA22: 0.65 | AB22: 0.67 | AC22: 0.69 | AD22: 0.71 | AE22: 0.73 | AF22: 0.75 | AG22: 0.77 | AH22: 0.79 | AI22: 0.81 | AJ22: 0.83
A23: Share final exergy Agriculture/forestry/Fishing electricity | B23: Input | C23: 0.17678412 | D23: 0.18850159 | E23: 0.16560611 | F23: 0.16584001 | G23: 0.17929811 | H23: 0.16275005 | I23: 0.18979469 | J23: 0.21683933 | K23: 0.24388397 | L23: 0.27092861 | M23: 0.29797325 | N23: 0.3250179 | O23: 0.35206254 | P23: 0.37910718 | Q23: 0.40615182 | R23: 0.43319646 | S23: 0.4602411 | T23: 0.48728574 | U23: 0.51433038 | V23: 0.54137502 | W23: 0.56841967 | X23: 0.59546431 | Y23: 0.62250895 | Z23: 0.64955359 | AA23: 0.67659823 | AB23: 0.70364287 | AC23: 0.73068751 | AD23: 0.75773215 | AE23: 0.78477679 | AF23: 0.81182144 | AG23: 0.83886608 | AH23: 0.86591072 | AI23: 0.89295536 | AJ23: 0.92
A24: Share final exergy Energy industry own electricity | B24: Input | C24: 0.20857445 | D24: 0.19412629 | E24: 0.17649312 | F24: 0.17373555 | G24: 0.18464616 | H24: 0.17476388 | I24: 0.20066517 | J24: 0.22656646 | K24: 0.25246775 | L24: 0.27836904 | M24: 0.30427033 | N24: 0.33017162 | O24: 0.35607291 | P24: 0.3819742 | Q24: 0.40787549 | R24: 0.43377678 | S24: 0.45967807 | T24: 0.48557936 | U24: 0.51148065 | V24: 0.53738194 | W24: 0.56328323 | X24: 0.58918452 | Y24: 0.61508581 | Z24: 0.6409871 | AA24: 0.66688839 | AB24: 0.69278968 | AC24: 0.71869097 | AD24: 0.74459226 | AE24: 0.77049355 | AF24: 0.79639484 | AG24: 0.82229613 | AH24: 0.84819742 | AI24: 0.87409871 | AJ24: 0.9
A25: Share final exergy industry coal/coke | B25: Input | C25: 0.069253404 | D25: 0.061170092 | E25: 0.059562702 | F25: 0.064743037 | G25: 0.054408395 | H25: 0.06007097 | I25: 0.052788926 | J25: 0.045506881 | K25: 0.038224837 | L25: 0.030942793 | M25: 0.023660748 | N25: 0.016378704 | O25: 0.0090966594 | P25: 0.001814615 | Q25: 0.0018311542 | R25: 0.0018476934 | S25: 0.0018642325 | T25: 0.0018807717 | U25: 0.0018973109 | V25: 0.0019138501 | W25: 0.0019303892 | X25: 0.0019469284 | Y25: 0.0019634676 | Z25: 0.0019800068 | AA25: 0.0019856155 | AB25: 0.0019912243 | AC25: 0.0019968331 | AD25: 0.0020024418 | AE25: 0.0020080506 | AF25: 0.0020136593 | AG25: 0.0020192681 | AH25: 0.0020248769 | AI25: 0.0020304856 | AJ25: 0.0020360944
A26: Share final exergy industry oil | B26: Input | C26: 0.078378662 | D26: 0.077637821 | E26: 0.069863979 | F26: 0.070795621 | G26: 0.069265914 | H26: 0.082289434 | I26: 0.072199429 | J26: 0.062109425 | K26: 0.05201942 | L26: 0.041929415 | M26: 0.031839411 | N26: 0.021749406 | O26: 0.011659401 | P26: 0.0015693968 | Q26: 0.0015235306 | R26: 0.0014776645 | S26: 0.0014317984 | T26: 0.0013859323 | U26: 0.0013400661 | V26: 0.0012942 | W26: 0.0012483339 | X26: 0.0012024678 | Y26: 0.0011566016 | Z26: 0.0011107355 | AA26: 0.0010922117 | AB26: 0.0010736879 | AC26: 0.0010551641 | AD26: 0.0010366403 | AE26: 0.0010181165 | AF26: 0.00099959267 | AG26: 0.00098106887 | AH26: 0.00096254506 | AI26: 0.00094402126 | AJ26: 0.00092549745
A27: Share final exergy industry natural gas | B27: Input | C27: 0.27024948 | D27: 0.2755297 | E27: 0.27458465 | F27: 0.2640436 | G27: 0.29137166 | H27: 0.25694602 | I27: 0.26313699 | J27: 0.26932796 | K27: 0.27551892 | L27: 0.28170989 | M27: 0.28790086 | N27: 0.29409183 | O27: 0.30028279 | P27: 0.30647376 | Q27: 0.29764509 | R27: 0.28881643 | S27: 0.27998776 | T27: 0.27115909 | U27: 0.26233042 | V27: 0.25350176 | W27: 0.24467309 | X27: 0.23584442 | Y27: 0.22701575 | Z27: 0.21818709 | AA27: 0.20882557 | AB27: 0.19946406 | AC27: 0.19010255 | AD27: 0.18074103 | AE27: 0.17137952 | AF27: 0.16201801 | AG27: 0.1526565 | AH27: 0.14329498 | AI27: 0.13393347 | AJ27: 0.12457196
A28: Share final exergy industry waste/c. renewables | B28: Input | C28: 0.26201817 | D28: 0.25876213 | E28: 0.26551584 | F28: 0.27237961 | G28: 0.25652296 | H28: 0.27022414 | I28: 0.25239144 | J28: 0.23455874 | K28: 0.21672604 | L28: 0.19889333 | M28: 0.18106063 | N28: 0.16322793 | O28: 0.14539523 | P28: 0.12756253 | Q28: 0.12657524 | R28: 0.12558796 | S28: 0.12460067 | T28: 0.12361339 | U28: 0.1226261 | V28: 0.12163881 | W28: 0.12065153 | X28: 0.11966424 | Y28: 0.11867696 | Z28: 0.11768967 | AA28: 0.11565694 | AB28: 0.1136242 | AC28: 0.11159147 | AD28: 0.10955873 | AE28: 0.107526 | AF28: 0.10549327 | AG28: 0.10346053 | AH28: 0.1014278 | AI28: 0.099395066 | AJ28: 0.097362332
A29: Share final exergy industry Renewables (Solar) | B29: Input | C29: 0 | D29: 0 | E29: 0 | F29: 0 | G29: 0 | H29: 0 | I29: 0.0008521334 | J29: 0.0017042668 | K29: 0.0025564002 | L29: 0.0034085336 | M29: 0.004260667 | N29: 0.0051128004 | O29: 0.0059649338 | P29: 0.0068170672 | Q29: 0.0071736567 | R29: 0.0075302462 | S29: 0.0078868357 | T29: 0.0082434252 | U29: 0.0086000147 | V29: 0.0089566042 | W29: 0.0093131938 | X29: 0.0096697833 | Y29: 0.010026373 | Z29: 0.010382962 | AA29: 0.012093393 | AB29: 0.013803825 | AC29: 0.015514256 | AD29: 0.017224687 | AE29: 0.018935118 | AF29: 0.02064555 | AG29: 0.022355981 | AH29: 0.024066412 | AI29: 0.025776843 | AJ29: 0.027487274
A30: Share final exergy industry heat | B30: Input | C30: 0.023025582 | D30: 0.026142703 | E30: 0.028115736 | F30: 0.026401859 | G30: 0.022515809 | H30: 0.017287611 | I30: 0.044552849 | J30: 0.071818087 | K30: 0.099083325 | L30: 0.12634856 | M30: 0.1536138 | N30: 0.18087904 | O30: 0.20814428 | P30: 0.23540951 | Q30: 0.2381447 | R30: 0.24087989 | S30: 0.24361508 | T30: 0.24635026 | U30: 0.24908545 | V30: 0.25182064 | W30: 0.25455582 | X30: 0.25729101 | Y30: 0.2600262 | Z30: 0.26276139 | AA30: 0.25594383 | AB30: 0.24912628 | AC30: 0.24230872 | AD30: 0.23549117 | AE30: 0.22867361 | AF30: 0.22185606 | AG30: 0.2150385 | AH30: 0.20822095 | AI30: 0.20140339 | AJ30: 0.19458584
... A58: Share Final Exergy Energy industry own use Heat | B58: Input | C58: 0.11153732 | D58: 0.12514663 | E58: 0.13516367 | F58: 0.14874172 | G58: 0.13776063 | H58: 0.069597049 | I58: 0.069254297 | J58: 0.068911545 | K58: 0.068568794 | L58: 0.068226042 | M58: 0.06788329 | N58: 0.067540538 | O58: 0.067197787 | P58: 0.066855035 | Q58: 0.066512283 | R58: 0.066169531 | S58: 0.06582678 | T58: 0.065484028 | U58: 0.065141276 | V58: 0.064798524 | W58: 0.064455773 | X58: 0.064113021 | Y58: 0.063770269 | Z58: 0.063427517 | AA58: 0.063084766 | AB58: 0.062742014 | AC58: 0.062399262 | AD58: 0.06205651 | AE58: 0.061713759 | AF58: 0.061371007 | AG58: 0.061028255 | AH58: 0.060685503 | AI58: 0.060342752 | AJ58: 0.06
A60: Final exergy industry electricity [TJ] | B60: Computed | C60: =+C19*C12 -> 0.08063478 | D60: =+D19*D12 -> 0.081564258 | E60: =+E19*E12 -> 0.082619224 | F60: =+F19*F12 -> 0.086132456 | G60: =+G19*G12 -> 0.087071965 | H60: =+H19*H12 -> 0.086352326 | I60: =+I19*I12 -> 0.086649512 | J60: =+J19*J12 -> 0.086946984 | ... AJ60: =+AJ19*AJ12 -> 0.21291694 | AL60: =+AJ60/$AL$66 -> 0.29953743
A61: Final exergy transport electricity [TJ] | B61: Computed | C61: =+C20*C13 -> 0.0024248582 | D61: =+D20*D13 -> 0.002440247 | E61: =+E20*E13 -> 0.0024468311 | F61: =+F20*F13 -> 0.0023044682 | G61: =+G20*G13 -> 0.0024703251 | H61: =+H20*H13 -> 0.0025278316 | I61: =+I20*I13 -> 0.0072704311 | J61: =+J20*J13 -> 0.011843625 | ... AJ61: =+AJ20*AJ13 -> 0.1308022 | AL61: =+AJ61/$AL$66 -> 0.18401615
A62: Final exergy services electricity [TJ] | B62: Computed | C62: =+C21*C14 -> 0.081768445 | D62: =+D21*D14 -> 0.083318954 | E62: =+E21*E14 -> 0.081373292 | F62: =+F21*F14 -> 0.080617743 | G62: =+G21*G14 -> 0.077051763 | H62: =+H21*H14 -> 0.082339176 | I62: =+I21*I14 -> 0.085979637 | J62: =+J21*J14 -> 0.089603567 | ... AJ62: =+AJ21*AJ14 -> 0.1496 | AL62: =+AJ62/$AL$66 -> 0.21046141
A63: Final exergy residencial electricity [TJ] | B63: Computed | C63: =+C22*C15 -> 0.062887425 | D63: =+D22*D15 -> 0.065724008 | E63: =+E22*E15 -> 0.065436985 | F63: =+F22*F15 -> 0.073207804 | G63: =+G22*G15 -> 0.074760337 | H63: =+H22*H15 -> 0.070569373 | I63: =+I22*I15 -> 0.071630845 | J63: =+J22*J15 -> 0.072697276 | ... AJ63: =+AJ22*AJ15 -> 0.1494 | AL63: =+AJ63/$AL$66 -> 0.21018005
A64: Final Exergy Agriculture/Forestry/fishing electricity [TJ] | B64: Computed | C64: =+C23*C16 -> 0.004914251 | D64: =+D23*D16 -> 0.0052902303 | E64: =+E23*E16 -> 0.0047393761 | F64: =+F23*F16 -> 0.0054342848 | G64: =+G23*G16 -> 0.0060460307 | H64: =+H23*H16 -> 0.0048708743 | I64: =+I23*I16 -> 0.0056819763 | J64: =+J23*J16 -> 0.0064935614 | ... AJ64: =+AJ23*AJ16 -> 0.0276 | AL64: =+AJ64/$AL$66 -> 0.038828443
A65: Final Exergy Energy industry own use electricity [TJ] | B65: Computed | C65: =+C24*C17 -> 0.016340496 | D65: =+D24*D17 -> 0.013556461 | E65: =+E24*E17 -> 0.011390517 | F65: =+F24*F17 -> 0.011593447 | G65: =+G24*G17 -> 0.009682344 | H65: =+H24*H17 -> 0.010625414 | I65: =+I24*I17 -> 0.012004563 | J65: =+J24*J17 -> 0.013333213 | ... AJ65: =+AJ24*AJ17 -> 0.0405 | AL65: =+AJ65/$AL$66 -> 0.056976519
A66: Final exergy industry coal/coke [TJ] | B66: Computed | C66: =+C25*C$12 -> 0.018797403 | D66: =+D25*D$12 -> 0.016589087 | E66: =+E25*E$12 -> 0.016275538 | F66: =+F25*F$12 -> 0.018487421 | G66: =+G25*G$12 -> 0.015486138 | H66: =+H25*H$12 -> 0.01656312 | I66: =+I25*I$12 -> 0.014563679 | J66: =+J25*J$12 -> 0.012561919 | ... AJ66: =+AJ25*AJ$12 -> 0.00078389634 | AL66: =+SUM(AJ60:AJ65) -> 0.71081914
A67: Final exergy industry oil [TJ] | B67: Computed | C67: =+C26*C$12 -> 0.021274266 | D67: =+D26*D$12 -> 0.02105507 | E67: =+E26*E$12 -> 0.019090367 | F67: =+F26*F$12 -> 0.020215741 | G67: =+G26*G$12 -> 0.019715 | H67: =+H26*H$12 -> 0.022689325 | I67: =+I26*I$12 -> 0.019918748 | J67: =+J26*J$12 -> 0.017144958 | ... AJ67: =+AJ26*AJ$12 -> 0.00035631652
A68: Final exergy industry natural gas [TJ] | B68: Computed | C68: =+C27*C$12 -> 0.073353629 | D68: =+D27*D$12 -> 0.074722565 | E68: =+E27*E$12 -> 0.075030393 | F68: =+F27*F$12 -> 0.07539784 | G68: =+G27*G$12 -> 0.082932455 | H68: =+H27*H$12 -> 0.070846662 | I68: =+I27*I$12 -> 0.072595581 | J68: =+J27*J$12 -> 0.074346472 | ... AJ68: =+AJ27*AJ$12 -> 0.047960204
A69: Final exergy industry c. renewables/waste [TJ] | B69: Computed | C69: =+C28*C$12 -> 0.071119412 | D69: =+D28*D$12 -> 0.070175264 | E69: =+E28*E$12 -> 0.072552336 | F69: =+F28*F$12 -> 0.077778194 | G69: =+G28*G$12 -> 0.073013548 | H69: =+H28*H$12 -> 0.074507782 | I69: =+I28*I$12 -> 0.069631043 | J69: =+J28*J$12 -> 0.064748624 | ... AJ69: =+AJ28*AJ$12 -> 0.037484498
A70: Final exergy industry renewables [TJ] | B70: Computed | C70: =+C29*C$12 -> 0 | D70: =+D29*D$12 -> 0 | E70: =+E29*E$12 -> 0 | F70: =+F29*F$12 -> 0 | G70: =+G29*G$12 -> 0 | H70: =+H29*H$12 -> 0 | I70: =+I29*I$12 -> 0.00023509093 | J70: =+J29*J$12 -> 0.00047045329 | ... AJ70: =+AJ29*AJ$12 -> 0.010582601
A71: Final exergy industry heat [TJ] | B71: Computed | C71: =+C30*C$12 -> 0.0062498177 | D71: =+D30*D$12 -> 0.0070897976 | E71: =+E30*E$12 -> 0.0076826389 | F71: =+F30*F$12 -> 0.00753907 | G71: =+G30*G$12 -> 0.0064086236 | H71: =+H30*H$12 -> 0.0047666413 | I71: =+I30*I$12 -> 0.012291468 | J71: =+J30*J$12 -> 0.01982498 | ... AJ71: =+AJ30*AJ$12 -> 0.074915548
A72: Final exergy transport coal/coke [TJ] | B72: Computed | C72: =+C$13*C31 -> 0 | D72: =+D$13*D31 -> 0 | E72: =+E$13*E31 -> 0 | F72: =+F$13*F31 -> 0 | G72: =+G$13*G31 -> 0 | H72: =+H$13*H31 -> 0 | I72: =+I$13*I31 -> 0 | J72: =+J$13*J31 -> 0 | ... AJ72: =+AJ$13*AJ31 -> 0
A73: Final exergy transport oil [TJ] | B73: Computed | C73: =+C$13*C32 -> 0.33567091 | D73: =+D$13*D32 -> 0.33654448 | E73: =+E$13*E32 -> 0.34228577 | F73: =+F$13*F32 -> 0.30856079 | G73: =+G$13*G32 -> 0.32451721 | H73: =+H$13*H32 -> 0.3340624 | I73: =+I$13*I32 -> 0.32239079 | J73: =+J$13*J32 -> 0.31092667 | ... AJ73: =+AJ$13*AJ32 -> 0.010381465
A74: Final exergy transport natural gas [TJ] | B74: Computed | C74: =+C$13*C33 -> 0.00088670839 | D74: =+D$13*D33 -> 0.00096301842 | E74: =+E$13*E33 -> 0.0010441319 | F74: =+F$13*F33 -> 0.001298036 | G74: =+G$13*G33 -> 0.0015022085 | H74: =+H$13*H33 -> 0.0020018913 | I74: =+I$13*I33 -> 0.0021252734 | J74: =+J$13*J33 -> 0.0022430569 | ... AJ74: =+AJ$13*AJ33 -> 0.0020677662
A75: Final exergy transport c. renewables/waste [TJ] | B75: Computed | C75: =+C$13*C34 -> 0.01566072 | D75: =+D$13*D34 -> 0.016850121 | E75: =+E$13*E34 -> 0.017382093 | F75: =+F$13*F34 -> 0.016832668 | G75: =+G$13*G34 -> 0.021481517 | H75: =+H$13*H34 -> 0.021498717 | I75: =+I$13*I34 -> 0.021738162 | J75: =+J$13*J34 -> 0.021955902 | ... AJ75: =+AJ$13*AJ34 -> 0.00093795579
A76: Final exergy transport hydrogen [TJ] | B76: Computed | C76: =+C$13*C35 -> 0 | D76: =+D$13*D35 -> 0 | E76: =+E$13*E35 -> 0 | F76: =+F$13*F35 -> 0 | G76: =+G$13*G35 -> 0 | H76: =+H$13*H35 -> 0 | I76: =+I$13*I35 -> 0.00030482986 | J76: =+J$13*J35 -> 0.00059887119 | ... AJ76: =+AJ$13*AJ35 -> 0.045810614
A77: Final exergy transport heat [TJ] | B77: Computed | C77: =+C$13*C36 -> 0 | D77: =+D$13*D36 -> 0 | E77: =+E$13*E36 -> 0 | F77: =+F$13*F36 -> 0 | G77: =+G$13*G36 -> 0 | H77: =+H$13*H36 -> 0 | I77: =+I$13*I36 -> 0 | J77: =+J$13*J36 -> 0 | ... AJ77: =+AJ$13*AJ36 -> 0
A78: Final exergy services coal/coke [TJ] | B78: Computed | C78: =+C$14*C37 -> 0 | D78: =+D$14*D37 -> 0 | E78: =+E$14*E37 -> 0 | F78: =+F$14*F37 -> 0 | G78: =+G$14*G37 -> 0 | H78: =+H$14*H37 -> 0 | I78: =+I$14*I37 -> 0 | J78: =+J$14*J37 -> 0 | ... AJ78: =+AJ$14*AJ37 -> 0
A79: Final exergy services oil [TJ] | B79: Computed | C79: =+C$14*C38 -> 0.008584364 | D79: =+D$14*D38 -> 0.0099401558 | E79: =+E$14*E38 -> 0.010074914 | F79: =+F$14*F38 -> 0.00777558 | G79: =+G$14*G38 -> 0.0069481686 | H79: =+H$14*H38 -> 0.0072441946 | I79: =+I$14*I38 -> 0.007159698 | J79: =+J$14*J38 -> 0.0070377946 | ... AJ79: =+AJ$14*AJ38 -> 0
A80: Final exergy services natural gas [TJ] | B80: Computed | C80: =+C$14*C39 -> 0.015435987 | D80: =+D$14*D39 -> 0.015734417 | E80: =+E$14*E39 -> 0.014761564 | F80: =+F$14*F39 -> 0.013093476 | G80: =+G$14*G39 -> 0.014999063 | H80: =+H$14*H39 -> 0.014258512 | I80: =+I$14*I39 -> 0.015201536 | J80: =+J$14*J39 -> 0.016169464 | ... AJ80: =+AJ$14*AJ39 -> 0.00085
A81: Final exergy services c. renewables/waste [TJ] | B81: Computed | C81: =+C$14*C40 -> 0.0021754649 | D81: =+D$14*D40 -> 0.0020799228 | E81: =+E$14*E40 -> 0.0018265235 | F81: =+F$14*F40 -> 0.0013654364 | G81: =+G$14*G40 -> 0.0017069347 | H81: =+H$14*H40 -> 0.0019363382 | I81: =+I$14*I40 -> 0.0019743912 | J81: =+J$14*J40 -> 0.0020078313 | ... AJ81: =+AJ$14*AJ40 -> 0.00085
A82: Final exergy services renewables [TJ] | B82: Computed | C82: =+C$14*C41 -> 0.0021343342 | D82: =+D$14*D41 -> 0.0022429856 | E82: =+E$14*E41 -> 0.0023165869 | F82: =+F$14*F41 -> 0.0025930311 | G82: =+G$14*G41 -> 0.0026522062 | H82: =+H$14*H41 -> 0.0028274246 | I82: =+I$14*I41 -> 0.0033041472 | J82: =+J$14*J41 -> 0.0038115411 | ... AJ82: =+AJ$14*AJ41 -> 0.0187
A83: Final exergy services heat [TJ] | B83: Computed | C83: =+C$14*C42 -> 0.00088367688 | D83: =+D$14*D42 -> 0.00086438824 | E83: =+E$14*E42 -> 0.00082445184 | F83: =+F$14*F42 -> 0.00085995277 | G83: =+G$14*G42 -> 0.00088673042 | H83: =+H$14*H42 -> 0.00074077995 | I83: =+I$14*I42 -> 0.00080871261 | J83: =+J$14*J42 -> 0.00087962126 | ... AJ83: =+AJ$14*AJ42 -> 0
A84: Final exergy residencial coal/coke [TJ] | B84: Computed | C84: =+C$15*C43 -> 0 | D84: =+D$15*D43 -> 0 | E84: =+E$15*E43 -> 0 | F84: =+F$15*F43 -> 0 | G84: =+G$15*G43 -> 0 | H84: =+H$15*H43 -> 0 | I84: =+I$15*I43 -> 0 | J84: =+J$15*J43 -> 0 | ... AJ84: =+AJ$15*AJ43 -> 0
A85: Final exergy residencial oil [TJ] | B85: Computed | C85: =+C$15*C44 -> 0.02636687 | D85: =+D$15*D44 -> 0.025782385 | E85: =+E$15*E44 -> 0.024839676 | F85: =+F$15*F44 -> 0.029690611 | G85: =+G$15*G44 -> 0.025381586 | H85: =+H$15*H44 -> 0.022143092 | I85: =+I$15*I44 -> 0.021166039 | J85: =+J$15*J44 -> 0.020159207 | ... AJ85: =+AJ$15*AJ44 -> 0
A86: Final exergy residencial natural gas [TJ] | B86: Computed | C86: =+C$15*C45 -> 0.015148648 | D86: =+D$15*D45 -> 0.016430404 | E86: =+E$15*E45 -> 0.017012544 | F86: =+F$15*F45 -> 0.019104196 | G86: =+G$15*G45 -> 0.018160326 | H86: =+H$15*H45 -> 0.016388172 | I86: =+I$15*I45 -> 0.017627509 | J86: =+J$15*J45 -> 0.018891743 | ... AJ86: =+AJ$15*AJ45 -> 0.0018
A87: Final exergy residencial c. renewables/waste [TJ] | B87: Computed | C87: =+C$15*C46 -> 0.049304341 | D87: =+D$15*D46 -> 0.048634677 | E87: =+E$15*E46 -> 0.04861165 | F87: =+F$15*F46 -> 0.053847966 | G87: =+G$15*G46 -> 0.052810681 | H87: =+H$15*H46 -> 0.051185398 | I87: =+I$15*I46 -> 0.050519801 | J87: =+J$15*J46 -> 0.049823468 | ... AJ87: =+AJ$15*AJ46 -> 0.009
A88: Final exergy residencial renewables [TJ] | B88: Computed | C88: =+C$15*C47 -> 0.0030662227 | D88: =+D$15*D47 -> 0.003319329 | E88: =+E$15*E47 -> 0.0033264157 | F88: =+F$15*F47 -> 0.0037666863 | G88: =+G$15*G47 -> 0.0038539597 | H88: =+H$15*H47 -> 0.0038024764 | I88: =+I$15*I47 -> 0.0044055367 | J88: =+J$15*J47 -> 0.0050219199 | ... AJ88: =+AJ$15*AJ47 -> 0.0198
A89: Final exergy residencial heat [TJ] | B89: Computed | C89: =+C$15*C48 -> 2.9970952e-05 | D89: =+D$15*D48 -> 3.6619665e-05 | E89: =+E$15*E48 -> 2.9691549e-05 | F89: =+F$15*F48 -> 3.2165136e-05 | G89: =+G$15*G48 -> 3.141649e-05 | H89: =+H$15*H48 -> 2.1130822e-05 | I89: =+I$15*I48 -> 0.00074620601 | J89: =+J$15*J48 -> 0.001488617 | ... AJ89: =+AJ$15*AJ48 -> 0
A90: Final exergy Agriculture/forestry/Fishing Coal/Coke [TJ] | B90: Computed | C90: =+C$16*C49 -> 0 | D90: =+D$16*D49 -> 0 | E90: =+E$16*E49 -> 0 | F90: =+F$16*F49 -> 0 | G90: =+G$16*G49 -> 0 | H90: =+H$16*H49 -> 0 | I90: =+I$16*I49 -> 0 | J90: =+J$16*J49 -> 0 | ... AJ90: =+AJ$16*AJ49 -> 0
A91: Final exergy Agriculture/forestry/Fishing oil [TJ] | B91: Computed | C91: =+C$16*C50 -> 0.021940478 | D91: =+D$16*D50 -> 0.021966128 | E91: =+E$16*E50 -> 0.022774767 | F91: =+F$16*F50 -> 0.026167646 | G91: =+G$16*G50 -> 0.026304993 | H91: =+H$16*H50 -> 0.024224712 | I91: =+I$16*I50 -> 0.023366514 | J91: =+J$16*J50 -> 0.0225078 | ... AJ91: =+AJ$16*AJ50 -> 0
A92: Final exergy Agriculture/forestry/Fishing natural gas [TJ] | B92: Computed | C92: =+C$16*C51 -> 0.00035197332 | D92: =+D$16*D51 -> 0.00023282933 | E92: =+E$16*E51 -> 0.00038589007 | F92: =+F$16*F51 -> 0.00045754548 | G92: =+G$16*G51 -> 0.00052222584 | H92: =+H$16*H51 -> 0.00026083002 | I92: =+I$16*I51 -> 0.00027297363 | J92: =+J$16*J51 -> 0.00028512444 | ... AJ92: =+AJ$16*AJ51 -> 0.0006
A93: Final exergy Agriculture/forestry/Fishing c. renewables/waste [TJ] | B93: Computed | C93: =+C$16*C52 -> 0.00024029794 | D93: =+D$16*D52 -> 0.00034767375 | E93: =+E$16*E52 -> 0.00039742922 | F93: =+F$16*F52 -> 0.00044460527 | G93: =+G$16*G52 -> 0.00047216453 | H93: =+H$16*H52 -> 0.00024010763 | I93: =+I$16*I52 -> 0.00027436928 | J93: =+J$16*J52 -> 0.00030865134 | ... AJ93: =+AJ$16*AJ52 -> 0.0012
A94: Final exergy Agriculture/forestry/Fishing heat [TJ] | B94: Computed | C94: =+C$16*C53 -> 0.00035103478 | D94: =+D$16*D53 -> 0.00022778476 | E94: =+E$16*E53 -> 0.00032090241 | F94: =+F$16*F53 -> 0.00026415618 | G94: =+G$16*G53 -> 0.00037513616 | H94: =+H$16*H53 -> 0.00033203361 | I94: =+I$16*I53 -> 0.00034165472 | J94: =+J$16*J53 -> 0.00035128152 | ... AJ94: =+AJ$16*AJ53 -> 0.0006
A95: Final Exergy Energy industry own use Coal/Coke [TJ] | B95: Computed | C95: =+C$17*C54 -> 0 | D95: =+D$17*D54 -> 0 | E95: =+E$17*E54 -> 0 | F95: =+F$17*F54 -> 0 | G95: =+G$17*G54 -> 0 | H95: =+H$17*H54 -> 0 | I95: =+I$17*I54 -> 0 | J95: =+J$17*J54 -> 0 | ... AJ95: =+AJ$17*AJ54 -> 0
A96: Final Exergy Energy industry own use Oil [TJ] | B96: Computed | C96: =+C$17*C55 -> 0.046898119 | D96: =+D$17*D55 -> 0.041844374 | E96: =+E$17*E55 -> 0.038777629 | F96: =+F$17*F55 -> 0.039582799 | G96: =+G$17*G55 -> 0.02980137 | H96: =+H$17*H55 -> 0.042268569 | I96: =+I$17*I55 -> 0.040105455 | J96: =+J$17*J55 -> 0.03799075 | ... AJ96: =+AJ$17*AJ55 -> 0
A97: Final Exergy Energy industry own use Natural Gas [TJ] | B97: Computed | C97: =+C$17*C56 -> 0.0063668482 | D97: =+D$17*D56 -> 0.0056929803 | E97: =+E$17*E56 -> 0.0056466783 | F97: =+F$17*F56 -> 0.0056285807 | G97: =+G$17*G56 -> 0.0057297813 | H97: =+H$17*H56 -> 0.0036732913 | I97: =+I$17*I56 -> 0.0035707715 | J97: =+J$17*J56 -> 0.0034696734 | ... AJ97: =+AJ$17*AJ56 -> 0.0018
A98: Final Exergy Energy industry own use C. Renewables/Waste [TJ] | B98: Computed | C98: =+C$17*C57 -> 0 | D98: =+D$17*D57 -> 0 | E98: =+E$17*E57 -> 0 | F98: =+F$17*F57 -> 0 | G98: =+G$17*G57 -> 0 | H98: =+H$17*H57 -> 0 | I98: =+I$17*I57 -> 0 | J98: =+J$17*J57 -> 0 | ... AJ98: =+AJ$17*AJ57 -> 0
A99: Final Exergy Energy industry own use Heat [TJ] | B99: Computed | C99: =+C$17*C58 -> 0.0087382476 | D99: =+D$17*D58 -> 0.0087393904 | E99: =+E$17*E58 -> 0.0087231957 | F99: =+F$17*F58 -> 0.009925598 | G99: =+G$17*G58 -> 0.0072237942 | H99: =+H$17*H58 -> 0.0042314089 | I99: =+I$17*I58 -> 0.0041430585 | J99: =+J$17*J58 -> 0.0040553764 | ... AJ99: =+AJ$17*AJ58 -> 0.0027
A101: Share final exergy industry coal HTH | B101: Input | C101: 0.034874132 | D101: 0.036372867 | E101: 0.039214851 | F101: 0.033094645 | G101: 0.040076007 | H101: 0.024729956 | I101: 0.05956164 | J101: 0.094392691 | K101: 0.12922374 | L101: 0.16405479 | M101: 0.19888584 | N101: 0.23371689 | O101: 0.26854794 | P101: 0.30337899 | Q101: 0.33821004 | R101: 0.37304109 | S101: 0.40787214 | T101: 0.44270319 | U101: 0.47753424 | V101: 0.5123653 | W101: 0.54719635 | X101: 0.5820274 | Y101: 0.61685845 | Z101: 0.6516895 | AA101: 0.68652055 | AB101: 0.7213516 | AC101: 0.75618265 | AD101: 0.7910137 | AE101: 0.82584475 | AF101: 0.8606758 | AG101: 0.89550685 | AH101: 0.9303379 | AI101: 0.96516895 | AJ101: 1
A102: Share final exergy industry coal HTH/MTH | B102: Input | C102: 0.96512594 | D102: 0.963629 | E102: 0.96078618 | F102: 0.96690554 | G102: 0.95992322 | H102: 0.97526941 | I102: 0.94043836 | J102: 0.90560731 | K102: 0.87077626 | L102: 0.83594521 | M102: 0.80111416 | N102: 0.76628311 | O102: 0.73145206 | P102: 0.69662101 | Q102: 0.66178996 | R102: 0.62695891 | S102: 0.59212786 | T102: 0.55729681 | U102: 0.52246576 | V102: 0.4876347 | W102: 0.45280365 | X102: 0.4179726 | Y102: 0.38314155 | Z102: 0.3483105 | AA102: 0.31347945 | AB102: 0.2786484 | AC102: 0.24381735 | AD102: 0.2089863 | AE102: 0.17415525 | AF102: 0.1393242 | AG102: 0.10449315 | AH102: 0.069662101 | AI102: 0.03483105 | AJ102: 0
A103: Share final exergy industry coal MTH | B103: Input | C103: 0 | D103: 0 | E103: 0 | F103: 0 | G103: 0 | H103: 0 | I103: 0 | J103: 0 | K103: 0 | L103: 0 | M103: 0 | N103: 0 | O103: 0 | P103: 0 | Q103: 0 | R103: 0 | S103: 0 | T103: 0 | U103: 0 | V103: 0 | W103: 0 | X103: 0 | Y103: 0 | Z103: 0 | AA103: 0 | AB103: 0 | AC103: 0 | AD103: 0 | AE103: 0 | AF103: 0 | AG103: 0 | AH103: 0 | AI103: 0 | AJ103: 0
A104: Share final exergy industry coal LTH1 | B104: Input | C104: 0 | D104: 0 | E104: 0 | F104: 0 | G104: 0 | H104: 0 | I104: 0 | J104: 0 | K104: 0 | L104: 0 | M104: 0 | N104: 0 | O104: 0 | P104: 0 | Q104: 0 | R104: 0 | S104: 0 | T104: 0 | U104: 0 | V104: 0 | W104: 0 | X104: 0 | Y104: 0 | Z104: 0 | AA104: 0 | AB104: 0 | AC104: 0 | AD104: 0 | AE104: 0 | AF104: 0 | AG104: 0 | AH104: 0 | AI104: 0 | AJ104: 0
A105: Share final exergy industry coal LTH2 | B105: Input | C105: 0 | D105: 0 | E105: 0 | F105: 0 | G105: 0 | H105: 0 | I105: 0 | J105: 0 | K105: 0 | L105: 0 | M105: 0 | N105: 0 | O105: 0 | P105: 0 | Q105: 0 | R105: 0 | S105: 0 | T105: 0 | U105: 0 | V105: 0 | W105: 0 | X105: 0 | Y105: 0 | Z105: 0 | AA105: 0 | AB105: 0 | AC105: 0 | AD105: 0 | AE105: 0 | AF105: 0 | AG105: 0 | AH105: 0 | AI105: 0 | AJ105: 0
A106: Share final exergy industry coal LTH3 | B106: Input | C106: 0 | D106: 0 | E106: 0 | F106: 0 | G106: 0 | H106: 0 | I106: 0 | J106: 0 | K106: 0 | L106: 0 | M106: 0 | N106: 0 | O106: 0 | P106: 0 | Q106: 0 | R106: 0 | S106: 0 | T106: 0 | U106: 0 | V106: 0 | W106: 0 | X106: 0 | Y106: 0 | Z106: 0 | AA106: 0 | AB106: 0 | AC106: 0 | AD106: 0 | AE106: 0 | AF106: 0 | AG106: 0 | AH106: 0 | AI106: 0 | AJ106: 0
A107: Share final exergy industry oil HTH | B107: Input | C107: 0.0014566748 | D107: 0.0010434608 | E107: 0.0010395558 | F107: 0.00073240396 | G107: 0.00059354653 | H107: 0.000499918 | I107: 0.036196349 | J107: 0.071892781 | K107: 0.10758921 | L107: 0.14328564 | M107: 0.17898208 | N107: 0.21467851 | O107: 0.25037494 | P107: 0.28607137 | Q107: 0.3217678 | R107: 0.35746423 | S107: 0.39316066 | T107: 0.4288571 | U107: 0.46455353 | V107: 0.50024996 | W107: 0.53594639 | X107: 0.57164282 | Y107: 0.60733925 | Z107: 0.64303568 | AA107: 0.67873212 | AB107: 0.71442855 | AC107: 0.75012498 | AD107: 0.78582141 | AE107: 0.82151784 | AF107: 0.85721427 | AG107: 0.89291071 | AH107: 0.92860714 | AI107: 0.96430357 | AJ107: 1
A108: Share final exergy industry oil HTH/MTH | B108: Input | C108: 0.10256733 | D108: 0.11993191 | E108: 0.10360982 | F108: 0.089575034 | G108: 0.096812209 | H108: 0.086535213 | I108: 0.083444669 | J108: 0.080354126 | K108: 0.077263583 | L108: 0.074173039 | M108: 0.071082496 | N108: 0.067991953 | O108: 0.064901409 | P108: 0.061810866 | Q108: 0.058720323 | R108: 0.05562978 | S108: 0.052539236 | T108: 0.049448693 | U108: 0.04635815 | V108: 0.043267606 | W108: 0.040177063 | X108: 0.03708652 | Y108: 0.033995976 | Z108: 0.030905433 | AA108: 0.02781489 | AB108: 0.024724346 | AC108: 0.021633803 | AD108: 0.01854326 | AE108: 0.015452717 | AF108: 0.012362173 | AG108: 0.0092716299 | AH108: 0.0061810866 | AI108: 0.0030905433 | AJ108: 0
A109: Share final exergy industry oil MTH | B109: Input | C109: 0 | D109: 0 | E109: 0 | F109: 0 | G109: 0 | H109: 0 | I109: 0 | J109: 0 | K109: 0 | L109: 0 | M109: 0 | N109: 0 | O109: 0 | P109: 0 | Q109: 0 | R109: 0 | S109: 0 | T109: 0 | U109: 0 | V109: 0 | W109: 0 | X109: 0 | Y109: 0 | Z109: 0 | AA109: 0 | AB109: 0 | AC109: 0 | AD109: 0 | AE109: 0 | AF109: 0 | AG109: 0 | AH109: 0 | AI109: 0 | AJ109: 0
A110: Share final exergy industry oil LTH1 | B110: Input | C110: 0.21730035 | D110: 0.19395363 | E110: 0.16321178 | F110: 0.18614929 | G110: 0.16041475 | H110: 0.2055045 | I110: 0.19816505 | J110: 0.19082561 | K110: 0.18348616 | L110: 0.17614671 | M110: 0.16880727 | N110: 0.16146782 | O110: 0.15412837 | P110: 0.14678893 | Q110: 0.13944948 | R110: 0.13211004 | S110: 0.12477059 | T110: 0.11743114 | U110: 0.1100917 | V110: 0.10275225 | W110: 0.095412803 | X110: 0.088073357 | Y110: 0.08073391 | Z110: 0.073394464 | AA110: 0.066055018 | AB110: 0.058715571 | AC110: 0.051376125 | AD110: 0.044036678 | AE110: 0.036697232 | AF110: 0.029357786 | AG110: 0.022018339 | AH110: 0.014678893 | AI110: 0.0073394464 | AJ110: 0
A111: Share final exergy industry oil LTH2 | B111: Input | C111: 0.14795723 | D111: 0.14906812 | E111: 0.15821703 | F111: 0.14846874 | G111: 0.1342072 | H111: 0.13154627 | I111: 0.12684819 | J111: 0.12215011 | K111: 0.11745203 | L111: 0.11275395 | M111: 0.10805587 | N111: 0.10335779 | O111: 0.098659706 | P111: 0.093961625 | Q111: 0.089263544 | R111: 0.084565462 | S111: 0.079867381 | T111: 0.0751693 | U111: 0.070471219 | V111: 0.065773137 | W111: 0.061075056 | X111: 0.056376975 | Y111: 0.051678894 | Z111: 0.046980812 | AA111: 0.042282731 | AB111: 0.03758465 | AC111: 0.032886569 | AD111: 0.028188487 | AE111: 0.023490406 | AF111: 0.018792325 | AG111: 0.014094244 | AH111: 0.0093961625 | AI111: 0.0046980812 | AJ111: 0
A112: Share final exergy industry oil LTH3 | B112: Input | C112: 0 | D112: 0 | E112: 0 | F112: 0 | G112: 0 | H112: 0 | I112: 0 | J112: 0 | K112: 0 | L112: 0 | M112: 0 | N112: 0 | O112: 0 | P112: 0 | Q112: 0 | R112: 0 | S112: 0 | T112: 0 | U112: 0 | V112: 0 | W112: 0 | X112: 0 | Y112: 0 | Z112: 0 | AA112: 0 | AB112: 0 | AC112: 0 | AD112: 0 | AE112: 0 | AF112: 0 | AG112: 0 | AH112: 0 | AI112: 0 | AJ112: 0
... A122: Share final exergy industry natural gas LTH3 | B122: Input | C122: 0 | D122: 0 | E122: 0 | F122: 0 | G122: 0 | H122: 0 | I122: 0 | J122: 0 | K122: 0 | L122: 0 | M122: 0 | N122: 0 | O122: 0 | P122: 0 | Q122: 0 | R122: 0 | S122: 0 | T122: 0 | U122: 0 | V122: 0 | W122: 0 | X122: 0 | Y122: 0 | Z122: 0 | AA122: 0 | AB122: 0 | AC122: 0 | AD122: 0 | AE122: 0 | AF122: 0 | AG122: 0 | AH122: 0 | AI122: 0 | AJ122: 0
A123: Share final exergy industry C. Renewables HTH | B123: Input | C123: 7.8040246e-05 | D123: 0.00011814162 | E123: 0.0007788883 | F123: 0.00026172324 | G123: 0.00067391086 | H123: 0.0003322734 | I123: =1-I124-I125-I126-I127-I128-I129-I130-I131 -> 0.025320832 | J123: =1-J124-J125-J126-J127-J128-J129-J130-J131 -> 0.050308949 | K123: =1-K124-K125-K126-K127-K128-K129-K130-K131 -> 0.075297066 | L123: =1-L124-L125-L126-L127-L128-L129-L130-L131 -> 0.10028518 | M123: =1-M124-M125-M126-M127-M128-M129-M130-M131 -> 0.1252733 | N123: =1-N124-N125-N126-N127-N128-N129-N130-N131 -> 0.15026142 | O123: =1-O124-O125-O126-O127-O128-O129-O130-O131 -> 0.17524954 | P123: =1-P124-P125-P126-P127-P128-P129-P130-P131 -> 0.20023765 | ... AJ123: =1-AJ124-AJ125-AJ126-AJ127-AJ128-AJ129-AJ130-AJ131 -> 0.7
A124: Share final exergy industry C. Renewables MTH | B124: Input | C124: 0.083618563 | D124: 0.07717949 | E124: 0.073833918 | F124: 0.082134573 | G124: 0.078519155 | H124: 0.076581102 | I124: 0.077417491 | J124: 0.07825388 | K124: 0.079090269 | L124: 0.079926659 | M124: 0.080763048 | N124: 0.081599437 | O124: 0.082435826 | P124: 0.083272216 | Q124: 0.084108605 | R124: 0.084944994 | S124: 0.085781383 | T124: 0.086617772 | U124: 0.087454162 | V124: 0.088290551 | W124: 0.08912694 | X124: 0.089963329 | Y124: 0.090799719 | Z124: 0.091636108 | AA124: 0.092472497 | AB124: 0.093308886 | AC124: 0.094145275 | AD124: 0.094981665 | AE124: 0.095818054 | AF124: 0.096654443 | AG124: 0.097490832 | AH124: 0.098327222 | AI124: 0.099163611 | AJ124: 0.1
A125: Share final exergy industry C. Renewables LTH1 | B125: Input | C125: 0.88204945 | D125: 0.88668939 | E125: 0.89138565 | F125: 0.88102906 | G125: 0.87304837 | H125: 0.8747575 | I125: 0.85065901 | J125: 0.82656053 | K125: 0.80246205 | L125: 0.77836357 | M125: 0.75426509 | N125: 0.7301666 | O125: 0.70606812 | P125: 0.68196964 | Q125: 0.65787116 | R125: 0.63377268 | S125: 0.60967419 | T125: 0.58557571 | U125: 0.56147723 | V125: 0.53737875 | W125: 0.51328027 | X125: 0.48918178 | Y125: 0.4650833 | Z125: 0.44098482 | AA125: 0.41688634 | AB125: 0.39278786 | AC125: 0.36868937 | AD125: 0.34459089 | AE125: 0.32049241 | AF125: 0.29639393 | AG125: 0.27229545 | AH125: 0.24819696 | AI125: 0.22409848 | AJ125: 0.2
A126: Share final exergy industry C. Renewables LTH2 | B126: Input | C126: 0.026117339 | D126: 0.027758903 | E126: 0.026427623 | F126: 0.028525084 | G126: 0.037040304 | H126: 0.038362052 | I126: 0.036991979 | J126: 0.035621906 | K126: 0.034251832 | L126: 0.032881759 | M126: 0.031511686 | N126: 0.030141612 | O126: 0.028771539 | P126: 0.027401466 | Q126: 0.026031393 | R126: 0.024661319 | S126: 0.023291246 | T126: 0.021921173 | U126: 0.020551099 | V126: 0.019181026 | W126: 0.017810953 | X126: 0.016440879 | Y126: 0.015070806 | Z126: 0.013700733 | AA126: 0.01233066 | AB126: 0.010960586 | AC126: 0.009590513 | AD126: 0.0082204397 | AE126: 0.0068503665 | AF126: 0.0054802932 | AG126: 0.0041102199 | AH126: 0.0027401466 | AI126: 0.0013700733 | AJ126: 0
A127: Share final exergy industry C. Renewables LTH3 | B127: Input | C127: 0 | D127: 0 | E127: 0 | F127: 0 | G127: 0 | H127: 0 | I127: 0 | J127: 0 | K127: 0 | L127: 0 | M127: 0 | N127: 0 | O127: 0 | P127: 0 | Q127: 0 | R127: 0 | S127: 0 | T127: 0 | U127: 0 | V127: 0 | W127: 0 | X127: 0 | Y127: 0 | Z127: 0 | AA127: 0 | AB127: 0 | AC127: 0 | AD127: 0 | AE127: 0 | AF127: 0 | AG127: 0 | AH127: 0 | AI127: 0 | AJ127: 0
A128: Share final exergy industry C. Renewables Diesel vehicles | B128: Input | C128: 0.00164327 | D128: 0.0016127689 | E128: 0.0014147253 | F128: 0.0011724646 | G128: 0.0012811557 | H128: 0.0024500717 | I128: 0.0023625691 | J128: 0.0022750665 | K128: 0.002187564 | L128: 0.0021000614 | M128: 0.0020125589 | N128: 0.0019250563 | O128: 0.0018375537 | P128: 0.0017500512 | Q128: 0.0016625486 | R128: 0.0015750461 | S128: 0.0014875435 | T128: 0.0014000409 | U128: 0.0013125384 | V128: 0.0012250358 | W128: 0.0011375333 | X128: 0.0010500307 | Y128: 0.00096252815 | Z128: 0.00087502559 | AA128: 0.00078752303 | AB128: 0.00070002047 | AC128: 0.00061251791 | AD128: 0.00052501536 | AE128: 0.0004375128 | AF128: 0.00035001024 | AG128: 0.00026250768 | AH128: 0.00017500512 | AI128: 8.7502559e-05 | AJ128: 0
A129: Share final exergy industry C. Renewables HTH/MTH | B129: Input | C129: 0.00031937971 | D129: 0.00032528325 | E129: 0 | F129: 0 | G129: 0 | H129: 0 | I129: 0 | J129: 0 | K129: 0 | L129: 0 | M129: 0 | N129: 0 | O129: 0 | P129: 0 | Q129: 0 | R129: 0 | S129: 0 | T129: 0 | U129: 0 | V129: 0 | W129: 0 | X129: 0 | Y129: 0 | Z129: 0 | AA129: 0 | AB129: 0 | AC129: 0 | AD129: 0 | AE129: 0 | AF129: 0 | AG129: 0 | AH129: 0 | AI129: 0 | AJ129: 0
A130: Share final exergy industry C. Renewables MW2 | B130: Input | C130: 0 | D130: 0 | E130: 0 | F130: 0 | G130: 0 | H130: 0 | I130: 0 | J130: 0 | K130: 0 | L130: 0 | M130: 0 | N130: 0 | O130: 0 | P130: 0 | Q130: 0 | R130: 0 | S130: 0 | T130: 0 | U130: 0 | V130: 0 | W130: 0 | X130: 0 | Y130: 0 | Z130: 0 | AA130: 0 | AB130: 0 | AC130: 0 | AD130: 0 | AE130: 0 | AF130: 0 | AG130: 0 | AH130: 0 | AI130: 0 | AJ130: 0
A131: Share final exergy industry C. Renewables Oil-SMD | B131: Input | C131: 0.006173957 | D131: 0.0063168787 | E131: 0.0061587973 | F131: 0.0068773115 | G131: 0.0094370807 | H131: 0.0075165636 | I131: 0.0072481149 | J131: 0.0069796662 | K131: 0.0067112175 | L131: 0.0064427688 | M131: 0.0061743201 | N131: 0.0059058714 | O131: 0.0056374227 | P131: 0.005368974 | Q131: 0.0051005253 | R131: 0.0048320766 | S131: 0.0045636279 | T131: 0.0042951792 | U131: 0.0040267305 | V131: 0.0037582818 | W131: 0.0034898331 | X131: 0.0032213844 | Y131: 0.0029529357 | Z131: 0.002684487 | AA131: 0.0024160383 | AB131: 0.0021475896 | AC131: 0.0018791409 | AD131: 0.0016106922 | AE131: 0.0013422435 | AF131: 0.0010737948 | AG131: 0.0008053461 | AH131: 0.0005368974 | AI131: 0.0002684487 | AJ131: 0
A132: Share final exergy industry Heat HTH | B132: Input | C132: 0.099728921 | D132: 0.25524961 | E132: 0.28444306 | F132: 0.28269204 | G132: 0.35637922 | H132: 0.45645465 | I132: 0.25352224 | J132: 0.24936932 | K132: 0.2452164 | L132: 0.24106348 | M132: 0.23691056 | N132: 0.23275764 | O132: 0.22860472 | P132: 0.2244518 | Q132: 0.22029888 | R132: 0.21614596 | S132: 0.21199304 | T132: 0.20784012 | U132: 0.2036872 | V132: 0.19953428 | W132: 0.19538136 | X132: 0.19122844 | Y132: 0.18707552 | Z132: 0.18292259 | AA132: 0.17876967 | AB132: 0.17461675 | AC132: 0.17046383 | AD132: 0.16631091 | AE132: 0.16215799 | AF132: 0.15800507 | AG132: 0.15385215 | AH132: 0.14969923 | AI132: 0.14554631 | AJ132: 0.14139339
A133: Share final exergy industry Heat MTH | B133: Input | C133: 0.56282961 | D133: 0.45724245 | E133: 0.43618316 | F133: 0.3681113 | G133: 0.30637656 | H133: 0.36443399 | I133: 0.44103386 | J133: 0.44193418 | K133: 0.44283449 | L133: 0.4437348 | M133: 0.44463511 | N133: 0.44553542 | O133: 0.44643573 | P133: 0.44733604 | Q133: 0.44823635 | R133: 0.44913666 | S133: 0.45003697 | T133: 0.45093728 | U133: 0.45183759 | V133: 0.4527379 | W133: 0.45363821 | X133: 0.45453852 | Y133: 0.45543883 | Z133: 0.45633914 | AA133: 0.45723945 | AB133: 0.45813976 | AC133: 0.45904007 | AD133: 0.45994038 | AE133: 0.46084069 | AF133: 0.461741 | AG133: 0.46264131 | AH133: 0.46354162 | AI133: 0.46444194 | AJ133: 0.46534225
A134: Share final exergy industry Heat LTH1 | B134: Input | C134: 0.3374428 | D134: 0.28750794 | E134: 0.27937271 | F134: 0.34919666 | G134: 0.33724285 | H134: 0.17910959 | I134: 0.30544307 | J134: 0.3086956 | K134: 0.31194813 | L134: 0.31520066 | M134: 0.31845319 | N134: 0.32170572 | O134: 0.32495825 | P134: 0.32821078 | Q134: 0.33146331 | R134: 0.33471584 | S134: 0.33796837 | T134: 0.3412209 | U134: 0.34447343 | V134: 0.34772596 | W134: 0.3509785 | X134: 0.35423103 | Y134: 0.35748356 | Z134: 0.36073609 | AA134: 0.36398862 | AB134: 0.36724115 | AC134: 0.37049368 | AD134: 0.37374621 | AE134: 0.37699874 | AF134: 0.38025127 | AG134: 0.3835038 | AH134: 0.38675633 | AI134: 0.39000886 | AJ134: 0.39326139
A135: Share final exergy industry Heat LTH3 | B135: Input | C135: 0 | D135: 0 | E135: 0 | F135: 0 | G135: 0 | H135: 0 | I135: 8.2679567e-07 | J135: 9.0616316e-07 | K135: 9.8553065e-07 | L135: 1.0648981e-06 | M135: 1.1442656e-06 | N135: 1.2236331e-06 | O135: 1.3030006e-06 | P135: 1.3823681e-06 | Q135: 1.4617356e-06 | R135: 1.5411031e-06 | S135: 1.6204706e-06 | T135: 1.6998381e-06 | U135: 1.7792056e-06 | V135: 1.8585731e-06 | W135: 1.9379406e-06 | X135: 2.017308e-06 | Y135: 2.0966755e-06 | Z135: 2.176043e-06 | AA135: 2.2554105e-06 | AB135: 2.334778e-06 | AC135: 2.4141455e-06 | AD135: 2.493513e-06 | AE135: 2.5728805e-06 | AF135: 2.652248e-06 | AG135: 2.7316155e-06 | AH135: 2.810983e-06 | AI135: 2.8903504e-06 | AJ135: 2.9697179e-06
... A187: Share Final Exergy Energy industry own use Electricity Generic | B187: Input | C187: 1 | D187: 1 | E187: 1 | F187: 1 | G187: 1 | H187: 1 | I187: 1 | J187: 1 | K187: 1 | L187: 1 | M187: 1 | N187: 1 | O187: 1 | P187: 1 | Q187: 1 | R187: 1 | S187: 1 | T187: 1 | U187: 1 | V187: 1 | W187: 1 | X187: 1 | Y187: 1 | Z187: 1 | AA187: 1 | AB187: 1 | AC187: 1 | AD187: 1 | AE187: 1 | AF187: 1 | AG187: 1 | AH187: 1 | AI187: 1 | AJ187: 1
A189: final exergy industry coal HTH [TJ] | B189: Computed | C189: =+C$66*C101 -> 0.00065554313 | D189: =+D$66*D101 -> 0.00060339264 | E189: =+E$66*E101 -> 0.0006382428 | F189: =+F$66*F101 -> 0.00061183464 | G189: =+G$66*G101 -> 0.00062062257 | H189: =+H$66*H101 -> 0.00040960521 | I189: =+I$66*I101 -> 0.00086743663 | J189: =+J$66*J101 -> 0.0011857534 | ... AJ189: =+AJ$66*AJ101 -> 0.00078389634
A190: final exergy industry coal HTH/MTH [TJ] | B190: Computed | C190: =+C$66*C102 -> 0.018141862 | D190: =+D$66*D102 -> 0.015985725 | E190: =+E$66*E102 -> 0.015637312 | F190: =+F$66*F102 -> 0.01787559 | G190: =+G$66*G102 -> 0.014865503 | H190: =+H$66*H102 -> 0.016153504 | I190: =+I$66*I102 -> 0.013696243 | J190: =+J$66*J102 -> 0.011376166 | ... AJ190: =+AJ$66*AJ102 -> 0
A191: final exergy industry coal MTH [TJ] | B191: Computed | C191: =+C$66*C103 -> 0 | D191: =+D$66*D103 -> 0 | E191: =+E$66*E103 -> 0 | F191: =+F$66*F103 -> 0 | G191: =+G$66*G103 -> 0 | H191: =+H$66*H103 -> 0 | I191: =+I$66*I103 -> 0 | J191: =+J$66*J103 -> 0 | ... AJ191: =+AJ$66*AJ103 -> 0
A192: final exergy industry coal LTH1 [TJ] | B192: Computed | C192: =+C$66*C104 -> 0 | D192: =+D$66*D104 -> 0 | E192: =+E$66*E104 -> 0 | F192: =+F$66*F104 -> 0 | G192: =+G$66*G104 -> 0 | H192: =+H$66*H104 -> 0 | I192: =+I$66*I104 -> 0 | J192: =+J$66*J104 -> 0 | ... AJ192: =+AJ$66*AJ104 -> 0
A193: final exergy industry coal LTH2 [TJ] | B193: Computed | C193: =+C$66*C105 -> 0 | D193: =+D$66*D105 -> 0 | E193: =+E$66*E105 -> 0 | F193: =+F$66*F105 -> 0 | G193: =+G$66*G105 -> 0 | H193: =+H$66*H105 -> 0 | I193: =+I$66*I105 -> 0 | J193: =+J$66*J105 -> 0 | ... AJ193: =+AJ$66*AJ105 -> 0
...

Sheet Decarbonizatio
A1: Scenarios up to 2050 - National Roadmap 2050
C2: 2017 | D2: 2018 | E2: 2019 | F2: 2020 | G2: 2021 | H2: 2022 | I2: 2023 | J2: 2024 | K2: 2025 | L2: 2026 | M2: 2027 | N2: 2028 | O2: 2029 | P2: 2030 | Q2: 2031 | R2: 2032 | S2: 2033 | T2: 2034 | U2: 2035 | V2: 2036 | W2: 2037 | X2: 2038 | Y2: 2039 | Z2: 2040 | AA2: 2041 | AB2: 2042 | AC2: 2043 | AD2: 2044 | AE2: 2045 | AF2: 2046 | AG2: 2047 | AH2: 2048 | AI2: 2049 | AJ2: 2050
A3: New Solar power [GW] | B3: Computed | D3: =D10-C10 -> 0.098 | E3: =E10-D10 -> 0.253 | F3: =F10-E10 -> 0.221 | G3: =G10-F10 -> 0.626 | H3: =H10-G10 -> 1 | I3: =I10-H10 -> 1.223 | J3: =J10-I10 -> 1.768 | K3: =K10-J10 -> 0.54 | ... AJ3: =AJ10-AI10 -> 1.746
A4: New Onshore Wind power [GW] | B4: Computed | D4: =D11-C11 -> 0.048 | E4: =E11-D11 -> 0.051 | F4: =F11-E11 -> -0.101 | G4: =G11-F11 -> 0.305 | H4: =H11-G11 -> 0.111 | I4: =I11-H11 -> 0 | J4: =J11-I11 -> 0.045 | K4: =K11-J11 -> 0.18 | ... AJ4: =AJ11-AI11 -> 0.569
A5: New Offshore Wind power [GW] | B5: Computed | D5: =D12-C12 -> 0 | E5: =E12-D12 -> 0 | F5: =F12-E12 -> 0.025 | G5: =G12-F12 -> 0 | H5: =H12-G12 -> 0 | I5: =I12-H12 -> 0 | J5: =J12-I12 -> 0 | K5: =K12-J12 -> 0.04 | ... AJ5: =AJ12-AI12 -> 0.01
A6: New Batteries [GWh] | B6: Computed | D6: =D13-C13 -> 0 | E6: =E13-D13 -> 0 | F6: =F13-E13 -> 0.02 | G6: =G13-F13 -> 0 | H6: =H13-G13 -> 0.03 | I6: =I13-H13 -> 0 | J6: =J13-I13 -> 0.01 | K6: =K13-J13 -> 0.07 | ... AJ6: =AJ13-AI13 -> 0.02
A7: New Hydrogen [GW] | B7: Computed | D7: =D14-C14 -> 0 | E7: =E14-D14 -> 0 | F7: =F14-E14 -> 0 | G7: =G14-F14 -> 0 | H7: =H14-G14 -> 0 | I7: =I14-H14 -> 0.012 | J7: =J14-I14 -> 0.013 | K7: =K14-J14 -> 0.012 | ... AJ7: =AJ14-AI14 -> 0.151
A8: New Hydropower [GW] | B8: Computed | D8: =D15-C15 -> 0.01 | E8: =E15-D15 -> 0.026 | F8: =F15-E15 -> -0.021 | G8: =G15-F15 -> 0.014 | H8: =H15-G15 -> 0.934 | I8: =I15-H15 -> -0.002 | J8: =J15-I15 -> 0.16 | K8: =K15-J15 -> 0.14 | ... AJ8: =AJ15-AI15 -> 0
A10: Solar power [GW] | B10: Input | C10: 0.619 | D10: 0.717 | E10: 0.97 | F10: 1.191 | G10: 1.817 | H10: 2.817 | I10: 4.04 | J10: 5.808 | K10: 6.348 | L10: 8.094 | M10: 9.84 | N10: 11.586 | O10: 13.332 | P10: 15.078 | Q10: 16.824 | R10: 18.571 | S10: 20.317 | T10: 22.063 | U10: 23.809 | V10: 25.555 | W10: 27.301 | X10: 29.047 | Y10: 30.793 | Z10: 32.539 | AA10: 34.285 | AB10: 36.031 | AC10: 37.777 | AD10: 39.524 | AE10: 41.27 | AF10: 43.016 | AG10: 44.762 | AH10: 46.508 | AI10: 48.254 | AJ10: 50
A11: Onshore Wind power [GW] | B11: Input | C11: 5.124 | D11: 5.172 | E11: 5.223 | F11: 5.122 | G11: 5.427 | H11: 5.538 | I11: 5.538 | J11: 5.583 | K11: 5.763 | L11: 6.332 | M11: 6.902 | N11: 7.471 | O11: 8.041 | P11: 8.61 | Q11: 9.18 | R11: 9.749 | S11: 10.319 | T11: 10.888 | U11: 11.458 | V11: 12.027 | W11: 12.597 | X11: 13.166 | Y11: 13.736 | Z11: 14.305 | AA11: 14.875 | AB11: 15.444 | AC11: 16.014 | AD11: 16.583 | AE11: 17.153 | AF11: 17.722 | AG11: 18.292 | AH11: 18.861 | AI11: 19.431 | AJ11: 20
A12: Offshore Wind Power [GW] | B12: Input | C12: 0 | D12: 0 | E12: 0 | F12: 0.025 | G12: 0.025 | H12: 0.025 | I12: 0.025 | J12: 0.025 | K12: 0.065 | L12: 0.105 | M12: 0.145 | N12: 0.185 | O12: 0.225 | P12: 0.265 | Q12: 0.345 | R12: 0.425 | S12: 0.505 | T12: 0.585 | U12: 0.665 | V12: 0.745 | W12: 0.825 | X12: 0.905 | Y12: 0.985 | Z12: 1.065 | AA12: 1.075 | AB12: 1.085 | AC12: 1.095 | AD12: 1.105 | AE12: 1.115 | AF12: 1.125 | AG12: 1.135 | AH12: 1.145 | AI12: 1.155 | AJ12: 1.165
A13: Batteries [GWh] | B13: Input | C13: 0 | D13: 0 | E13: 0 | F13: 0.02 | G13: 0.02 | H13: 0.05 | I13: 0.05 | J13: 0.06 | K13: 0.13 | L13: 0.14 | M13: 0.15 | N13: 0.17 | O13: 0.18 | P13: 0.19 | Q13: 0.21 | R13: 0.22 | S13: 0.24 | T13: 0.26 | U13: 0.28 | V13: 0.3 | W13: 0.31 | X13: 0.33 | Y13: 0.35 | Z13: 0.37 | AA13: 0.39 | AB13: 0.41 | AC13: 0.43 | AD13: 0.45 | AE13: 0.47 | AF13: 0.49 | AG13: 0.51 | AH13: 0.53 | AI13: 0.55 | AJ13: 0.57
A14: Hydrogen [GW] | B14: Input | C14: 0 | D14: 0 | E14: 0 | F14: 0 | G14: 0 | H14: 0 | I14: 0.012 | J14: 0.025 | K14: 0.037 | L14: 0.049 | M14: 0.061 | N14: 0.073 | O14: 0.085 | P14: 0.096 | Q14: 0.252 | R14: 0.41 | S14: 0.569 | T14: 0.726 | U14: 0.882 | V14: 1.034 | W14: 1.182 | X14: 1.325 | Y14: 1.462 | Z14: 1.591 | AA14: 1.77 | AB14: 1.948 | AC14: 2.127 | AD14: 2.298 | AE14: 2.466 | AF14: 2.631 | AG14: 2.792 | AH14: 2.95 | AI14: 3.104 | AJ14: 3.255
A15: Hydro power [GW] | B15: Input | C15: 7.226 | D15: 7.236 | E15: 7.262 | F15: 7.241 | G15: 7.255 | H15: 8.189 | I15: 8.187 | J15: 8.347 | K15: 8.487 | L15: 8.627 | M15: 8.767 | N15: 8.907 | O15: 9.047 | P15: 9.187 | Q15: 9.187 | R15: 9.187 | S15: 9.187 | T15: 9.187 | U15: 9.187 | V15: 9.187 | W15: 9.187 | X15: 9.187 | Y15: 9.187 | Z15: 9.187 | AA15: 9.187 | AB15: 9.187 | AC15: 9.187 | AD15: 9.187 | AE15: 9.187 | AF15: 9.187 | AG15: 9.187 | AH15: 9.187 | AI15: 9.187 | AJ15: 9.187
A16: Total Renewable [GW] | C16: =SUM(C10:C15) -> 12.969 | D16: =SUM(D10:D15) -> 13.125 | E16: =SUM(E10:E15) -> 13.455 | F16: =SUM(F10:F15) -> 13.599 | G16: =SUM(G10:G15) -> 14.544 | H16: =SUM(H10:H15) -> 16.619 | I16: =SUM(I10:I15) -> 17.852 | J16: =SUM(J10:J15) -> 19.848 | ... AJ16: =SUM(AJ10:AJ15) -> 84.177
A18: Extra Solar compared to BAU [GW] | B18: Computed | C18: =+IF(C10-BAU!C10<0,0,C10-BAU!C10) -> 0 | D18: =+IF(D10-BAU!D10<0,0,D10-BAU!D10) -> 0 | E18: =+IF(E10-BAU!E10<0,0,E10-BAU!E10) -> 0 | F18: =+IF(F10-BAU!F10<0,0,F10-BAU!F10) -> 0 | G18: =+IF(G10-BAU!G10<0,0,G10-BAU!G10) -> 0 | H18: =+IF(H10-BAU!H10<0,0,H10-BAU!H10) -> 0 | I18: =+IF(I10-BAU!I10<0,0,I10-BAU!I10) -> 0 | J18: =+IF(J10-BAU!J10<0,0,J10-BAU!J10) -> 0 | K18: =+IF(K3-BAU!K3<0,0,K3-BAU!K3) -> 0 | L18: =+IF(L3-BAU!L3<0,0,L3-BAU!L3) -> 1.2001538 | M18: =+IF(M3-BAU!M3<0,0,M3-BAU!M3) -> 1.2001538 | N18: =+IF(N3-BAU!N3<0,0,N3-BAU!N3) -> 1.2001538 | O18: =+IF(O3-BAU!O3<0,0,O3-BAU!O3) -> 1.2001538 | P18: =+IF(P3-BAU!P3<0,0,P3-BAU!P3) -> 1.2001538 | Q18: =+IF(Q3-BAU!Q3<0,0,Q3-BAU!Q3) -> 1.2001538 | R18: =+IF(R3-BAU!R3<0,0,R3-BAU!R3) -> 1.2011538 | ... AJ18: =+IF(AJ3-BAU!AJ3<0,0,AJ3-BAU!AJ3) -> 1.2001538
A19: Extra Onshore Wind compared to BAU [GW] | B19: Computed | C19: =+C11-BAU!C11 -> 0 | D19: =+D11-BAU!D11 -> 0 | E19: =+E11-BAU!E11 -> 0 | F19: =+F11-BAU!F11 -> 0 | G19: =+G11-BAU!G11 -> 0 | H19: =+H11-BAU!H11 -> 0 | I19: =+I11-BAU!I11 -> 0 | J19: =+J11-BAU!J11 -> 0 | K19: =+K4-BAU!K4 -> 0.1123 | L19: =+L4-BAU!L4 -> 0.4983 | M19: =+M4-BAU!M4 -> 0.4963 | N19: =+N4-BAU!N4 -> 0.4923 | O19: =+O4-BAU!O4 -> 0.4903 | P19: =+P4-BAU!P4 -> 0.4863 | Q19: =+Q4-BAU!Q4 -> 0.4843 | R19: =+R4-BAU!R4 -> 0.4803 | ... AJ19: =+AJ4-BAU!AJ4 -> 0.4263
A20: Extra Offshore Wind compared to BAU [GW] | B20: Computed | C20: =+C12-BAU!C12 -> 0 | D20: =+D12-BAU!D12 -> 0 | E20: =+E12-BAU!E12 -> 0 | F20: =+F12-BAU!F12 -> 0 | G20: =+G12-BAU!G12 -> 0 | H20: =+H12-BAU!H12 -> 0 | I20: =+I12-BAU!I12 -> 0 | J20: =+J12-BAU!J12 -> 0 | K20: =+K5-BAU!K5 -> 0.04 | L20: =+L5-BAU!L5 -> 0.04 | M20: =+M5-BAU!M5 -> 0.04 | N20: =+N5-BAU!N5 -> 0.04 | O20: =+O5-BAU!O5 -> 0.04 | P20: =+P5-BAU!P5 -> 0.04 | Q20: =+Q5-BAU!Q5 -> 0.08 | R20: =+R5-BAU!R5 -> 0.08 | ... AJ20: =+AJ5-BAU!AJ5 -> 0.01
A21: Extra Batteries compared to BAU [GW] | B21: Computed | C21: =+C13-BAU!C13 -> 0 | D21: =+D13-BAU!D13 -> 0 | E21: =+E13-BAU!E13 -> 0 | F21: =+F13-BAU!F13 -> 0 | G21: =+G13-BAU!G13 -> 0 | H21: =+H13-BAU!H13 -> 0 | I21: =+I13-BAU!I13 -> 0 | J21: =+J13-BAU!J13 -> 0 | K21: =+K6-BAU!K6 -> 0.07 | L21: =+L6-BAU!L6 -> 0.01 | M21: =+M6-BAU!M6 -> 0.01 | N21: =+N6-BAU!N6 -> 0.02 | O21: =+O6-BAU!O6 -> 0.01 | P21: =+P6-BAU!P6 -> 0.01 | Q21: =+Q6-BAU!Q6 -> 0.02 | R21: =+R6-BAU!R6 -> 0.01 | ... AJ21: =+AJ6-BAU!AJ6 -> 0.02
A22: Extra Hydrogen compared to BAU [GW] | B22: Computed | C22: =+C14 -> 0 | D22: =+D14 -> 0 | E22: =+E14 -> 0 | F22: =+F14 -> 0 | G22: =+G14 -> 0 | H22: =+H14 -> 0 | I22: =+I14 -> 0.012 | J22: =+J14 -> 0.025 | K22: =+K7 -> 0.012 | L22: =+L7 -> 0.012 | M22: =+M7 -> 0.012 | N22: =+N7 -> 0.012 | O22: =+O7 -> 0.012 | P22: =+P7 -> 0.011 | Q22: =+Q7 -> 0.156 | R22: =+R7 -> 0.158 | ... AJ22: =+AJ7 -> 0.151
A23: Extra Hydropower compared to BAU [GW] | B23: Computed | C23: =+C15-BAU!C15 -> 0 | D23: =+D15-BAU!D15 -> 0 | E23: =+E15-BAU!E15 -> 0 | F23: =+F15-BAU!F15 -> 0 | G23: =+G15-BAU!G15 -> 0 | H23: =+H15-BAU!H15 -> 0 | I23: =+I15-BAU!I15 -> 0 | J23: =+J15-BAU!J15 -> 0 | K23: =+K8-BAU!K8 -> 0.14 | L23: =+L8-BAU!L8 -> 0.14 | M23: =+M8-BAU!M8 -> 0.14 | N23: =+N8-BAU!N8 -> 0.14 | O23: =+O8-BAU!O8 -> 0.14 | P23: =+P8-BAU!P8 -> 0.14 | Q23: =+Q8-BAU!Q8 -> 0 | R23: =+R8-BAU!R8 -> 0 | ... AJ23: =+AJ8-BAU!AJ8 -> 0
A26: Cost per GW solar [Euro/GW] | B26: Input | C26: 1446720000 | D26: 1236400000 | E26: 1021680000 | F26: 896720000 | G26: 836000000 | H26: 799040000 | I26: 667040000 | J26: 5.2253277e+08 | K26: 4.4974812e+08 | L26: 3.8710179e+08 | M26: 3.331816e+08 | N26: 2.8677206e+08 | O26: 2.46827e+08 | P26: 2.1244597e+08 | Q26: 1.8285394e+08 | R26: 1.5738384e+08 | S26: 1.3546153e+08 | T26: 1.1659282e+08 | U26: 1.0035237e+08 | V26: 100000000 | W26: 100000000 | X26: 100000000 | Y26: 100000000 | Z26: 100000000 | AA26: 100000000 | AB26: 100000000 | AC26: 100000000 | AD26: 100000000 | AE26: 100000000 | AF26: 100000000 | AG26: 100000000 | AH26: 100000000 | AI26: 100000000 | AJ26: 100000000
A27: Cost per GW of Onshore wind [Euro/GW] | B27: Input | C27: 1686960000 | D27: 1600720000 | E27: 1518000000 | F27: 1365760000 | G27: 1294480000 | H27: 1163360000 | I27: 1020800000 | J27: 1.0655588e+09 | K27: 1.0135909e+09 | L27: 9.6415749e+08 | M27: 9.1713498e+08 | N27: 8.7240578e+08 | O27: 8.2985805e+08 | P27: 7.8938539e+08 | Q27: 7.5088661e+08 | R27: 7.1426544e+08 | S27: 6.794303e+08 | T27: 6.462941e+08 | U27: 6.1477396e+08 | V27: 5.8479108e+08 | W27: 5.5627048e+08 | X27: 5.2914085e+08 | Y27: 5.0333435e+08 | Z27: 4.7878644e+08 | AA27: 4.5543575e+08 | AB27: 4.3322389e+08 | AC27: 4.1209531e+08 | AD27: 3.9199718e+08 | AE27: 3.7287926e+08 | AF27: 3.5469372e+08 | AG27: 3.373951e+08 | AH27: 3.2094015e+08 | AI27: 3.0528771e+08 | AJ27: 2.9039866e+08
A28: Cost per GW of Offshore wind [Euro/GW] | B28: Input | C28: 4788960000 | D28: 4684240000 | E28: 4684240000 | F28: 3753200000 | G28: 3177680000 | H28: 2785200000 | I28: 3060640000 | J28: 2464000000 | K28: 2.7915727e+09 | L28: 2.6554261e+09 | M28: 2.5259195e+09 | N28: 2.4027289e+09 | O28: 2.2855464e+09 | P28: 2.174079e+09 | Q28: 2.0680479e+09 | R28: 1.9671881e+09 | S28: 1.8712472e+09 | T28: 1.7799854e+09 | U28: 1.6931744e+09 | V28: 1.6105974e+09 | W28: 1.5320476e+09 | X28: 1.4573288e+09 | Y28: 1.386254e+09 | Z28: 1.3186456e+09 | AA28: 1.2543345e+09 | AB28: 1.1931599e+09 | AC28: 1.1349688e+09 | AD28: 1.0796157e+09 | AE28: 1.0269622e+09 | AF28: 9.7687668e+08 | AG28: 9.2923384e+08 | AH28: 8.8391457e+08 | AI28: 8.4080555e+08 | AJ28: 7.9979898e+08
A29: Cost per GW of Batteries [Euro/GWh] | B29: Input | C29: 660000000 | D29: 616000000 | E29: 281600000 | F29: 264000000 | G29: 249040000 | H29: 315040000 | I29: 240240000 | J29: 1.5698899e+08 | K29: 1.2853171e+08 | L29: 1.0523287e+08 | M29: 86157384 | N29: 70539700 | O29: 57753021 | P29: 47284175 | Q29: 38713008 | R29: 31695530 | S29: 30000000 | T29: 30000000 | U29: 30000000 | V29: 30000000 | W29: 30000000 | X29: 30000000 | Y29: 30000000 | Z29: 30000000 | AA29: 30000000 | AB29: 30000000 | AC29: 30000000 | AD29: 30000000 | AE29: 30000000 | AF29: 30000000 | AG29: 30000000 | AH29: 30000000 | AI29: 30000000 | AJ29: 30000000
A30: Cost per GW of Hydrogen [Euro/GW] | B30: Input | C30: 880000000 | D30: 880000000 | E30: 880000000 | F30: 880000000 | G30: 8.5653333e+08 | H30: 8.3306667e+08 | I30: 809600000 | J30: 7.8613333e+08 | K30: 7.6266667e+08 | L30: 739200000 | M30: 7.1573333e+08 | N30: 6.9226667e+08 | O30: 668800000 | P30: 6.4533333e+08 | Q30: 6.2186667e+08 | R30: 598400000 | S30: 5.7493333e+08 | T30: 5.5146667e+08 | U30: 528000000 | V30: 5.0453333e+08 | W30: 4.8106667e+08 | X30: 457600000 | Y30: 4.3413333e+08 | Z30: 4.1066667e+08 | AA30: 387200000 | AB30: 3.6373333e+08 | AC30: 3.4026667e+08 | AD30: 316800000 | AE30: 2.9333333e+08 | AF30: 2.6986667e+08 | AG30: 246400000 | AH30: 2.2293333e+08 | AI30: 1.9946667e+08 | AJ30: 176000000
A31: Cost per GW of Hydropower [Euro/GW] | B31: Input | C31: 1874400000 | D31: 1468720000 | E31: 1806640000 | F31: 1892880000 | G31: 2081200000 | H31: 2686640000 | I31: 2469280000 | J31: 2469280000 | K31: 2469280000 | L31: 2469280000 | M31: 2469280000 | N31: 2469280000 | O31: 2469280000 | P31: 2469280000 | Q31: 2469280000 | R31: 2469280000 | S31: 2469280000 | T31: 2469280000 | U31: 2469280000 | V31: 2469280000 | W31: 2469280000 | X31: 2469280000 | Y31: 2469280000 | Z31: 2469280000 | AA31: 2469280000 | AB31: 2469280000 | AC31: 2469280000 | AD31: 2469280000 | AE31: 2469280000 | AF31: 2469280000 | AG31: 2469280000 | AH31: 2469280000 | AI31: 2469280000 | AJ31: 2469280000
A32: Extra Cost Solar [Euro] | B32: Computed | C32: =+C26*C18 -> 0 | D32: =+D26*D18 -> 0 | E32: =+E26*E18 -> 0 | F32: =+F26*F18 -> 0 | G32: =+G26*G18 -> 0 | H32: =+H26*H18 -> 0 | I32: =+I26*I18 -> 0 | J32: =+J26*J18 -> 0 | ... AJ32: =+AJ26*AJ18 -> 1.2001538e+08
A33: Extra Cost Onshore Wind [Euro] | B33: Computed | C33: =+C27*C19 -> 0 | D33: =+D27*D19 -> 0 | E33: =+E27*E19 -> 0 | F33: =+F27*F19 -> 0 | G33: =+G27*G19 -> 0 | H33: =+H27*H19 -> 0 | I33: =+I27*I19 -> 0 | J33: =+J27*J19 -> 0 | ... AJ33: =+AJ27*AJ19 -> 1.2379695e+08
A34: Extra Cost Offshore Wind [Euro] | B34: Computed | C34: =+C28*C20 -> 0 | D34: =+D28*D20 -> 0 | E34: =+E28*E20 -> 0 | F34: =+F28*F20 -> 0 | G34: =+G28*G20 -> 0 | H34: =+H28*H20 -> 0 | I34: =+I28*I20 -> 0 | J34: =+J28*J20 -> 0 | ... AJ34: =+AJ28*AJ20 -> 7997989.8
A35: Extra Cost Batteries [Euro] | B35: Computed | C35: =+C29*C21 -> 0 | D35: =+D29*D21 -> 0 | E35: =+E29*E21 -> 0 | F35: =+F29*F21 -> 0 | G35: =+G29*G21 -> 0 | H35: =+H29*H21 -> 0 | I35: =+I29*I21 -> 0 | J35: =+J29*J21 -> 0 | ... AJ35: =+AJ29*AJ21 -> 600000
A36: Extra Cost Hydrogen [Euro] | B36: Computed | C36: =+C30*C22 -> 0 | D36: =+D30*D22 -> 0 | E36: =+E30*E22 -> 0 | F36: =+F30*F22 -> 0 | G36: =+G30*G22 -> 0 | H36: =+H30*H22 -> 0 | I36: =+I30*I22 -> 9715200 | J36: =+J30*J22 -> 19653333 | ... AJ36: =+AJ30*AJ22 -> 26576000
A37: Extra Cost Hydropower [Euro] | B37: Computed | C37: =+C31*C23 -> 0 | D37: =+D31*D23 -> 0 | E37: =+E31*E23 -> 0 | F37: =+F31*F23 -> 0 | G37: =+G31*G23 -> 0 | H37: =+H31*H23 -> 0 | I37: =+I31*I23 -> 0 | J37: =+J31*J23 -> 0 | ... AJ37: =+AJ31*AJ23 -> 0
A38: Extra Cost tot [Mrd Euros] | B38: Computed | C38: =+(C33+C32+C34+C35+C36+C37)/10^9 -> 0 | D38: =+(D33+D32+D34+D35+D36+D37)/10^9 -> 0 | E38: =+(E33+E32+E34+E35+E36+E37)/10^9 -> 0 | F38: =+(F33+F32+F34+F35+F36+F37)/10^9 -> 0 | G38: =+(G33+G32+G34+G35+G36+G37)/10^9 -> 0 | H38: =+(H33+H32+H34+H35+H36+H37)/10^9 -> 0 | I38: =+(I33+I32+I34+I35+I36+I37)/10^9 -> 0.0097152 | J38: =+(J33+J32+J34+J35+J36+J37)/10^9 -> 0.019653333 | ... AJ38: =+(AJ33+AJ32+AJ34+AJ35+AJ36+AJ37)/10^9 -> 0.27898632
A40: Investment Industry [Mrd Euro] | B40: Input | C40: 8.0532 | D40: 8.5546 | E40: 8.5605 | F40: 8.3117 | G40: 9.503 | H40: 10.0172 | I40: 3.045424 | J40: 3.1051382 | K40: 3.1660233 | L40: 3.2281022 | M40: 3.2913983 | N40: 3.3559355 | O40: 3.4217382 | P40: 3.4888311 | Q40: 6.1305618 | R40: 6.2507688 | S40: 6.3733329 | T40: 6.4983003 | U40: 6.6257179 | V40: 6.7556339 | W40: 6.8880974 | X40: 7.0231581 | Y40: 7.1608671 | Z40: 7.3012762 | AA40: 6.8470453 | AB40: 6.9813011 | AC40: 7.1181893 | AD40: 7.2577617 | AE40: 7.4000707 | AF40: 7.5451702 | AG40: 7.6931147 | AH40: 7.8439601 | AI40: 7.9977632 | AJ40: 8.1545821
A41: Investment Transport [Mrd Euro] | B41: Input | C41: 1.9438 | D41: 1.8375 | E41: 2.0515 | F41: 1.9884 | G41: 2.1811 | H41: 2.6349 | I41: 14.946336 | J41: 15.239402 | K41: 15.538214 | L41: 15.842884 | M41: 16.153529 | N41: 16.470265 | O41: 16.793211 | P41: 17.12249 | Q41: 10.09146 | R41: 10.289331 | S41: 10.491083 | T41: 10.696791 | U41: 10.906532 | V41: 11.120385 | W41: 11.338432 | X41: 11.560754 | Y41: 11.787435 | Z41: 12.018562 | AA41: 17.385674 | AB41: 17.72657 | AC41: 18.07415 | AD41: 18.428545 | AE41: 18.789889 | AF41: 19.158318 | AG41: 19.533971 | AH41: 19.91699 | AI41: 20.30752 | AJ41: 20.705706
A42: Investment Residential [Mrd Euro] | B42: Input | C42: 5.3217 | D42: 5.663 | E42: 5.7613 | F42: 5.3511 | G42: 6.1815 | H42: 6.3237 | I42: 0.6767609 | J42: 0.69003072 | K42: 0.70356073 | L42: 0.71735604 | M42: 0.73142184 | N42: 0.74576345 | O42: 0.76038626 | P42: 0.7752958 | Q42: 1.1857465 | R42: 1.2089964 | S42: 1.2327023 | T42: 1.2568729 | U42: 1.2815175 | V42: 1.3066452 | W42: 1.3322657 | X42: 1.3583886 | Y42: 1.3850237 | Z42: 1.412181 | AA42: 2.3742551 | AB42: 2.4208091 | AC42: 2.4682759 | AD42: 2.5166735 | AE42: 2.5660201 | AF42: 2.6163342 | AG42: 2.6676348 | AH42: 2.7199414 | AI42: 2.7732736 | AJ42: 2.8276515
A43: Investment Services [Mrd Euro] | B43: Input | C43: 16.9093 | D43: 17.9789 | E43: 19.5213 | F43: 19.3649 | G43: 19.9656 | H43: 20.5271 | I43: 12.390484 | J43: 12.633435 | K43: 12.881149 | L43: 13.133721 | M43: 13.391245 | N43: 13.653818 | O43: 13.92154 | P43: 14.194511 | Q43: 16.991495 | R43: 17.324662 | S43: 17.664361 | T43: 18.010721 | U43: 18.363872 | V43: 18.723948 | W43: 19.091085 | X43: 19.46542 | Y43: 19.847095 | Z43: 20.236253 | AA43: 21.368296 | AB43: 21.787282 | AC43: 22.214483 | AD43: 22.650062 | AE43: 23.09418 | AF43: 23.547008 | AG43: 24.008714 | AH43: 24.479473 | AI43: 24.959462 | AJ43: 25.448864
A44: Investment Agriculture/Forestry/Fishing [Mrd Euro] | B44: Input | C44: 1.1382 | D44: 1.1194 | E44: 1.129 | F44: 1.1885 | G44: 1.2523 | H44: 1.1821 | I44: 1.1407205 | J44: 1.1430155 | K44: 1.1453186 | L44: 1.1476298 | M44: 1.1499491 | N44: 1.1522763 | O44: 1.1546114 | P44: 1.1569545 | Q44: 1.1593054 | R44: 1.1647779 | S44: 1.1670834 | T44: 1.1693979 | U44: 1.1717212 | V44: 1.1740534 | W44: 1.1763943 | X44: 1.178744 | Y44: 1.1811024 | Z44: 1.1834693 | AA44: 1.1858449 | AB44: 1.1882289 | AC44: 1.1906215 | AD44: 1.1930224 | AE44: 1.1954317 | AF44: 1.1978494 | AG44: 1.2002754 | AH44: 1.2027095 | AI44: 1.2051519 | AJ44: 1.2076025
A45: Investment [Mrd Euros] | B45: Computed | C45: =+SUM(Decarbonizatio!C40:C44) -> 33.3662 | D45: =+SUM(Decarbonizatio!D40:D44) -> 35.1534 | E45: =+SUM(Decarbonizatio!E40:E44) -> 37.0236 | F45: =+SUM(Decarbonizatio!F40:F44) -> 36.2046 | G45: =+SUM(Decarbonizatio!G40:G44) -> 39.0835 | H45: =+SUM(Decarbonizatio!H40:H44) -> 40.685 | I45: =+SUM(Decarbonizatio!I40:I44) -> 32.199726 | J45: =+SUM(Decarbonizatio!J40:J44) -> 32.811021 | ... AJ45: =+SUM(Decarbonizatio!AJ40:AJ44) -> 58.344406
A46: Investment for capital [Mrd Euros] | B46: Computed | C46: =+C45-C38 -> 33.3662 | D46: =+D45-D38 -> 35.1534 | E46: =+E45-E38 -> 37.0236 | F46: =+F45-F38 -> 36.2046 | G46: =+G45-G38 -> 39.0835 | H46: =+H45-H38 -> 40.685 | I46: =+I45-I38 -> 32.190011 | J46: =+J45-J38 -> 32.791368 | ... AJ46: =+AJ45-AJ38 -> 58.065419
A48: Depreciation Industry [Mrd Euros] | B48: Computed | C48: 6.8306 | D48: 7.0159 | E48: 7.2788 | F48: 7.507 | G48: 7.657 | H48: 7.9939 | I48: =0.0854053900119604*H55 -> 7.5248554 | J48: =0.0854053900119604*I55 -> 7.1422878 | K48: =0.0854053900119604*J55 -> 6.7974935 | L48: =0.0854053900119604*K55 -> 6.4873464 | M48: =0.0854053900119604*L55 -> 6.2089893 | N48: =0.0854053900119604*M55 -> 5.9598113 | O48: =0.0854053900119604*N55 -> 5.7374263 | P48: =0.0854053900119604*O55 -> 5.5396541 | ... AJ48: =0.0854053900119604*AI55 -> 6.9189575
A49: Depreciation Transport [Mrd Euros] | B49: Computed | C49: 1.9801 | D49: 1.9425 | E49: 1.97 | F49: 2.011 | G49: 2.2206 | H49: 2.2665 | I49: =0.0747889159710027*H56 -> 2.0418122 | J49: =0.0747889159710027*I56 -> 3.0069276 | K49: =0.0747889159710027*J56 -> 3.9217811 | L49: =0.0747889159710027*K56 -> 4.7905615 | M49: =0.0747889159710027*L56 -> 5.6171527 | N49: =0.0747889159710027*M56 -> 6.4051569 | O49: =0.0747889159710027*N56 -> 7.1579154 | P49: =0.0747889159710027*O56 -> 7.8785288 | ... AJ49: =0.0747889159710027*AI56 -> 14.516266
A50: Depreciation Residential [Mrd Euros] | B50: Computed | C50: 9.368 | D50: 9.2889 | E50: 9.2216 | F50: 9.158 | G50: 9.082 | H50: 9.0321 | I50: =0.0386761793725209*H57 -> 8.7241432 | J50: =0.0386761793725209*I57 -> 8.4129012 | K50: =0.0386761793725209*J57 -> 8.1142101 | L50: =0.0386761793725209*K57 -> 7.8275945 | M50: =0.0386761793725209*L57 -> 7.5525976 | N50: =0.0386761793725209*M57 -> 7.2887806 | O50: =0.0386761793725209*N57 -> 7.0357217 | P50: =0.0386761793725209*O57 -> 6.7930157 | ... AJ50: =0.0386761793725209*AI57 -> 4.1703366
A51: Depreciation Services [Mrd Euros] | B51: Computed | C51: 16.7645 | D51: 17.1296 | E51: 17.6437 | F51: 18.4122 | G51: 18.4823 | H51: 19.0888 | I51: =0.0973324743081864*H58 -> 17.682011 | J51: =0.0973324743081864*I58 -> 17.166974 | K51: =0.0973324743081864*J58 -> 16.725713 | L51: =0.0973324743081864*K58 -> 16.351512 | M51: =0.0973324743081864*L58 -> 16.038317 | N51: =0.0973324743081864*M58 -> 15.78067 | O51: =0.0973324743081864*N58 -> 15.573659 | P51: =0.0973324743081864*O58 -> 15.412854 | ... AJ51: =0.0973324743081864*AI58 -> 21.102854
A52: Depreciation Agriculture/Forestry/Fishing [Mrd Euros] | B52: Computed | C52: 1.0005 | D52: 0.9901 | E52: 0.9827 | F52: 0.9994 | G52: 1.0046 | H52: 1.0195 | I52: =0.0980065492623211*H59 -> 1.0826195 | J52: =0.0980065492623211*I59 -> 1.0883138 | K52: =0.0980065492623211*J59 -> 1.0936749 | L52: =0.0980065492623211*K59 -> 1.0987364 | M52: =0.0980065492623211*L59 -> 1.1035282 | N52: =0.0980065492623211*M59 -> 1.1080778 | O52: =0.0980065492623211*N59 -> 1.1124095 | P52: =0.0980065492623211*O59 -> 1.1165456 | ... AJ52: =0.0980065492623211*AI59 -> 1.1806054
A53: Depreciation TOT [Mrd Euro] | B53: Computed | C53: =+SUM(C48:C52) -> 35.9437 | D53: =+SUM(D48:D52) -> 36.367 | E53: =+SUM(E48:E52) -> 37.0968 | F53: =+SUM(F48:F52) -> 38.0876 | G53: =+SUM(G48:G52) -> 38.4465 | H53: =+SUM(H48:H52) -> 39.4008 | I53: =+SUM(I48:I52) -> 37.055441 | J53: =+SUM(J48:J52) -> 36.817404 | ... AJ53: =+SUM(AJ48:AJ52) -> 47.889019
A55: Capital Industry [Mrd Euros] | B55: Computed | C55: 80.6131 | D55: 82.1518 | E55: 83.4335 | F55: 84.2382 | G55: 86.0842 | H55: 88.1075 | I55: =+((H55)+I40-I48) -> 83.628069 | J55: =+((I55)+J40-J48) -> 79.590919 | K55: =+((J55)+K40-K48) -> 75.959449 | L55: =+((K55)+L40-L48) -> 72.700205 | M55: =+((L55)+M40-M48) -> 69.782614 | N55: =+((M55)+N40-N48) -> 67.178738 | O55: =+((N55)+O40-O48) -> 64.86305 | P55: =+((O55)+P40-P48) -> 62.812227 | ... AJ55: =+((AI55)+AJ40-AJ48) -> 82.248749
A56: Capital Transport [Mrd Euros] | B56: Computed | C56: 27.0182 | D56: 26.9132 | E56: 26.9947 | F56: 26.9721 | G56: 26.9326 | H56: 27.301 | I56: =+((H56)+I41-I49) -> 40.205524 | J56: =+((I56)+J41-J49) -> 52.437998 | K56: =+((J56)+K41-K49) -> 64.054431 | L56: =+((K56)+L41-L49) -> 75.106754 | M56: =+((L56)+M41-M49) -> 85.64313 | N56: =+((M56)+N41-N49) -> 95.708239 | O56: =+((N56)+O41-O49) -> 105.34353 | P56: =+((O56)+P41-P49) -> 114.5875 | ... AJ56: =+((AI56)+AJ41-AJ49) -> 200.28592
A57: Capital Residential [Mrd Euros] | B57: Computed | C57: 242.0709 | D57: 238.445 | E57: 234.9847 | F57: 231.1778 | G57: 228.2773 | H57: 225.5689 | I57: =+((H57)+I42-I50) -> 217.52152 | J57: =+((I57)+J42-J50) -> 209.79865 | K57: =+((J57)+K42-K50) -> 202.388 | L57: =+((K57)+L42-L50) -> 195.27776 | M57: =+((L57)+M42-M50) -> 188.45658 | N57: =+((M57)+N42-N50) -> 181.91357 | O57: =+((N57)+O42-O50) -> 175.63823 | P57: =+((O57)+P42-P50) -> 169.62051 | ... AJ57: =+((AI57)+AJ42-AJ50) -> 106.48432
A58: Capital Services [Mrd Euros] | B58: Computed | C58: 175.0649 | D58: 175.9142 | E58: 177.7918 | F58: 178.7445 | G58: 180.2278 | H58: 181.6661 | I58: =+((H58)+I43-I51) -> 176.37457 | J58: =+((I58)+J43-J51) -> 171.84103 | K58: =+((J58)+K43-K51) -> 167.99647 | L58: =+((K58)+L43-L51) -> 164.77868 | M58: =+((L58)+M43-M51) -> 162.13161 | N58: =+((M58)+N43-N51) -> 160.00475 | O58: =+((N58)+O43-O51) -> 158.35264 | P58: =+((O58)+P43-P51) -> 157.13429 | ... AJ58: =+((AI58)+AJ43-AJ51) -> 221.15807
A59: Capital Agriculture/Forestry/Fishing [Mrd Euros] | B59: Computed | C59: 10.1714 | D59: 10.3007 | E59: 10.447 | F59: 10.6361 | G59: 10.8838 | H59: 11.0464 | I59: =+((H59)+I44-I52) -> 11.104501 | J59: =+((I59)+J44-J52) -> 11.159203 | K59: =+((J59)+K44-K52) -> 11.210846 | L59: =+((K59)+L44-L52) -> 11.25974 | M59: =+((L59)+M44-M52) -> 11.306161 | N59: =+((M59)+N44-N52) -> 11.350359 | O59: =+((N59)+O44-O52) -> 11.392561 | P59: =+((O59)+P44-P52) -> 11.43297 | ... AJ59: =+((AI59)+AJ44-AJ52) -> 12.073186
A60: Capital TOT [Mrd Euros] | B60: Computed | C60: =+SUM(C55:C59) -> 534.9385 | D60: =+SUM(D55:D59) -> 533.7249 | E60: =+SUM(E55:E59) -> 533.6517 | F60: =+SUM(F55:F59) -> 531.7687 | G60: =+SUM(G55:G59) -> 532.4057 | H60: =+SUM(H55:H59) -> 533.6899 | I60: =+((H60)+I46-I53) -> 528.82447 | J60: =+((I60)+J46-J53) -> 524.79843 | K60: =+((J60)+K46-K53) -> 520.99049 | L60: =+((K60)+L46-L53) -> 517.09757 | M60: =+((L60)+M46-M53) -> 513.9833 | N60: =+((M60)+N46-N53) -> 511.59368 | O60: =+((N60)+O46-O53) -> 509.8792 | P60: =+((O60)+P46-P53) -> 508.7976 | ... AJ60: =+((AI60)+AJ46-AJ53) -> 605.64922
A62: Average Hours Worked by an engaged individual (H) gives | B62: Input | C62: 1873.6191 | D62: 1867.852 | E62: 1864.5884 | F62: 1851.2145 | G62: 1837.8407 | H62: 1824.4669 | I62: 1811.0931 | J62: 1797.7193 | K62: 1784.3455 | L62: 1770.9716 | M62: 1757.5978 | N62: 1744.224 | O62: 1730.8502 | P62: 1717.4764 | Q62: 1704.1025 | R62: 1690.7287 | S62: 1677.3549 | T62: 1663.9811 | U62: 1650.6073 | V62: 1637.2335 | W62: 1623.8596 | X62: 1610.4858 | Y62: 1597.112 | Z62: 1583.7382 | AA62: 1570.3644 | AB62: 1556.9905 | AC62: 1543.6167 | AD62: 1530.2429 | AE62: 1516.8691 | AF62: 1503.4953 | AG62: 1490.1215 | AH62: 1476.7476 | AI62: 1463.3738 | AJ62: 1450
A63: Unemployment rate (u) | B63: Input | C63: 0.092 | D63: 0.072 | E63: 0.066 | F63: 0.07 | G63: 0.067 | H63: 0.061 | I63: 0.065 | J63: 0.064 | K63: 0.06346154 | L63: 0.06292308 | M63: 0.06238462 | N63: 0.06184615 | O63: 0.06130769 | P63: 0.06076923 | Q63: 0.06023077 | R63: 0.05969231 | S63: 0.05915385 | T63: 0.05861538 | U63: 0.05807692 | V63: 0.05753846 | W63: 0.057 | X63: 0.05646154 | Y63: 0.05592308 | Z63: 0.05538462 | AA63: 0.05484615 | AB63: 0.05430769 | AC63: 0.05376923 | AD63: 0.05323077 | AE63: 0.05269231 | AF63: 0.05215385 | AG63: 0.05161538 | AH63: 0.05107692 | AI63: 0.05053846 | AJ63: 0.05
A64: Working age population | B64: Input | C64: 6657888 | D64: 6624826 | E64: 6607282.5 | F64: 6589739 | G64: 6572195.5 | H64: 6554652 | I64: 6537108.5 | J64: 6519565 | K64: 6502021.5 | L64: 6484478.1 | M64: 6466934.6 | N64: 6449391.1 | O64: 6431847.6 | P64: 6414304.1 | Q64: 6396760.6 | R64: 6379217.1 | S64: 6361673.6 | T64: 6344130.1 | U64: 6326586.6 | V64: 6309043.1 | W64: 6291499.7 | X64: 6273956.2 | Y64: 6256412.7 | Z64: 6238869.2 | AA64: 6221325.7 | AB64: 6203782.2 | AC64: 6186238.7 | AD64: 6168695.2 | AE64: 6151151.7 | AF64: 6133608.2 | AG64: 6116064.7 | AH64: 6098521.2 | AI64: 6080977.7 | AJ64: 6063434.2
A65: Labour Force Participation Rate | B65: Input | C65: 0.75 | D65: 0.757 | E65: 0.76 | F65: 0.749 | G65: 0.76 | H65: 0.774 | I65: 0.788 | J65: 0.792 | K65: 0.79615385 | L65: 0.80030769 | M65: 0.80446154 | N65: 0.80861538 | O65: 0.81276923 | P65: 0.81692308 | Q65: 0.82107692 | R65: 0.82523077 | S65: 0.82938462 | T65: 0.83353846 | U65: 0.83769231 | V65: 0.84184615 | W65: 0.846 | X65: 0.85015385 | Y65: 0.85430769 | Z65: 0.85846154 | AA65: 0.86261539 | AB65: 0.86676923 | AC65: 0.87092308 | AD65: 0.87507692 | AE65: 0.87923077 | AF65: 0.88338461 | AG65: 0.88753846 | AH65: 0.89169231 | AI65: 0.89584615 | AJ65: 0.9
A66: Labour [Hours worked by engaged people] | B66: Computed | C66: =C62*(1-C63)*C64*C65 -> 8.4950296e+09 | D66: =D62*(1-D63)*D64*D65 -> 8.6928222e+09 | E66: =E62*(1-E63)*E64*E65 -> 8.7451309e+09 | F66: =F62*(1-F63)*F64*F65 -> 8.4974719e+09 | G66: =G62*(1-G63)*G64*G65 -> 8.5647281e+09 | H66: =H62*(1-H63)*H64*H65 -> 8.691449e+09 | I66: =I62*(1-I63)*I64*I65 -> 8.7229684e+09 | J66: =J62*(1-J63)*J64*J65 -> 8.6884344e+09 | ... AJ66: =AJ62*(1-AJ63)*AJ64*AJ65 -> 7.5171426e+09
A68: TFP | B68: Computed | C68: - | D68: =+((D491/0.14)^1.93)*0.00000102 + 0.00000039 -> 3.1326107e-06 | E68: =+((E491/0.14)^1.93)*0.00000102 + 0.00000039 -> 3.0789659e-06 | F68: =+((F491/0.14)^1.93)*0.00000102 + 0.00000039 -> 3.1379241e-06 | G68: =+((G491/0.14)^1.93)*0.00000102 + 0.00000039 -> 3.0652364e-06 | H68: =+((H491/0.14)^1.93)*0.00000102 + 0.00000039 -> 3.0557922e-06 | I68: =+((I491/0.14)^1.93)*0.00000102 + 0.00000039 -> 3.3765473e-06 | J68: =+((J491/0.14)^1.93)*0.00000102 + 0.00000039 -> 3.5554139e-06 | K68: =+((K491/0.14)^1.93)*0.00000102 + 0.00000039 -> 3.7278689e-06 | ... AJ68: =+((AJ491/0.14)^1.93)*0.00000102 + 0.00000039 -> 8.3665685e-06
A70: GDP [Mrd Euros] | B70: Computed | C70: =189.1 -> 189.1 | D70: =194.6 -> 194.6 | E70: =200 -> 200 | F70: =183.6 -> 183.6 | G70: =193.8 -> 193.8 | H70: =207.3 -> 207.3 | I70: =+((I68*((I60)^0.3)*(I66^0.7))) -> 201.34058 | J70: =+((J68*((J60)^0.3)*(J66^0.7))) -> 210.9342 | K70: =+((K68*((K60)^0.3)*(K66^0.7))) -> 220.01107 | L70: =+((L68*((L60)^0.3)*(L66^0.7))) -> 228.54474 | M70: =+((M68*((M60)^0.3)*(M66^0.7))) -> 236.60582 | N70: =+((N68*((N60)^0.3)*(N66^0.7))) -> 244.04144 | O70: =+((O68*((O60)^0.3)*(O66^0.7))) -> 250.84289 | P70: =+((P68*((P60)^0.3)*(P66^0.7))) -> 257.00434 | ... AJ70: =+((AJ68*((AJ60)^0.3)*(AJ66^0.7))) -> 468.22077
A71: GDP annual growth rate [%] | B71: Computed | D71: =+((D70-C70)/C70)*100 -> 2.908514 | E71: =+((E70-D70)/D70)*100 -> 2.7749229 | F71: =+((F70-E70)/E70)*100 -> -8.2 | G71: =+((G70-F70)/F70)*100 -> 5.5555556 | H71: =+((H70-G70)/G70)*100 -> 6.9659443 | I71: =+((I70-H70)/H70)*100 -> -2.8747808 | J71: =+((J70-I70)/I70)*100 -> 4.7648714 | K71: =+((K70-J70)/J70)*100 -> 4.3031784 | ... S71: =+((S70-R70)/R70)*100 -> 6.409605 | U71: =+((U70-T70)/T70)*100 -> 5.051096 | V71: =+((V70-U70)/U70)*100 -> 4.5004441 | W71: =+((W70-V70)/V70)*100 -> 3.9651913 | X71: =+((X70-W70)/W70)*100 -> 3.4780699 | Y71: =+((Y70-X70)/X70)*100 -> 3.0275836 | Z71: =+((Z70-Y70)/Y70)*100 -> 2.6103506 | AA71: =+((AA70-Z70)/Z70)*100 -> 2.090806 | AB71: =+((AB70-AA70)/AA70)*100 -> 1.857222 | ... AJ71: =+((AJ70-AI70)/AI70)*100 -> 0.28288444
A73: Total Useful exergy [TJ] | C73: 184372.38 | D73: 184124.9 | E73: 183477.17 | F73: 170891.44 | G73: 174119.51 | H73: 177140.85 | I73: =+I70*10^3 -> 201340.58 | J73: =+J70*10^3 -> 210934.2 | K73: =+K70*10^3 -> 220011.07 | L73: =+L70*10^3 -> 228544.74 | M73: =+M70*10^3 -> 236605.82 | N73: =+N70*10^3 -> 244041.44 | O73: =+O70*10^3 -> 250842.89 | P73: =+P70*10^3 -> 257004.34 | ... AJ73: =+AJ70*10^3 -> 468220.77
A74: Total Final exergy [TJ] | C74: 774063.77 | D74: 755634.98 | E74: 778696.11 | F74: 724009.39 | G74: 743241.04 | H74: 752302.28 | I74: =+I73/I491 -> 824247.36 | J74: =+J73/J491 -> 837885.34 | K74: =+K73/K491 -> 850246.69 | L74: =+L73/L491 -> 861365.67 | M74: =+M73/M491 -> 871660.25 | N74: =+N73/N491 -> 880931.71 | O74: =+O73/O491 -> 889209.15 | P74: =+P73/P491 -> 896520.91 | ... AJ74: =+AJ73/AJ491 -> 1152169.7
A76: Share final exergy industry [-] | C76: =Aggregate_Efficiency_Decarboniz!C5 -> 0.27142931 | D76: =Aggregate_Efficiency_Decarboniz!D5 -> 0.27119604 | E76: =Aggregate_Efficiency_Decarboniz!E5 -> 0.2732505 | F76: =Aggregate_Efficiency_Decarboniz!F5 -> 0.28555072 | G76: =Aggregate_Efficiency_Decarboniz!G5 -> 0.28462773 | H76: =Aggregate_Efficiency_Decarboniz!H5 -> 0.27572585 | I76: =Aggregate_Efficiency_Decarboniz!I5 -> 0.27588512 | J76: =Aggregate_Efficiency_Decarboniz!J5 -> 0.27604439 | ... AJ76: =Aggregate_Efficiency_Decarboniz!AJ5 -> 0.385
A77: Share final exergy transport [-] | C77: =Aggregate_Efficiency_Decarboniz!C6 -> 0.3546432 | D77: =Aggregate_Efficiency_Decarboniz!D6 -> 0.35679786 | E77: =Aggregate_Efficiency_Decarboniz!E6 -> 0.36315882 | F77: =Aggregate_Efficiency_Decarboniz!F6 -> 0.32899597 | G77: =Aggregate_Efficiency_Decarboniz!G6 -> 0.34997126 | H77: =Aggregate_Efficiency_Decarboniz!H6 -> 0.36009084 | I77: =Aggregate_Efficiency_Decarboniz!I6 -> 0.35382948 | J77: =Aggregate_Efficiency_Decarboniz!J6 -> 0.34756813 | ... AJ77: =Aggregate_Efficiency_Decarboniz!AJ6 -> 0.19
A78: Share final exergy services [-] | C78: =Aggregate_Efficiency_Decarboniz!C7 -> 0.11098227 | D78: =Aggregate_Efficiency_Decarboniz!D7 -> 0.11418082 | E78: =Aggregate_Efficiency_Decarboniz!E7 -> 0.11117733 | F78: =Aggregate_Efficiency_Decarboniz!F7 -> 0.10630522 | G78: =Aggregate_Efficiency_Decarboniz!G7 -> 0.10424487 | H78: =Aggregate_Efficiency_Decarboniz!H7 -> 0.10934643 | I78: =Aggregate_Efficiency_Decarboniz!I7 -> 0.11442812 | J78: =Aggregate_Efficiency_Decarboniz!J7 -> 0.11950982 | ... AJ78: =Aggregate_Efficiency_Decarboniz!AJ7 -> 0.17
A79: Share final exergy residencial [-] | C79: =Aggregate_Efficiency_Decarboniz!C8 -> 0.15680348 | D79: =Aggregate_Efficiency_Decarboniz!D8 -> 0.15992742 | E79: =Aggregate_Efficiency_Decarboniz!E8 -> 0.15925696 | F79: =Aggregate_Efficiency_Decarboniz!F8 -> 0.17964943 | G79: =Aggregate_Efficiency_Decarboniz!G8 -> 0.17499831 | H79: =Aggregate_Efficiency_Decarboniz!H8 -> 0.16410964 | I79: =Aggregate_Efficiency_Decarboniz!I8 -> 0.16609594 | J79: =Aggregate_Efficiency_Decarboniz!J8 -> 0.16808223 | ... AJ79: =Aggregate_Efficiency_Decarboniz!AJ8 -> 0.18
A80: Share Final Exergy Agriculture/forestry/Fishing [-] | C80: =Aggregate_Efficiency_Decarboniz!C9 -> 0.027798035 | D80: =Aggregate_Efficiency_Decarboniz!D9 -> 0.028064646 | E80: =Aggregate_Efficiency_Decarboniz!E9 -> 0.028618365 | F80: =Aggregate_Efficiency_Decarboniz!F9 -> 0.032768238 | G80: =Aggregate_Efficiency_Decarboniz!G9 -> 0.03372055 | H80: =Aggregate_Efficiency_Decarboniz!H9 -> 0.029928558 | I80: =Aggregate_Efficiency_Decarboniz!I9 -> 0.029937488 | J80: =Aggregate_Efficiency_Decarboniz!J9 -> 0.029946419 | ... AJ80: =Aggregate_Efficiency_Decarboniz!AJ9 -> 0.03
A81: Share Final Exergy Energy industry own use [-] | C81: =Aggregate_Efficiency_Decarboniz!C10 -> 0.078343711 | D81: =Aggregate_Efficiency_Decarboniz!D10 -> 0.069833206 | E81: =Aggregate_Efficiency_Decarboniz!E10 -> 0.06453802 | F81: =Aggregate_Efficiency_Decarboniz!F10 -> 0.066730424 | G81: =Aggregate_Efficiency_Decarboniz!G10 -> 0.05243729 | H81: =Aggregate_Efficiency_Decarboniz!H10 -> 0.060798684 | I81: =Aggregate_Efficiency_Decarboniz!I10 -> 0.059823848 | J81: =Aggregate_Efficiency_Decarboniz!J10 -> 0.058849013 | ... AJ81: =Aggregate_Efficiency_Decarboniz!AJ10 -> 0.045
A83: Final exergy Industry [TJ] | B83: Computed | C83: =+C76*C$74 -> 210103.59 | D83: =+D76*D$74 -> 204925.21 | E83: =+E76*E$74 -> 212779.1 | F83: =+F76*F$74 -> 206741.4 | G83: =+G76*G$74 -> 211547.01 | H83: =+H76*H$74 -> 207429.19 | I83: =+I76*I$74 -> 227397.58 | J83: =+J76*J$74 -> 231293.55 | ... AJ83: =+AJ76*AJ$74 -> 443585.34
A84: Final exergy Transport [TJ] | B84: Computed | C84: =+C77*C$74 -> 274516.45 | D84: =+D77*D$74 -> 269608.95 | E84: =+E77*E$74 -> 282790.36 | F84: =+F77*F$74 -> 238196.17 | G84: =+G77*G$74 -> 260113 | H84: =+H77*H$74 -> 270897.16 | I84: =+I77*I$74 -> 291643.02 | J84: =+J77*J$74 -> 291222.24 | ... AJ84: =+AJ77*AJ$74 -> 218912.25
A85: Final exergy Services [TJ] | B85: Computed | C85: =+C78*C$74 -> 85907.357 | D85: =+D78*D$74 -> 86279.024 | E85: =+E78*E$74 -> 86573.356 | F85: =+F78*F$74 -> 76965.977 | G85: =+G78*G$74 -> 77479.063 | H85: =+H78*H$74 -> 82261.565 | I85: =+I78*I$74 -> 94317.077 | J85: =+J78*J$74 -> 100135.53 | ... AJ85: =+AJ78*AJ$74 -> 195868.85
A86: Final exergy Residencial [TJ] | B86: Computed | C86: =+C79*C$74 -> 121375.89 | D86: =+D79*D$74 -> 120846.75 | E86: =+E79*E$74 -> 124012.78 | F86: =+F79*F$74 -> 130067.87 | G86: =+G79*G$74 -> 130065.92 | H86: =+H79*H$74 -> 123460.06 | I86: =+I79*I$74 -> 136904.14 | J86: =+J79*J$74 -> 140833.64 | ... AJ86: =+AJ79*AJ$74 -> 207390.55
A87: Final Exergy Agriculture/Forestry/fishing [TJ] | B87: Computed | C87: =+C80*C$74 -> 21517.452 | D87: =+D80*D$74 -> 21206.628 | E87: =+E80*E$74 -> 22285.01 | F87: =+F80*F$74 -> 23724.512 | G87: =+G80*G$74 -> 25062.497 | H87: =+H80*H$74 -> 22515.322 | I87: =+I80*I$74 -> 24675.896 | J87: =+J80*J$74 -> 25091.665 | ... AJ87: =+AJ80*AJ$74 -> 34565.092
A88: Final Exergy Energy industry own use [TJ] | B88: Computed | C88: =+C81*C$74 -> 60643.029 | D88: =+D81*D$74 -> 52768.413 | E88: =+E81*E$74 -> 50255.505 | F88: =+F81*F$74 -> 48313.454 | G88: =+G81*G$74 -> 38973.546 | H88: =+H81*H$74 -> 45738.988 | I88: =+I81*I$74 -> 49309.649 | J88: =+J81*J$74 -> 49308.725 | ... AJ88: =+AJ81*AJ$74 -> 51847.637
A90: Share final exergy industry electricity | C90: =Aggregate_Efficiency_Decarboniz!C19 -> 0.2970747 | D90: =Aggregate_Efficiency_Decarboniz!D19 -> 0.30075756 | E90: =Aggregate_Efficiency_Decarboniz!E19 -> 0.30235708 | F90: =Aggregate_Efficiency_Decarboniz!F19 -> 0.30163627 | G90: =Aggregate_Efficiency_Decarboniz!G19 -> 0.30591526 | H90: =Aggregate_Efficiency_Decarboniz!H19 -> 0.31318182 | I90: =Aggregate_Efficiency_Decarboniz!I19 -> 0.31407823 | J90: =Aggregate_Efficiency_Decarboniz!J19 -> 0.31497465 | ... AJ90: =Aggregate_Efficiency_Decarboniz!AJ19 -> 0.553031
A91: Share final exergy transport electricity | C91: =Aggregate_Efficiency_Decarboniz!C20 -> 0.0068374586 | D91: =Aggregate_Efficiency_Decarboniz!D20 -> 0.0068392983 | E91: =Aggregate_Efficiency_Decarboniz!E20 -> 0.0067376336 | F91: =Aggregate_Efficiency_Decarboniz!F20 -> 0.0070045484 | G91: =Aggregate_Efficiency_Decarboniz!G20 -> 0.0070586514 | H91: =Aggregate_Efficiency_Decarboniz!H20 -> 0.0070199832 | I91: =Aggregate_Efficiency_Decarboniz!I20 -> 0.020547839 | J91: =Aggregate_Efficiency_Decarboniz!J20 -> 0.034075694 | ... AJ91: =Aggregate_Efficiency_Decarboniz!AJ20 -> 0.68843263
A92: Share final exergy services electricity | C92: =Aggregate_Efficiency_Decarboniz!C21 -> 0.73677033 | D92: =Aggregate_Efficiency_Decarboniz!D21 -> 0.72971057 | E92: =Aggregate_Efficiency_Decarboniz!E21 -> 0.73192341 | F92: =Aggregate_Efficiency_Decarboniz!F21 -> 0.7583611 | G92: =Aggregate_Efficiency_Decarboniz!G21 -> 0.73914204 | H92: =Aggregate_Efficiency_Decarboniz!H21 -> 0.75301205 | I92: =Aggregate_Efficiency_Decarboniz!I21 -> 0.75138554 | J92: =Aggregate_Efficiency_Decarboniz!J21 -> 0.74975904 | ... AJ92: =Aggregate_Efficiency_Decarboniz!AJ21 -> 0.88
A93: Share final exergy residencial electricity | C93: =Aggregate_Efficiency_Decarboniz!C22 -> 0.40105887 | D93: =Aggregate_Efficiency_Decarboniz!D22 -> 0.41096146 | E93: =Aggregate_Efficiency_Decarboniz!E22 -> 0.41088932 | F93: =Aggregate_Efficiency_Decarboniz!F22 -> 0.40750368 | G93: =Aggregate_Efficiency_Decarboniz!G22 -> 0.42720606 | H93: =Aggregate_Efficiency_Decarboniz!H22 -> 0.43001357 | I93: =Aggregate_Efficiency_Decarboniz!I22 -> 0.43126188 | J93: =Aggregate_Efficiency_Decarboniz!J22 -> 0.43251018 | ... AJ93: =Aggregate_Efficiency_Decarboniz!AJ22 -> 0.83
A94: Share final exergy Agriculture/forestry/Fishing electricity | C94: =Aggregate_Efficiency_Decarboniz!C23 -> 0.17678412 | D94: =Aggregate_Efficiency_Decarboniz!D23 -> 0.18850159 | E94: =Aggregate_Efficiency_Decarboniz!E23 -> 0.16560611 | F94: =Aggregate_Efficiency_Decarboniz!F23 -> 0.16584001 | G94: =Aggregate_Efficiency_Decarboniz!G23 -> 0.17929811 | H94: =Aggregate_Efficiency_Decarboniz!H23 -> 0.16275005 | I94: =Aggregate_Efficiency_Decarboniz!I23 -> 0.18979469 | J94: =Aggregate_Efficiency_Decarboniz!J23 -> 0.21683933 | ... AJ94: =Aggregate_Efficiency_Decarboniz!AJ23 -> 0.92
A95: Share final exergy Energy industry own electricity | C95: =Aggregate_Efficiency_Decarboniz!C24 -> 0.20857445 | D95: =Aggregate_Efficiency_Decarboniz!D24 -> 0.19412629 | E95: =Aggregate_Efficiency_Decarboniz!E24 -> 0.17649312 | F95: =Aggregate_Efficiency_Decarboniz!F24 -> 0.17373555 | G95: =Aggregate_Efficiency_Decarboniz!G24 -> 0.18464616 | H95: =Aggregate_Efficiency_Decarboniz!H24 -> 0.17476388 | I95: =Aggregate_Efficiency_Decarboniz!I24 -> 0.20066517 | J95: =Aggregate_Efficiency_Decarboniz!J24 -> 0.22656646 | ... AJ95: =Aggregate_Efficiency_Decarboniz!AJ24 -> 0.9
A96: Share final exergy industry coal/coke | C96: =Aggregate_Efficiency_Decarboniz!C25 -> 0.069253404 | D96: =Aggregate_Efficiency_Decarboniz!D25 -> 0.061170092 | E96: =Aggregate_Efficiency_Decarboniz!E25 -> 0.059562702 | F96: =Aggregate_Efficiency_Decarboniz!F25 -> 0.064743037 | G96: =Aggregate_Efficiency_Decarboniz!G25 -> 0.054408395 | H96: =Aggregate_Efficiency_Decarboniz!H25 -> 0.06007097 | I96: =Aggregate_Efficiency_Decarboniz!I25 -> 0.052788926 | J96: =Aggregate_Efficiency_Decarboniz!J25 -> 0.045506881 | ... AJ96: =Aggregate_Efficiency_Decarboniz!AJ25 -> 0.0020360944
A97: Share final exergy industry oil | C97: =Aggregate_Efficiency_Decarboniz!C26 -> 0.078378662 | D97: =Aggregate_Efficiency_Decarboniz!D26 -> 0.077637821 | E97: =Aggregate_Efficiency_Decarboniz!E26 -> 0.069863979 | F97: =Aggregate_Efficiency_Decarboniz!F26 -> 0.070795621 | G97: =Aggregate_Efficiency_Decarboniz!G26 -> 0.069265914 | H97: =Aggregate_Efficiency_Decarboniz!H26 -> 0.082289434 | I97: =Aggregate_Efficiency_Decarboniz!I26 -> 0.072199429 | J97: =Aggregate_Efficiency_Decarboniz!J26 -> 0.062109425 | ... AJ97: =Aggregate_Efficiency_Decarboniz!AJ26 -> 0.00092549745
A98: Share final exergy industry natural gas | C98: =Aggregate_Efficiency_Decarboniz!C27 -> 0.27024948 | D98: =Aggregate_Efficiency_Decarboniz!D27 -> 0.2755297 | E98: =Aggregate_Efficiency_Decarboniz!E27 -> 0.27458465 | F98: =Aggregate_Efficiency_Decarboniz!F27 -> 0.2640436 | G98: =Aggregate_Efficiency_Decarboniz!G27 -> 0.29137166 | H98: =Aggregate_Efficiency_Decarboniz!H27 -> 0.25694602 | I98: =Aggregate_Efficiency_Decarboniz!I27 -> 0.26313699 | J98: =Aggregate_Efficiency_Decarboniz!J27 -> 0.26932796 | ... AJ98: =Aggregate_Efficiency_Decarboniz!AJ27 -> 0.12457196
A99: Share final exergy industry waste/c. renewables | C99: =Aggregate_Efficiency_Decarboniz!C28 -> 0.26201817 | D99: =Aggregate_Efficiency_Decarboniz!D28 -> 0.25876213 | E99: =Aggregate_Efficiency_Decarboniz!E28 -> 0.26551584 | F99: =Aggregate_Efficiency_Decarboniz!F28 -> 0.27237961 | G99: =Aggregate_Efficiency_Decarboniz!G28 -> 0.25652296 | H99: =Aggregate_Efficiency_Decarboniz!H28 -> 0.27022414 | I99: =Aggregate_Efficiency_Decarboniz!I28 -> 0.25239144 | J99: =Aggregate_Efficiency_Decarboniz!J28 -> 0.23455874 | ... AJ99: =Aggregate_Efficiency_Decarboniz!AJ28 -> 0.097362332
A100: Share final exergy industry Renewables (Solar) | C100: =Aggregate_Efficiency_Decarboniz!C29 -> 0 | D100: =Aggregate_Efficiency_Decarboniz!D29 -> 0 | E100: =Aggregate_Efficiency_Decarboniz!E29 -> 0 | F100: =Aggregate_Efficiency_Decarboniz!F29 -> 0 | G100: =Aggregate_Efficiency_Decarboniz!G29 -> 0 | H100: =Aggregate_Efficiency_Decarboniz!H29 -> 0 | I100: =Aggregate_Efficiency_Decarboniz!I29 -> 0.0008521334 | J100: =Aggregate_Efficiency_Decarboniz!J29 -> 0.0017042668 | ... AJ100: =Aggregate_Efficiency_Decarboniz!AJ29 -> 0.027487274
A101: Share final exergy industry heat | C101: =Aggregate_Efficiency_Decarboniz!C30 -> 0.023025582 | D101: =Aggregate_Efficiency_Decarboniz!D30 -> 0.026142703 | E101: =Aggregate_Efficiency_Decarboniz!E30 -> 0.028115736 | F101: =Aggregate_Efficiency_Decarboniz!F30 -> 0.026401859 | G101: =Aggregate_Efficiency_Decarboniz!G30 -> 0.022515809 | H101: =Aggregate_Efficiency_Decarboniz!H30 -> 0.017287611 | I101: =Aggregate_Efficiency_Decarboniz!I30 -> 0.044552849 | J101: =Aggregate_Efficiency_Decarboniz!J30 -> 0.071818087 | ... AJ101: =Aggregate_Efficiency_Decarboniz!AJ30 -> 0.19458584
... A129: Share Final Exergy Energy industry own use Heat | C129: =Aggregate_Efficiency_Decarboniz!C58 -> 0.11153732 | D129: =Aggregate_Efficiency_Decarboniz!D58 -> 0.12514663 | E129: =Aggregate_Efficiency_Decarboniz!E58 -> 0.13516367 | F129: =Aggregate_Efficiency_Decarboniz!F58 -> 0.14874172 | G129: =Aggregate_Efficiency_Decarboniz!G58 -> 0.13776063 | H129: =Aggregate_Efficiency_Decarboniz!H58 -> 0.069597049 | I129: =Aggregate_Efficiency_Decarboniz!I58 -> 0.069254297 | J129: =Aggregate_Efficiency_Decarboniz!J58 -> 0.068911545 | ... AJ129: =Aggregate_Efficiency_Decarboniz!AJ58 -> 0.06
A131: Final exergy industry electricity [TJ] | B131: Computed | C131: =+C90*C83 -> 62416.462 | D131: =+D90*D83 -> 61632.807 | E131: =+E90*E83 -> 64335.268 | F131: =+F90*F83 -> 62360.707 | G131: =+G90*G83 -> 64715.458 | H131: =+H90*H83 -> 64963.051 | I131: =+I90*I83 -> 71420.631 | J131: =+J90*J83 -> 72851.603 | ... AJ131: =+AJ90*AJ83 -> 245316.45
A132: Final exergy transport electricity [TJ] | B132: Computed | C132: =+C91*C84 -> 1876.9949 | D132: =+D91*D84 -> 1843.936 | E132: =+E91*E84 -> 1905.3378 | F132: =+F91*F84 -> 1668.4566 | G132: =+G91*G84 -> 1836.047 | H132: =+H91*H84 -> 1901.6935 | I132: =+I91*I84 -> 5992.6336 | J132: =+J91*J84 -> 9923.5999 | ... AJ132: =+AJ91*AJ84 -> 150706.33
A133: Final exergy services electricity [TJ] | B133: Computed | C133: =+C92*C85 -> 63293.991 | D133: =+D92*D85 -> 62958.716 | E133: =+E92*E85 -> 63365.066 | F133: =+F92*F85 -> 58368.003 | G133: =+G92*G85 -> 57268.032 | H133: =+H92*H85 -> 61943.949 | I133: =+I92*I85 -> 70868.488 | J133: =+J92*J85 -> 75077.515 | ... AJ133: =+AJ92*AJ85 -> 172364.59
A134: Final exergy residencial electricity [TJ] | B134: Computed | C134: =+C93*C86 -> 48678.877 | D134: =+D93*D86 -> 49663.359 | E134: =+E93*E86 -> 50955.526 | F134: =+F93*F86 -> 53003.138 | G134: =+G93*G86 -> 55564.951 | H134: =+H93*H86 -> 53089.5 | I134: =+I93*I86 -> 59041.535 | J134: =+J93*J86 -> 60911.981 | ... AJ134: =+AJ93*AJ86 -> 172134.16
A135: Final Exergy Agriculture/Forestry/fishing electricity [TJ] | B135: Computed | C135: =+C94*C87 -> 3803.9437 | D135: =+D94*D87 -> 3997.483 | E135: =+E94*E87 -> 3690.5337 | F135: =+F94*F87 -> 3934.4732 | G135: =+G94*G87 -> 4493.6582 | H135: =+H94*H87 -> 3664.3698 | I135: =+I94*I87 -> 4683.354 | J135: =+J94*J87 -> 5440.8599 | ... AJ135: =+AJ94*AJ87 -> 31799.884
A136: Final Exergy Energy industry own use electricity [TJ] | B136: Computed | C136: =+C95*C88 -> 12648.586 | D136: =+D95*D88 -> 10243.736 | E136: =+E95*E88 -> 8869.7511 | F136: =+F95*F88 -> 8393.7643 | G136: =+G95*G88 -> 7196.3154 | H136: =+H95*H88 -> 7993.5231 | I136: =+I95*I88 -> 9894.7291 | J136: =+J95*J88 -> 11171.703 | ... AJ136: =+AJ95*AJ88 -> 46662.874
A137: Final exergy industry coal/coke [TJ] | B137: Computed | C137: =+C96*C$83 -> 14550.389 | D137: =+D96*D$83 -> 12535.294 | E137: =+E96*E$83 -> 12673.698 | F137: =+F96*F$83 -> 13385.066 | G137: =+G96*G$83 -> 11509.933 | H137: =+H96*H$83 -> 12460.473 | I137: =+I96*I$83 -> 12004.074 | J137: =+J96*J$83 -> 10525.448 | ... AJ137: =+AJ96*AJ$83 -> 903.18163
A138: Final exergy industry oil [TJ] | B138: Computed | C138: =+C97*C$83 -> 16467.639 | D138: =+D97*D$83 -> 15909.947 | E138: =+E97*E$83 -> 14865.595 | F138: =+F97*F$83 -> 14636.386 | G138: =+G97*G$83 -> 14652.997 | H138: =+H97*H$83 -> 17069.23 | I138: =+I97*I$83 -> 16417.976 | J138: =+J97*J$83 -> 14365.509 | ... AJ138: =+AJ97*AJ$83 -> 410.5371
A139: Final exergy industry natural gas [TJ] | B139: Computed | C139: =+C98*C$83 -> 56780.386 | D139: =+D98*D$83 -> 56462.984 | E139: =+E98*E$83 -> 58425.875 | F139: =+F98*F$83 -> 54588.744 | G139: =+G98*G$83 -> 61638.804 | H139: =+H98*H$83 -> 53298.105 | I139: =+I98*I$83 -> 59836.715 | J139: =+J98*J$83 -> 62293.819 | ... AJ139: =+AJ98*AJ$83 -> 55258.294
A140: Final exergy industry c. renewables/waste [TJ] | B140: Computed | C140: =+C99*C$83 -> 55050.96 | D140: =+D99*D$83 -> 53026.884 | E140: =+E99*E$83 -> 56496.222 | F140: =+F99*F$83 -> 56312.143 | G140: =+G99*G$83 -> 54266.665 | H140: =+H99*H$83 -> 56052.374 | I140: =+I99*I$83 -> 57393.203 | J140: =+J99*J$83 -> 54251.922 | ... AJ140: =+AJ99*AJ$83 -> 43188.503
A141: Final exergy industry renewables [TJ] | B141: Computed | C141: =+C100*C$83 -> 0 | D141: =+D100*D$83 -> 0 | E141: =+E100*E$83 -> 0 | F141: =+F100*F$83 -> 0 | G141: =+G100*G$83 -> 0 | H141: =+H100*H$83 -> 0 | I141: =+I100*I$83 -> 193.77308 | J141: =+J100*J$83 -> 394.18591 | ... AJ141: =+AJ100*AJ$83 -> 12192.952
A142: Final exergy industry heat [TJ] | B142: Computed | C142: =+C101*C$83 -> 4837.7575 | D142: =+D101*D$83 -> 5357.2991 | E142: =+E101*E$83 -> 5982.441 | F142: =+F101*F$83 -> 5458.3575 | G142: =+G101*G$83 -> 4763.1521 | H142: =+H101*H$83 -> 3585.9551 | I142: =+I101*I$83 -> 10131.21 | J142: =+J101*J$83 -> 16611.06 | ... AJ142: =+AJ101*AJ$83 -> 86315.426
...

Sheet Charts
A2: BAU Scenario
A3: Year | B3: =BAU!D2 -> 2018 | C3: =BAU!E2 -> 2019 | D3: =BAU!F2 -> 2020 | E3: =BAU!G2 -> 2021 | F3: =BAU!H2 -> 2022 | G3: =BAU!I2 -> 2023 | H3: =BAU!J2 -> 2024 | I3: =BAU!K2 -> 2025 | ... AH3: =BAU!AJ2 -> 2050
A4: BAU - Efficiency | B4: =BAU!D462 -> 0.23372227 | C4: =BAU!E462 -> 0.2313423 | D4: =BAU!F462 -> 0.23395674 | E4: =BAU!G462 -> 0.23072952 | F4: =BAU!H462 -> 0.23030711 | G4: =BAU!I462 -> 0.21174579 | H4: =BAU!J462 -> 0.2115142 | I4: =BAU!K462 -> 0.21125553 | ... AH4: =BAU!AJ462 -> 0.20160665
A5: BAU - CO2 | B5: =BAU!D486 -> 55.747685 | C5: =BAU!E486 -> 57.423867 | D5: =BAU!F486 -> 53.229527 | E5: =BAU!G486 -> 53.97045 | F5: =BAU!H486 -> 53.905395 | G5: =BAU!I486 -> 53.051045 | H5: =BAU!J486 -> 51.413271 | I5: =BAU!K486 -> 50.449021 | ... AH5: =BAU!AJ486 -> 32.916611
A6: BAU - Final Energy Use | B6: =BAU!D72 -> 755634.98 | C6: =BAU!E72 -> 778696.11 | D6: =BAU!F72 -> 724009.39 | E6: =BAU!G72 -> 743241.04 | F6: =BAU!H72 -> 752302.28 | G6: =BAU!I72 -> 756420.01 | H6: =BAU!J72 -> 751641.24 | I6: =BAU!K72 -> 745209.07 | ... AH6: =BAU!AJ72 -> 604024.81
A7: BAU - GDP | B7: =BAU!D63 -> 194.6 | C7: =BAU!E63 -> 200 | D7: =BAU!F63 -> 183.6 | E7: =BAU!G63 -> 193.8 | F7: =BAU!H63 -> 207.3 | G7: =BAU!I63 -> 160.16875 | H7: =BAU!J63 -> 158.9828 | I7: =BAU!K63 -> 157.42954 | ... AH7: =BAU!AJ63 -> 121.77542
A8: BAU - Total Renewable GW | B8: =BAU!D16 -> 13.125 | C8: =BAU!E16 -> 13.455 | D8: =BAU!F16 -> 13.599 | E8: =BAU!G16 -> 14.544 | F8: =BAU!H16 -> 16.619 | G8: =BAU!I16 -> 17.84 | H8: =BAU!J16 -> 19.823 | I8: =BAU!K16 -> 20.436546 | ... AH8: =BAU!AJ16 -> 36.7502
A9: Share final exergy industry [-] | B9: =BAU!D74 -> 0.27119604 | C9: =BAU!E74 -> 0.2732505 | D9: =BAU!F74 -> 0.28555072 | E9: =BAU!G74 -> 0.28462773 | F9: =BAU!H74 -> 0.27572585 | G9: =BAU!I74 -> 0.25944504 | H9: =BAU!J74 -> 0.25617084 | I9: =BAU!K74 -> 0.25289663 | ... AH9: =BAU!AJ74 -> 0.17104153
A10: Share final exergy transport [-] | B10: =BAU!D75 -> 0.35679786 | C10: =BAU!E75 -> 0.36315882 | D10: =BAU!F75 -> 0.32899597 | E10: =BAU!G75 -> 0.34997126 | F10: =BAU!H75 -> 0.36009084 | G10: =BAU!I75 -> 0.372118 | H10: =BAU!J75 -> 0.37430883 | I10: =BAU!K75 -> 0.37649966 | ... AH10: =BAU!AJ75 -> 0.4312704
A11: Share final exergy services [-] | B11: =BAU!D76 -> 0.11418082 | C11: =BAU!E76 -> 0.11117733 | D11: =BAU!F76 -> 0.10630522 | E11: =BAU!G76 -> 0.10424487 | F11: =BAU!H76 -> 0.10934643 | G11: =BAU!I76 -> 0.15300365 | H11: =BAU!J76 -> 0.15238571 | I11: =BAU!K76 -> 0.15176778 | ... AH11: =BAU!AJ76 -> 0.13631935
A12: Share final exergy residencial [-] | B12: =BAU!D77 -> 0.15992742 | C12: =BAU!E77 -> 0.15925696 | D12: =BAU!F77 -> 0.17964943 | E12: =BAU!G77 -> 0.17499831 | F12: =BAU!H77 -> 0.16410964 | G12: =BAU!I77 -> 0.12335774 | H12: =BAU!J77 -> 0.12518344 | I12: =BAU!K77 -> 0.12700913 | ... AH12: =BAU!AJ77 -> 0.17265148
A13: Share Final Exergy Agriculture/forestry/Fishing [-] | B13: =BAU!D78 -> 0.028064646 | C13: =BAU!E78 -> 0.028618365 | D13: =BAU!F78 -> 0.032768238 | E13: =BAU!G78 -> 0.03372055 | F13: =BAU!H78 -> 0.029928558 | G13: =BAU!I78 -> 0.023282591 | H13: =BAU!J78 -> 0.022797523 | I13: =BAU!K78 -> 0.022312456 | ... AH13: =BAU!AJ78 -> 0.010185772
A14: Share Final Exergy Energy industry own use [-] | B14: =BAU!D79 -> 0.069833206 | C14: =BAU!E79 -> 0.06453802 | D14: =BAU!F79 -> 0.066730424 | E14: =BAU!G79 -> 0.05243729 | F14: =BAU!H79 -> 0.060798684 | G14: =BAU!I79 -> 0.068792975 | H14: =BAU!J79 -> 0.06915366 | I14: =BAU!K79 -> 0.069514345 | ... AH14: =BAU!AJ79 -> 0.078531474
A15: BAU - Capital/PIB | B15: =BAU!D52/BAU!D63 -> 2.7426768 | C15: =BAU!E52/BAU!E63 -> 2.6682585 | D15: =BAU!F52/BAU!F63 -> 2.8963437 | E15: =BAU!G52/BAU!G63 -> 2.7471914 | F15: =BAU!H52/BAU!H63 -> 2.5744809 | G15: =BAU!I52/BAU!I63 -> 3.3174371 | H15: =BAU!J52/BAU!J63 -> 3.2779238 | I15: =BAU!K52/BAU!K63 -> 3.2485037 | ... AH15: =BAU!AJ52/BAU!AJ63 -> 2.8524615
A19: Decarbonization Scenario
A20: Year | B20: =Decarbonizatio!D2 -> 2018 | C20: =Decarbonizatio!E2 -> 2019 | D20: =Decarbonizatio!F2 -> 2020 | E20: =Decarbonizatio!G2 -> 2021 | F20: =Decarbonizatio!H2 -> 2022 | G20: =Decarbonizatio!I2 -> 2023 | H20: =Decarbonizatio!J2 -> 2024 | I20: =Decarbonizatio!K2 -> 2025 | ... AH20: =Decarbonizatio!AJ2 -> 2050
A21: DEC - Efficiency | B21: =Decarbonizatio!D491 -> 0.23372225 | C21: =Decarbonizatio!E491 -> 0.2313423 | D21: =Decarbonizatio!F491 -> 0.23395675 | E21: =Decarbonizatio!G491 -> 0.23072952 | F21: =Decarbonizatio!H491 -> 0.23030712 | G21: =Decarbonizatio!I491 -> 0.24427204 | H21: =Decarbonizatio!J491 -> 0.2517459 | I21: =Decarbonizatio!K491 -> 0.25876146 | ... AH21: =Decarbonizatio!AJ491 -> 0.40638177
A22: DEC - CO2 emissions | B22: =Decarbonizatio!D540 -> 55.739714 | C22: =Decarbonizatio!E540 -> 57.387408 | D22: =Decarbonizatio!F540 -> 53.167261 | E22: =Decarbonizatio!G540 -> 53.901885 | F22: =Decarbonizatio!H540 -> 53.852066 | G22: =Decarbonizatio!I540 -> 58.525407 | H22: =Decarbonizatio!J540 -> 57.74333 | I22: =Decarbonizatio!K540 -> 57.390663 | ... AH22: =Decarbonizatio!AJ540 -> 14.808405
A23: DEC - Final Energy Use | B23: =Decarbonizatio!D74 -> 755634.98 | C23: =Decarbonizatio!E74 -> 778696.11 | D23: =Decarbonizatio!F74 -> 724009.39 | E23: =Decarbonizatio!G74 -> 743241.04 | F23: =Decarbonizatio!H74 -> 752302.28 | G23: =Decarbonizatio!I74 -> 824247.36 | H23: =Decarbonizatio!J74 -> 837885.34 | I23: =Decarbonizatio!K74 -> 850246.69 | ... AH23: =Decarbonizatio!AJ74 -> 1152169.7
A24: DEC - GDP | B24: =Decarbonizatio!D70 -> 194.6 | C24: =Decarbonizatio!E70 -> 200 | D24: =Decarbonizatio!F70 -> 183.6 | E24: =Decarbonizatio!G70 -> 193.8 | F24: =Decarbonizatio!H70 -> 207.3 | G24: =Decarbonizatio!I70 -> 201.34058 | H24: =Decarbonizatio!J70 -> 210.9342 | I24: =Decarbonizatio!K70 -> 220.01107 | ... AH24: =Decarbonizatio!AJ70 -> 468.22077
A25: DEC - Total Renewable GW | B25: =Decarbonizatio!D16 -> 13.125 | C25: =Decarbonizatio!E16 -> 13.455 | D25: =Decarbonizatio!F16 -> 13.599 | E25: =Decarbonizatio!G16 -> 14.544 | F25: =Decarbonizatio!H16 -> 16.619 | G25: =Decarbonizatio!I16 -> 17.852 | H25: =Decarbonizatio!J16 -> 19.848 | I25: =Decarbonizatio!K16 -> 20.83 | ... AH25: =Decarbonizatio!AJ16 -> 84.177
A26: Share final exergy industry [-] | B26: =Decarbonizatio!D76 -> 0.27119604 | C26: =Decarbonizatio!E76 -> 0.2732505 | D26: =Decarbonizatio!F76 -> 0.28555072 | E26: =Decarbonizatio!G76 -> 0.28462773 | F26: =Decarbonizatio!H76 -> 0.27572585 | G26: =Decarbonizatio!I76 -> 0.27588512 | H26: =Decarbonizatio!J76 -> 0.27604439 | I26: =Decarbonizatio!K76 -> 0.27620366 | ... AH26: =Decarbonizatio!AJ76 -> 0.385
A27: Share final exergy transport [-] | B27: =Decarbonizatio!D77 -> 0.35679786 | C27: =Decarbonizatio!E77 -> 0.36315882 | D27: =Decarbonizatio!F77 -> 0.32899597 | E27: =Decarbonizatio!G77 -> 0.34997126 | F27: =Decarbonizatio!H77 -> 0.36009084 | G27: =Decarbonizatio!I77 -> 0.35382948 | H27: =Decarbonizatio!J77 -> 0.34756813 | I27: =Decarbonizatio!K77 -> 0.34130677 | ... AH27: =Decarbonizatio!AJ77 -> 0.19
A28: Share final exergy services [-] | B28: =Decarbonizatio!D78 -> 0.11418082 | C28: =Decarbonizatio!E78 -> 0.11117733 | D28: =Decarbonizatio!F78 -> 0.10630522 | E28: =Decarbonizatio!G78 -> 0.10424487 | F28: =Decarbonizatio!H78 -> 0.10934643 | G28: =Decarbonizatio!I78 -> 0.11442812 | H28: =Decarbonizatio!J78 -> 0.11950982 | I28: =Decarbonizatio!K78 -> 0.12459152 | ... AH28: =Decarbonizatio!AJ78 -> 0.17
A29: Share final exergy residencial [-] | B29: =Decarbonizatio!D79 -> 0.15992742 | C29: =Decarbonizatio!E79 -> 0.15925696 | D29: =Decarbonizatio!F79 -> 0.17964943 | E29: =Decarbonizatio!G79 -> 0.17499831 | F29: =Decarbonizatio!H79 -> 0.16410964 | G29: =Decarbonizatio!I79 -> 0.16609594 | H29: =Decarbonizatio!J79 -> 0.16808223 | I29: =Decarbonizatio!K79 -> 0.17006853 | ... AH29: =Decarbonizatio!AJ79 -> 0.18
A30: Share Final Exergy Agriculture/forestry/Fishing [-] | B30: =Decarbonizatio!D80 -> 0.028064646 | C30: =Decarbonizatio!E80 -> 0.028618365 | D30: =Decarbonizatio!F80 -> 0.032768238 | E30: =Decarbonizatio!G80 -> 0.03372055 | F30: =Decarbonizatio!H80 -> 0.029928558 | G30: =Decarbonizatio!I80 -> 0.029937488 | H30: =Decarbonizatio!J80 -> 0.029946419 | I30: =Decarbonizatio!K80 -> 0.029955349 | ... AH30: =Decarbonizatio!AJ80 -> 0.03
A31: Share Final Exergy Energy industry own use [-] | B31: =Decarbonizatio!D81 -> 0.069833206 | C31: =Decarbonizatio!E81 -> 0.06453802 | D31: =Decarbonizatio!F81 -> 0.066730424 | E31: =Decarbonizatio!G81 -> 0.05243729 | F31: =Decarbonizatio!H81 -> 0.060798684 | G31: =Decarbonizatio!I81 -> 0.059823848 | H31: =Decarbonizatio!J81 -> 0.058849013 | I31: =Decarbonizatio!K81 -> 0.057874177 | ... AH31: =Decarbonizatio!AJ81 -> 0.045
A32: DEC - Capital/PIB | B32: =Decarbonizatio!D60/Decarbonizatio!D70 -> 2.7426768 | C32: =Decarbonizatio!E60/Decarbonizatio!E70 -> 2.6682585 | D32: =Decarbonizatio!F60/Decarbonizatio!F70 -> 2.8963437 | E32: =Decarbonizatio!G60/Decarbonizatio!G70 -> 2.7471914 | F32: =Decarbonizatio!H60/Decarbonizatio!H70 -> 2.5744809 | G32: =Decarbonizatio!I60/Decarbonizatio!I70 -> 2.6265171 | H32: =Decarbonizatio!J60/Decarbonizatio!J70 -> 2.4879722 | I32: =Decarbonizatio!K60/Decarbonizatio!K70 -> 2.3680194 | ... AH32: =Decarbonizatio!AJ60/Decarbonizatio!AJ70 -> 1.2935121
